Workbook

Sheet Sheet1
A1: =+INDEX('EMP NAMES'!D:D,Sheet1!U5) -> 0 | I1: =+IF(M25=M28,"OLD","NEW") -> OLD | U1: SR | V1: 115BAC Section Applicable (New Tax Regime) | W1: PAN NO. | X1: NAME OF EMPLOYEE | Y1: Salary as per provisions contained in section 17(1) | Z1: Value of perquisites [section 17(2)] (as per FormNo.12BA, wherever applicable) | AA1: Reported total amount of salary received from other employer(s) | AB1: GROSS SALARY | AC1: STD DED | AD1: PT | AE1: HRA | AF1: OTHER ALLOWANCES 10 | AG1: NET | AH1: HSG. INT | AI1: OTHER INCOME | AJ1: NET | AK1: 80C INVESTMENT | AL1: 80C ELIGIBLE | AM1: 80CCD1 GROSS | AN1: 80CCD1 ELIGIBLE | AO1: 80CCD1(B) ELIGIBLE | AP1: 80CCD2 ELIGIBLE | AQ1: 80D | AR1: 80E | AS1: 80G | AT1: OTHERS | AU1: TOTAL ELIGIBLE SAVING | AV1: TAXABLE | AW1: TAX | AX1: REBATE | AY1: CESS | AZ1: RELIEF | BA1: TOTAL TAX | BB1: TDS-CURRENT | BC1: TDS-PREV. | BD1: TOTAL | BE1: R/P
G2: =IFERROR(INDEX('EMP NAMES'!E:E,Sheet1!U5),"PAN") -> PAN
N3: M
A4: SR. | B4: MONTH | C4: BASIC | D4: DA | E4: H. R. A. | F4: TA/SDA/CLA/RA/ETC | G4: WA | H4: DCPS Employer | I4: Basic Arr. / 7th Pay DCPS/NPS Arr | J4: Total Emolument | K4: PT | L4: GPF/DCPS Employee | M4: GIS | N4: LIC | O4: HBA HOUSE | P4: OTHER | Q4: NET | R4: I. TAX | S4: GROSS TOTAL ERROR | U4: SR | V4: 115BAC Section Applicable (New Tax Regime) | W4: PAN NO. | X4: NAME OF EMPLOYEE | Y4: Salary as per provisions contained in section 17(1) | Z4: Value of perquisites [section 17(2)] (as per FormNo.12BA, wherever applicable) | AA4: Reported total amount of salary received from other employer(s) | AB4: GROSS SALARY | AC4: STD DED | AD4: PT | AE4: HRA | AF4: OTHER ALLOWANCES 10 | AG4: NET | AH4: HSG. INT | AI4: OTHER INCOME | AJ4: NET | AK4: 80C INVESTMENT | AL4: 80C ELIGIBLE | AM4: 80CCD1 GROSS | AN4: 80CCD1 ELIGIBLE | AO4: 80CCD1(B) ELIGIBLE | AP4: 80CCD2 ELIGIBLE | AQ4: 80D | AR4: 80E | AS4: 80G | AT4: OTHERS | AU4: TOTAL ELIGIBLE SAVING | AV4: TAXABLE | AW4: TAX | AX4: REBATE | AY4: CESS | AZ4: RELIEF | BA4: TOTAL TAX | BB4: TDS-CURRENT | BC4: TDS-PREV. | BD4: TOTAL | BE4: R/P
A5: 1 | B5: 44256 | C5: =IFERROR(SUM(SUMIF(OFFSET('MAR-21'!$A$1,MATCH(Sheet1!A1,'MAR-21'!$A:$A,0),0,22,1),{"BA*C","BASIC??"},OFFSET('MAR-21'!$A$1,MATCH(Sheet1!A1,'MAR-21'!$A:$A,0),1,22,1))),0) -> 0 | D5: =IFERROR(SUM(SUMIF(OFFSET('MAR-21'!$A$1,MATCH(Sheet1!A1,'MAR-21'!$A:$A,0),0,22,1),{"DA*C","D. *"},OFFSET('MAR-21'!$A$1,MATCH(Sheet1!A1,'MAR-21'!$A:$A,0),1,22,1))),0) -> 0 | E5: =IFERROR(SUM(SUMIF(OFFSET('MAR-21'!$A$1,MATCH(Sheet1!A1,'MAR-21'!$A:$A,0),0,22,1),{"H. R. A."},OFFSET('MAR-21'!$A$1,MATCH(Sheet1!A1,'MAR-21'!$A:$A,0),1,22,1))),0) -> 0 | F5: {=IFERROR(SUM(SUMIF(OFFSET('MAR-21'!$A$1,MATCH(Sheet1!A1,'MAR-21'!$A:$A,0),0,22,1),{"SP*AY*","S D A*","O.A.*","CLA (5th Pay)*","REF. Allow*","Trans.Allw.*","LF*","P. O.*","ARM*","Conv.A*","Otr.Allow*","Trans_Arrear*","BMIA*","Incentives*","Fit Allow*","KMA","NON-*","U.*","ME*A","PG*","Per.Tra"},OFFSET('MAR-21'!$A$1,MATCH(Sheet1!A1,'MAR-21'!$A:$A,0),1,22,1))),0)} -> 0 | G5: =IFERROR(SUM(SUMIF(OFFSET('MAR-21'!$A$1,MATCH(Sheet1!A1,'MAR-21'!$A:$A,0),0,22,1),{"WA"},OFFSET('MAR-21'!$A$1,MATCH(Sheet1!A1,'MAR-21'!$A:$A,0),1,22,1))),0) -> 0 | H5: =IFERROR(SUM(SUMIF(OFFSET('MAR-21'!$A$1,MATCH(Sheet1!A1,'MAR-21'!$A:$A,0),0,22,1),{"DCPS","GROSS_ADJUST"},OFFSET('MAR-21'!$A$1,MATCH(Sheet1!A1,'MAR-21'!$A:$A,0),1,22,1))),0) -> 0 | I5: {=+IFERROR(SUM(SUMIF(OFFSET('MAR-21'!$A$1,MATCH(Sheet1!A1,'MAR-21'!$A:$A,0),0,22,1),{"Basic*Arr*","7th Pay* Arr*"},OFFSET('MAR-21'!$A$1,MATCH(Sheet1!A1,'MAR-21'!$A:$A,0),1,22,1))),0)} -> 0 | J5: =+SUM(C5:I5) -> 0 | K5: =IFERROR(SUM(SUMIF(OFFSET('MAR-21'!$A$1,MATCH(Sheet1!A1,'MAR-21'!$A:$A,0),2,22,1),{"*Pro*ax*"},OFFSET('MAR-21'!$A$1,MATCH(Sheet1!A1,'MAR-21'!$A:$A,0),3,22,1))),0) -> 0 | L5: =IFERROR(SUM(SUMIF(OFFSET('MAR-21'!$A$1,MATCH(Sheet1!A1,'MAR-21'!$A:$A,0),2,22,1),{"GPF_G*","DCPS"},OFFSET('MAR-21'!$A$1,MATCH(Sheet1!A1,'MAR-21'!$A:$A,0),3,22,1))),0) -> 0 | M5: =IFERROR(SUM(SUMIF(OFFSET('MAR-21'!$A$1,MATCH(Sheet1!A1,'MAR-21'!$A:$A,0),2,22,1),{"*GIS","GIS*R"},OFFSET('MAR-21'!$A$1,MATCH(Sheet1!A1,'MAR-21'!$A:$A,0),3,22,1))),0) -> 0 | N5: =IFERROR(SUM(SUMIF(OFFSET('MAR-21'!$A$1,MATCH(Sheet1!A1,'MAR-21'!$A:$A,0),5,22,1),{"LI*1"},OFFSET('MAR-21'!$A$1,MATCH(Sheet1!A1,'MAR-21'!$A:$A,0),6,22,1))),0) -> 0 | O5: {=IFERROR(SUM(SUMIF(OFFSET('MAR-21'!$A$1,MATCH(Sheet1!A1,'MAR-21'!$A:$A,0),2,22,1),{"*HB*USE","HB*INT"},OFFSET('MAR-21'!$A$1,MATCH(Sheet1!A1,'MAR-21'!$A:$A,0),3,22,1))),0)} -> 0 | P5: {=IFERROR(SUM(SUMIF(OFFSET('MAR-21'!$A$1,MATCH(Sheet1!A1,'MAR-21'!$A:$A,0),5,22,1),{"OTHE*1","CO.*1","OTHE*2","WEL*ND","BAN*1","CLU*ND","RD*1","LI*2","MIS*US","*TAINAN*","MCA*INT*","MAIN*NANCE*","*C M Relief Fund*","Co. Op. Hsg Soc.*","GPF_ADV*","Co. Op. Cr. Soc. 2*","DCPS DA","DCPS Pay","MCA Int"},OFFSET('MAR-21'!$A$1,MATCH(Sheet1!A1,'MAR-21'!$A:$A,0),6,22,1)))+SUM(SUMIF(OFFSET('MAR-21'!$A$1,MATCH(Sheet1!A1,'MAR-21'!$A:$A,0),2,22,1),{"MCA","COM*DV*","HB*ND","CO*SOC","HRR","SRV*H","ACC*CY","F.A","STAMP_REVENUE","*C M Relief Fund*","GPF_ADV*","Co. Op. Cr. Soc. 2*","DCPS DA","DCPS Pay","MCA Int"},OFFSET('MAR-21'!$A$1,MATCH(Sheet1!A1,'MAR-21'!$A:$A,0),3,22,1))),0)} -> 0 | Q5: =+J5-H5-K5-L5-M5-N5-O5-P5-R5 -> 0 | R5: =IFERROR(SUM(SUMIF(OFFSET('MAR-21'!$A$1,MATCH(Sheet1!A1,'MAR-21'!$A:$A,0),2,22,1),{"*I.*ax*"},OFFSET('MAR-21'!$A$1,MATCH(Sheet1!A1,'MAR-21'!$A:$A,0),3,22,1))),0) -> 0 | S5: {=+IFERROR(IF(OFFSET('MAR-21'!$B$1,MATCH(Sheet1!A1,'MAR-21'!B:B,0)-2,0,1,1)=Sheet1!J5,IF(MID(IFERROR(OFFSET('MAR-21'!$B$1,MATCH(Sheet1!A1,'MAR-21'!$B:$B,0)-1,-1,1,1),"GROSS ERROR"),11,FIND(" ",OFFSET('MAR-21'!$B$1,MATCH(Sheet1!A1,'MAR-21'!$B:$B,0)-1,-1,1,1),12)-11)-Q5=0,"","NET MISMATCH"),"GROSS MISMATCH"),"")} | U5: 2 | V5: =+IF(M25=M28,"NO","YES") -> NO | W5: =+G2 -> PAN | X5: =+A1 -> 0 | Y5: =+D24 -> 0 | Z5: 0 | AA5: 0 | AB5: =+SUM(Y5:AA5) -> 0 | AC5: =+D26 -> 50000 | AD5: =+D28 -> 0 | AE5: =+D30 -> 0 | AF5: =+D29+D27+D31 -> 0 | AG5: =+AB5-SUM(AC5:AF5) -> -50000 | AH5: =+IF(D32>=200000,-200000,-D32) -> 0 | AI5: 0 | AJ5: =+AG5+AH5+AI5 -> -50000 | AK5: =+IF(H41>0,H36-H25,H36) -> 0 | AL5: {=+IF(IF(AND((AK5+AN5)>=150000,AK5>=150000),150000-AN5,AK5)<0,0,IF(AND((AK5+AN5)>=150000,AK5>=150000),150000-AN5,IF(AND(SUM(AK5+AN5)>150000,AK5<150000),150000-AN5,AK5)))} -> 0 | AM5: =+IF(H20>0,L20,0) -> 0 | AN5: =+AM5-AO5 -> 0 | AO5: =+IF(AND(H20>0,L20>50000),50000,IF(H20>0,L20,0)) -> 0 | AP5: =+H20 -> 0 | AQ5: =+H43 -> 0 | AR5: =+H45 -> 0 | AS5: =+H42 -> 0 | AT5: =+H44 -> 0 | AU5: =+SUM(AQ5:AT5)+AP5+AO5+AN5+AL5 -> 0 | AV5: =+AJ5-AU5 -> -50000 | AW5: =+M28 -> 0 | AX5: =+M30 -> 0 | AY5: =+M32 -> 0 | AZ5: =+M35 -> 0 | BA5: =+AW5-AX5+AY5-AZ5 -> 0 | BB5: =+M34 -> 0 | BC5: 0 | BD5: =+BB5+BC5 -> 0 | BE5: =+BA5-BD5 -> 0 | BF5: =+IF(AV5=M24,"","NOT OK") | BH5: =+G2 -> PAN | BI5: =+A1 -> 0 | BJ5: {=IFERROR(OFFSET('MAR-21'!$B$1,MATCH(Sheet1!A1,'MAR-21'!$B:$B,0)+1,0,1,1),"")} | BK5: =+J5 -> 0 | BL5: =+R5 -> 0 | BM5: {=IFERROR(OFFSET('MAR-21'!$A$1,MATCH(Sheet1!A1,'MAR-21'!$A:$A,0)-2,0,1,1),"")}
A6: 2 | B6: 44287 | C6: =IFERROR(SUM(SUMIF(OFFSET('APR-21'!$A$1,MATCH(Sheet1!A1,'APR-21'!$A:$A,0),0,22,1),{"BA*C","BASIC??"},OFFSET('APR-21'!$A$1,MATCH(Sheet1!A1,'APR-21'!$A:$A,0),1,22,1))),0) -> 0 | D6: =IFERROR(SUM(SUMIF(OFFSET('APR-21'!$A$1,MATCH(Sheet1!A1,'APR-21'!$A:$A,0),0,22,1),{"DA*C","D. *"},OFFSET('APR-21'!$A$1,MATCH(Sheet1!A1,'APR-21'!$A:$A,0),1,22,1))),0) -> 0 | E6: {=+IFERROR(SUM(SUMIF(OFFSET('APR-21'!$A$1,MATCH(Sheet1!A1,'APR-21'!$A:$A,0),0,22,1),{"H. R. A."},OFFSET('APR-21'!$A$1,MATCH(Sheet1!A1,'APR-21'!$A:$A,0),1,22,1))),0)} -> 0 | F6: =IFERROR(SUM(SUMIF(OFFSET('APR-21'!$A$1,MATCH(Sheet1!A1,'APR-21'!$A:$A,0),0,22,1),{"SP*AY*","S D A*","O.A.*","CLA (5th Pay)*","REF. Allow*","Trans.Allw.*","LF*","P. O.*","ARM*","Conv.A*","Otr.Allow*","Trans_Arrear*","BMIA*","Incentives*","Fit Allow*","KMA","NON-*","U.*","ME*A","PG*","Per.Tra"},OFFSET('APR-21'!$A$1,MATCH(Sheet1!A1,'APR-21'!$A:$A,0),1,22,1))),0) -> 0 | G6: =IFERROR(SUM(SUMIF(OFFSET('APR-21'!$A$1,MATCH(Sheet1!A1,'APR-21'!$A:$A,0),0,22,1),{"WA"},OFFSET('APR-21'!$A$1,MATCH(Sheet1!A1,'APR-21'!$A:$A,0),1,22,1))),0) -> 0 | H6: =IFERROR(SUM(SUMIF(OFFSET('APR-21'!$A$1,MATCH(Sheet1!A1,'APR-21'!$A:$A,0),0,22,1),{"DCPS","GROSS_ADJUST"},OFFSET('APR-21'!$A$1,MATCH(Sheet1!A1,'APR-21'!$A:$A,0),1,22,1))),0) -> 0 | I6: {=+IFERROR(SUM(SUMIF(OFFSET('APR-21'!$A$1,MATCH(Sheet1!A1,'APR-21'!$A:$A,0),0,22,1),{"Arr*","7th Pay* Arr*","Basic Arr."},OFFSET('APR-21'!$A$1,MATCH(Sheet1!A1,'APR-21'!$A:$A,0),1,22,1))),0)} -> 0 | J6: =SUM(C6:I6) -> 0 | K6: =IFERROR(SUM(SUMIF(OFFSET('APR-21'!$A$1,MATCH(Sheet1!A1,'APR-21'!$A:$A,0),2,22,1),{"*Pro*ax*"},OFFSET('APR-21'!$A$1,MATCH(Sheet1!A1,'APR-21'!$A:$A,0),3,22,1))),0) -> 0 | L6: =IFERROR(SUM(SUMIF(OFFSET('APR-21'!$A$1,MATCH(Sheet1!A1,'APR-21'!$A:$A,0),2,22,1),{"GPF_G*","DCPS"},OFFSET('APR-21'!$A$1,MATCH(Sheet1!A1,'APR-21'!$A:$A,0),3,22,1))),0) -> 0 | M6: =IFERROR(SUM(SUMIF(OFFSET('APR-21'!$A$1,MATCH(Sheet1!A1,'APR-21'!$A:$A,0),2,22,1),{"*GIS","GIS*R"},OFFSET('APR-21'!$A$1,MATCH(Sheet1!A1,'APR-21'!$A:$A,0),3,22,1))),0) -> 0 | N6: =IFERROR(SUM(SUMIF(OFFSET('APR-21'!$A$1,MATCH(Sheet1!A1,'APR-21'!$A:$A,0),5,22,1),{"LI*1"},OFFSET('APR-21'!$A$1,MATCH(Sheet1!A1,'APR-21'!$A:$A,0),6,22,1))),0) -> 0 | O6: {=IFERROR(SUM(SUMIF(OFFSET('APR-21'!$A$1,MATCH(Sheet1!A1,'APR-21'!$A:$A,0),2,22,1),{"HB*USE","HB*INT"},OFFSET('APR-21'!$A$1,MATCH(Sheet1!A1,'APR-21'!$A:$A,0),3,22,1))),0)} -> 0 | P6: {=IFERROR(SUM(SUMIF(OFFSET('APR-21'!$A$1,MATCH(Sheet1!A1,'APR-21'!$A:$A,0),5,22,1),{"OTHE*1","CO.*1","OTHE*2","WEL*ND","BAN*1","CLU*ND","RD*1","LI*2","MIS*US","*TAINAN*","MCA*INT*","MAIN*NANCE*","*C M Relief Fund*","Co. Op. Hsg Soc.*","GPF_ADV*","Co. Op. Cr. Soc. 2*","DCPS DA","DCPS Pay","MCA Int"},OFFSET('APR-21'!$A$1,MATCH(Sheet1!A1,'APR-21'!$A:$A,0),6,22,1)))+SUM(SUMIF(OFFSET('APR-21'!$A$1,MATCH(Sheet1!A1,'APR-21'!$A:$A,0),2,22,1),{"MCA","COM*DV*","HB*ND","CO*SOC","HRR","SRV*H","ACC*CY","F.A","STAMP_REVENUE","*C M Relief Fund*","GPF_ADV*","Co. Op. Cr. Soc. 2*","DCPS DA","DCPS Pay","MCA Int"},OFFSET('APR-21'!$A$1,MATCH(Sheet1!A1,'APR-21'!$A:$A,0),3,22,1))),0)} -> 0 | Q6: =+J6-H6-K6-L6-M6-N6-O6-P6-R6 -> 0 | R6: {=IFERROR(SUM(SUMIF(OFFSET('APR-21'!$A$1,MATCH(Sheet1!A1,'APR-21'!$A:$A,0),2,22,1),{"*I. *ax*"},OFFSET('APR-21'!$A$1,MATCH(Sheet1!A1,'APR-21'!$A:$A,0),3,22,1))),0)} -> 0 | S6: {=+IFERROR(IF(OFFSET('APR-21'!$B$1,MATCH(Sheet1!A1,'APR-21'!B:B,0)-2,0,1,1)=Sheet1!J6,IF(MID(IFERROR(OFFSET('APR-21'!$B$1,MATCH(Sheet1!A1,'APR-21'!$B:$B,0)-1,-1,1,1),"GROSS ERROR"),11,FIND(" ",OFFSET('APR-21'!$B$1,MATCH(Sheet1!A1,'APR-21'!$B:$B,0)-1,-1,1,1),12)-11)-Q6=0,"","NET MISMATCH"),"GROSS MISMATCH"),"")} | BH6: =+G2 -> PAN | BI6: =+A1 -> 0 | BJ6: {=IFERROR(OFFSET('APR-21'!$B$1,MATCH(Sheet1!A1,'APR-21'!$B:$B,0)+1,0,1,1),"")} | BK6: =+J6 -> 0 | BL6: =+R6 -> 0 | BM6: {=IFERROR(OFFSET('APR-21'!$A$1,MATCH(Sheet1!A1,'APR-21'!$A:$A,0)-2,0,1,1),"")}
A7: 3 | B7: 44317 | C7: =IFERROR(SUM(SUMIF(OFFSET('MAY-21'!$A$1,MATCH(Sheet1!A1,'MAY-21'!$A:$A,0),0,22,1),{"BA*C","BASIC??"},OFFSET('MAY-21'!$A$1,MATCH(Sheet1!A1,'MAY-21'!$A:$A,0),1,22,1))),0) -> 0 | D7: =IFERROR(SUM(SUMIF(OFFSET('MAY-21'!$A$1,MATCH(Sheet1!A1,'MAY-21'!$A:$A,0),0,22,1),{"DA*C","D. *"},OFFSET('MAY-21'!$A$1,MATCH(Sheet1!A1,'MAY-21'!$A:$A,0),1,22,1))),0) -> 0 | E7: =IFERROR(SUM(SUMIF(OFFSET('MAY-21'!$A$1,MATCH(Sheet1!A1,'MAY-21'!$A:$A,0),0,22,1),{"H. R. A."},OFFSET('MAY-21'!$A$1,MATCH(Sheet1!A1,'MAY-21'!$A:$A,0),1,22,1))),0) -> 0 | F7: {=IFERROR(SUM(SUMIF(OFFSET('MAY-21'!$A$1,MATCH(Sheet1!A1,'MAY-21'!$A:$A,0),0,22,1),{"SP*AY*","S D A*","O.A.*","CLA (5th Pay)*","REF. Allow*","Trans.Allw.*","LF*","P. O.*","ARM*","Conv.A*","Otr.Allow*","Trans_Arrear*","BMIA*","Incentives*","Fit Allow*","KMA","NON-*","U.*","ME*A","PG*","Per.Tra"},OFFSET('MAY-21'!$A$1,MATCH(Sheet1!A1,'MAY-21'!$A:$A,0),1,22,1))),0)} -> 0 | G7: =IFERROR(SUM(SUMIF(OFFSET('MAY-21'!$A$1,MATCH(Sheet1!A1,'MAY-21'!$A:$A,0),0,22,1),{"WA"},OFFSET('MAY-21'!$A$1,MATCH(Sheet1!A1,'MAY-21'!$A:$A,0),1,22,1))),0) -> 0 | H7: =IFERROR(SUM(SUMIF(OFFSET('MAY-21'!$A$1,MATCH(Sheet1!A1,'MAY-21'!$A:$A,0),0,22,1),{"DCPS","GROSS_ADJUST"},OFFSET('MAY-21'!$A$1,MATCH(Sheet1!A1,'MAY-21'!$A:$A,0),1,22,1))),0) -> 0 | I7: {=+IFERROR(SUM(SUMIF(OFFSET('MAY-21'!$A$1,MATCH(Sheet1!A1,'MAY-21'!$A:$A,0),0,22,1),{"Arr*","7th Pay* Arr*","Basic Arr.","DA Arr"},OFFSET('MAY-21'!$A$1,MATCH(Sheet1!A1,'MAY-21'!$A:$A,0),1,22,1))),0)} -> 0 | J7: =SUM(C7:I7) -> 0 | K7: =IFERROR(SUM(SUMIF(OFFSET('MAY-21'!$A$1,MATCH(Sheet1!A1,'MAY-21'!$A:$A,0),2,22,1),{"*Pro*ax*"},OFFSET('MAY-21'!$A$1,MATCH(Sheet1!A1,'MAY-21'!$A:$A,0),3,22,1))),0) -> 0 | L7: =IFERROR(SUM(SUMIF(OFFSET('MAY-21'!$A$1,MATCH(Sheet1!A1,'MAY-21'!$A:$A,0),2,22,1),{"GPF_G*","DCPS"},OFFSET('MAY-21'!$A$1,MATCH(Sheet1!A1,'MAY-21'!$A:$A,0),3,22,1))),0) -> 0 | M7: =IFERROR(SUM(SUMIF(OFFSET('MAY-21'!$A$1,MATCH(Sheet1!A1,'MAY-21'!$A:$A,0),2,22,1),{"*GIS","GIS*R"},OFFSET('MAY-21'!$A$1,MATCH(Sheet1!A1,'MAY-21'!$A:$A,0),3,22,1))),0) -> 0 | N7: =IFERROR(SUM(SUMIF(OFFSET('MAY-21'!$A$1,MATCH(Sheet1!A1,'MAY-21'!$A:$A,0),5,22,1),{"LI*1"},OFFSET('MAY-21'!$A$1,MATCH(Sheet1!A1,'MAY-21'!$A:$A,0),6,22,1))),0) -> 0 | O7: {=IFERROR(SUM(SUMIF(OFFSET('MAY-21'!$A$1,MATCH(Sheet1!A1,'MAY-21'!$A:$A,0),2,22,1),{"HB*USE","HB*INT"},OFFSET('MAY-21'!$A$1,MATCH(Sheet1!A1,'MAY-21'!$A:$A,0),3,22,1))),0)} -> 0 | P7: {=IFERROR(SUM(SUMIF(OFFSET('MAY-21'!$A$1,MATCH(Sheet1!A1,'MAY-21'!$A:$A,0),5,22,1),{"OTHE*1","CO.*1","OTHE*2","WEL*ND","BAN*1","CLU*ND","RD*1","LI*2","MIS*US","*TAINAN*","MCA*INT*","MAIN*NANCE*","*C M Relief Fund*","Co. Op. Hsg Soc.*","GPF_ADV*","Co. Op. Cr. Soc. 2*","DCPS DA","DCPS Pay","MCA Int"},OFFSET('MAY-21'!$A$1,MATCH(Sheet1!A1,'MAY-21'!$A:$A,0),6,22,1)))+SUM(SUMIF(OFFSET('MAY-21'!$A$1,MATCH(Sheet1!A1,'MAY-21'!$A:$A,0),2,22,1),{"MCA","COM*DV*","HB*ND","CO*SOC","HRR","SRV*H","ACC*CY","F.A","STAMP_REVENUE","*C M Relief Fund*","GPF_ADV*","Co. Op. Cr. Soc. 2*","DCPS DA","DCPS Pay","MCA Int"},OFFSET('MAY-21'!$A$1,MATCH(Sheet1!A1,'MAY-21'!$A:$A,0),3,22,1))),0)} -> 0 | Q7: =+J7-H7-K7-L7-M7-N7-O7-P7-R7 -> 0 | R7: =IFERROR(SUM(SUMIF(OFFSET('MAY-21'!$A$1,MATCH(Sheet1!A1,'MAY-21'!$A:$A,0),2,22,1),{"*I. *ax*"},OFFSET('MAY-21'!$A$1,MATCH(Sheet1!A1,'MAY-21'!$A:$A,0),3,22,1))),0) -> 0 | S7: {=+IFERROR(IF(OFFSET('MAY-21'!$B$1,MATCH(Sheet1!A1,'MAY-21'!B:B,0)-2,0,1,1)=Sheet1!J7,IF(MID(IFERROR(OFFSET('MAY-21'!$B$1,MATCH(Sheet1!A1,'MAY-21'!$B:$B,0)-1,-1,1,1),"GROSS ERROR"),11,FIND(" ",OFFSET('MAY-21'!$B$1,MATCH(Sheet1!A1,'MAY-21'!$B:$B,0)-1,-1,1,1),12)-11)-Q7=0,"","NET MISMATCH"),"GROSS MISMATCH"),"")} | BH7: =+G2 -> PAN | BI7: =+A1 -> 0 | BJ7: {=IFERROR(OFFSET('MAY-21'!$B$1,MATCH(Sheet1!A1,'MAY-21'!$B:$B,0)+1,0,1,1),"")} | BK7: =+J7 -> 0 | BL7: =+R7 -> 0 | BM7: {=+IFERROR(OFFSET('MAY-21'!$A$1,MATCH(Sheet1!A1,'MAY-21'!$A:$A,0)-2,0,1,1),"")}
A8: 4 | B8: 44348 | C8: =IFERROR(SUM(SUMIF(OFFSET('JUN-21'!$A$1,MATCH(Sheet1!A1,'JUN-21'!$A:$A,0),0,22,1),{"BA*C","BASIC??"},OFFSET('JUN-21'!$A$1,MATCH(Sheet1!A1,'JUN-21'!$A:$A,0),1,22,1))),0) -> 0 | D8: =IFERROR(SUM(SUMIF(OFFSET('JUN-21'!$A$1,MATCH(Sheet1!A1,'JUN-21'!$A:$A,0),0,22,1),{"DA*C","D. *"},OFFSET('JUN-21'!$A$1,MATCH(Sheet1!A1,'JUN-21'!$A:$A,0),1,22,1))),0) -> 0 | E8: =IFERROR(SUM(SUMIF(OFFSET('JUN-21'!$A$1,MATCH(Sheet1!A1,'JUN-21'!$A:$A,0),0,22,1),{"H. R. A."},OFFSET('JUN-21'!$A$1,MATCH(Sheet1!A1,'JUN-21'!$A:$A,0),1,22,1))),0) -> 0 | F8: {=IFERROR(SUM(SUMIF(OFFSET('JUN-21'!$A$1,MATCH(Sheet1!A1,'JUN-21'!$A:$A,0),0,22,1),{"SP*AY*","S D A*","O.A.*","CLA (5th Pay)*","REF. Allow*","Trans.Allw.*","LF*","P. O.*","ARM*","Conv.A*","Otr.Allow*","Trans_Arrear*","BMIA*","Incentives*","Fit Allow*","KMA","NON-*","U.*","ME*A","PG*","Per.Tra"},OFFSET('JUN-21'!$A$1,MATCH(Sheet1!A1,'JUN-21'!$A:$A,0),1,22,1))),0)} -> 0 | G8: =IFERROR(SUM(SUMIF(OFFSET('JUN-21'!$A$1,MATCH(Sheet1!A1,'JUN-21'!$A:$A,0),0,22,1),{"WA"},OFFSET('JUN-21'!$A$1,MATCH(Sheet1!A1,'JUN-21'!$A:$A,0),1,22,1))),0) -> 0 | H8: =IFERROR(SUM(SUMIF(OFFSET('JUN-21'!$A$1,MATCH(Sheet1!A1,'JUN-21'!$A:$A,0),0,22,1),{"DCPS","GROSS_ADJUST"},OFFSET('JUN-21'!$A$1,MATCH(Sheet1!A1,'JUN-21'!$A:$A,0),1,22,1))),0) -> 0 | I8: {=+IFERROR(SUM(SUMIF(OFFSET('JUN-21'!$A$1,MATCH(Sheet1!A1,'JUN-21'!$A:$A,0),0,22,1),{"Basic*Arr*","7th Pay* Arr*"},OFFSET('JUN-21'!$A$1,MATCH(Sheet1!A1,'JUN-21'!$A:$A,0),1,22,1))),0)} -> 0 | J8: =SUM(C8:I8) -> 0 | K8: =IFERROR(SUM(SUMIF(OFFSET('JUN-21'!$A$1,MATCH(Sheet1!A1,'JUN-21'!$A:$A,0),2,22,1),{"*Pro*ax*"},OFFSET('JUN-21'!$A$1,MATCH(Sheet1!A1,'JUN-21'!$A:$A,0),3,22,1))),0) -> 0 | L8: =IFERROR(SUM(SUMIF(OFFSET('JUN-21'!$A$1,MATCH(Sheet1!A1,'JUN-21'!$A:$A,0),2,22,1),{"GPF_G*","DCPS"},OFFSET('JUN-21'!$A$1,MATCH(Sheet1!A1,'JUN-21'!$A:$A,0),3,22,1))),0) -> 0 | M8: =IFERROR(SUM(SUMIF(OFFSET('JUN-21'!$A$1,MATCH(Sheet1!A1,'JUN-21'!$A:$A,0),2,22,1),{"*GIS","GIS*R"},OFFSET('JUN-21'!$A$1,MATCH(Sheet1!A1,'JUN-21'!$A:$A,0),3,22,1))),0) -> 0 | N8: =IFERROR(SUM(SUMIF(OFFSET('JUN-21'!$A$1,MATCH(Sheet1!A1,'JUN-21'!$A:$A,0),5,22,1),{"LI*1"},OFFSET('JUN-21'!$A$1,MATCH(Sheet1!A1,'JUN-21'!$A:$A,0),6,22,1))),0) -> 0 | O8: {=IFERROR(SUM(SUMIF(OFFSET('JUN-21'!$A$1,MATCH(Sheet1!A1,'JUN-21'!$A:$A,0),2,22,1),{"HB*USE","HB*INT"},OFFSET('JUN-21'!$A$1,MATCH(Sheet1!A1,'JUN-21'!$A:$A,0),3,22,1))),0)} -> 0 | P8: {=IFERROR(SUM(SUMIF(OFFSET('JUN-21'!$A$1,MATCH(Sheet1!A1,'JUN-21'!$A:$A,0),5,22,1),{"OTHE*1","CO.*1","OTHE*2","WEL*ND","BAN*1","CLU*ND","RD*1","LI*2","MIS*US","*TAINAN*","MCA*INT*","MAIN*NANCE*","*C M Relief Fund*","Co. Op. Hsg Soc.*","GPF_ADV*","Co. Op. Cr. Soc. 2*","DCPS DA","DCPS Pay","MCA Int"},OFFSET('JUN-21'!$A$1,MATCH(Sheet1!A1,'JUN-21'!$A:$A,0),6,22,1)))+SUM(SUMIF(OFFSET('JUN-21'!$A$1,MATCH(Sheet1!A1,'JUN-21'!$A:$A,0),2,22,1),{"MCA","COM*DV*","HB*ND","CO*SOC","HRR","SRV*H","ACC*CY","F.A","STAMP_REVENUE","*C M Relief Fund*","GPF_ADV*","Co. Op. Cr. Soc. 2*","DCPS DA","DCPS Pay","MCA Int"},OFFSET('JUN-21'!$A$1,MATCH(Sheet1!A1,'JUN-21'!$A:$A,0),3,22,1))),0)} -> 0 | Q8: =+J8-H8-K8-L8-M8-N8-O8-P8-R8 -> 0 | R8: {=IFERROR(SUM(SUMIF(OFFSET('JUN-21'!$A$1,MATCH(Sheet1!A1,'JUN-21'!$A:$A,0),2,22,1),{"*I. *ax*"},OFFSET('JUN-21'!$A$1,MATCH(Sheet1!A1,'JUN-21'!$A:$A,0),3,22,1))),0)} -> 0 | S8: {=+IFERROR(IF(OFFSET('JUN-21'!$B$1,MATCH(Sheet1!A1,'JUN-21'!B:B,0)-2,0,1,1)=Sheet1!J8,IF(MID(IFERROR(OFFSET('JUN-21'!$B$1,MATCH(Sheet1!A1,'JUN-21'!$B:$B,0)-1,-1,1,1),"GROSS ERROR"),11,FIND(" ",OFFSET('JUN-21'!$B$1,MATCH(Sheet1!A1,'JUN-21'!$B:$B,0)-1,-1,1,1),12)-11)-Q8=0,"","NET MISMATCH"),"GROSS MISMATCH"),"")} | BH8: =+G2 -> PAN | BI8: =+A1 -> 0 | BJ8: {=IFERROR(OFFSET('JUN-21'!$B$1,MATCH(Sheet1!A1,'JUN-21'!$B:$B,0)+1,0,1,1),"")} | BK8: =+J8 -> 0 | BL8: =+R8 -> 0 | BM8: {=IFERROR(OFFSET('JUN-21'!$A$1,MATCH(Sheet1!A1,'JUN-21'!$A:$A,0)-2,0,1,1),"")}
A9: 5 | B9: 44378 | C9: =IFERROR(SUM(SUMIF(OFFSET('JUL-21'!$A$1,MATCH(Sheet1!A1,'JUL-21'!$A:$A,0),0,22,1),{"BA*C","BASIC??"},OFFSET('JUL-21'!$A$1,MATCH(Sheet1!A1,'JUL-21'!$A:$A,0),1,22,1))),0) -> 0 | D9: =IFERROR(SUM(SUMIF(OFFSET('JUL-21'!$A$1,MATCH(Sheet1!A1,'JUL-21'!$A:$A,0),0,22,1),{"DA*C","D. *"},OFFSET('JUL-21'!$A$1,MATCH(Sheet1!A1,'JUL-21'!$A:$A,0),1,22,1))),0) -> 0 | E9: =IFERROR(SUM(SUMIF(OFFSET('JUL-21'!$A$1,MATCH(Sheet1!A1,'JUL-21'!$A:$A,0),0,22,1),{"H. R. A."},OFFSET('JUL-21'!$A$1,MATCH(Sheet1!A1,'JUL-21'!$A:$A,0),1,22,1))),0) -> 0 | F9: {=IFERROR(SUM(SUMIF(OFFSET('JUL-21'!$A$1,MATCH(Sheet1!A1,'JUL-21'!$A:$A,0),0,22,1),{"SP*AY*","S D A*","O.A.*","CLA (5th Pay)*","REF. Allow*","Trans.Allw.*","LF*","P. O.*","ARM*","Conv.A*","Otr.Allow*","Trans_Arrear*","BMIA*","Incentives*","Fit Allow*","KMA","NON-*","U.*","ME*A","PG*","Per.Tra"},OFFSET('JUL-21'!$A$1,MATCH(Sheet1!A1,'JUL-21'!$A:$A,0),1,22,1))),0)} -> 0 | G9: =IFERROR(SUM(SUMIF(OFFSET('JUL-21'!$A$1,MATCH(Sheet1!A1,'JUL-21'!$A:$A,0),0,22,1),{"WA"},OFFSET('JUL-21'!$A$1,MATCH(Sheet1!A1,'JUL-21'!$A:$A,0),1,22,1))),0) -> 0 | H9: {=+IFERROR(SUM(SUMIF(OFFSET('JUL-21'!$A$1,MATCH(Sheet1!A1,'JUL-21'!$A:$A,0),0,22,1),{"DCPS","GROSS_ADJUST"},OFFSET('JUL-21'!$A$1,MATCH(Sheet1!A1,'JUL-21'!$A:$A,0),1,22,1))),0)} -> 0 | I9: {=++IFERROR(SUM(SUMIF(OFFSET('JUL-21'!$A$1,MATCH(Sheet1!A1,'JUL-21'!$A:$A,0),0,22,1),{"Basic*Arr*","7th Pay* Arr*"},OFFSET('JUL-21'!$A$1,MATCH(Sheet1!A1,'JUL-21'!$A:$A,0),1,22,1))),0)} -> 0 | J9: =SUM(C9:I9) -> 0 | K9: =IFERROR(SUM(SUMIF(OFFSET('JUL-21'!$A$1,MATCH(Sheet1!A1,'JUL-21'!$A:$A,0),2,22,1),{"*Pro*ax*"},OFFSET('JUL-21'!$A$1,MATCH(Sheet1!A1,'JUL-21'!$A:$A,0),3,22,1))),0) -> 0 | L9: =IFERROR(SUM(SUMIF(OFFSET('JUL-21'!$A$1,MATCH(Sheet1!A1,'JUL-21'!$A:$A,0),2,22,1),{"GPF_G*","DCPS"},OFFSET('JUL-21'!$A$1,MATCH(Sheet1!A1,'JUL-21'!$A:$A,0),3,22,1))),0) -> 0 | M9: =IFERROR(SUM(SUMIF(OFFSET('JUL-21'!$A$1,MATCH(Sheet1!A1,'JUL-21'!$A:$A,0),2,22,1),{"*GIS","GIS*R"},OFFSET('JUL-21'!$A$1,MATCH(Sheet1!A1,'JUL-21'!$A:$A,0),3,22,1))),0) -> 0 | N9: =IFERROR(SUM(SUMIF(OFFSET('JUL-21'!$A$1,MATCH(Sheet1!A1,'JUL-21'!$A:$A,0),5,22,1),{"LI*1"},OFFSET('JUL-21'!$A$1,MATCH(Sheet1!A1,'JUL-21'!$A:$A,0),6,22,1))),0) -> 0 | O9: {=IFERROR(SUM(SUMIF(OFFSET('JUL-21'!$A$1,MATCH(Sheet1!A1,'JUL-21'!$A:$A,0),2,22,1),{"HB*USE","HB*INT"},OFFSET('JUL-21'!$A$1,MATCH(Sheet1!A1,'JUL-21'!$A:$A,0),3,22,1))),0)} -> 0 | P9: {=IFERROR(SUM(SUMIF(OFFSET('JUL-21'!$A$1,MATCH(Sheet1!A1,'JUL-21'!$A:$A,0),5,22,1),{"OTHE*1","CO.*1","OTHE*2","WEL*ND","BAN*1","CLU*ND","RD*1","LI*2","MIS*US","*TAINAN*","MCA*INT*","MAIN*NANCE*","*C M Relief Fund*","Co. Op. Hsg Soc.*","GPF_ADV*","Co. Op. Cr. Soc. 2*","DCPS DA","DCPS Pay","MCA Int"},OFFSET('JUL-21'!$A$1,MATCH(Sheet1!A1,'JUL-21'!$A:$A,0),6,22,1)))+SUM(SUMIF(OFFSET('JUL-21'!$A$1,MATCH(Sheet1!A1,'JUL-21'!$A:$A,0),2,22,1),{"MCA","COM*DV*","HB*ND","CO*SOC","HRR","SRV*H","ACC*CY","F.A","STAMP_REVENUE","*C M Relief Fund*","GPF_ADV*","Co. Op. Cr. Soc. 2*","DCPS DA","DCPS Pay","MCA Int"},OFFSET('JUL-21'!$A$1,MATCH(Sheet1!A1,'JUL-21'!$A:$A,0),3,22,1))),0)} -> 0 | Q9: =+J9-H9-K9-L9-M9-N9-O9-P9-R9 -> 0 | R9: =IFERROR(SUM(SUMIF(OFFSET('JUL-21'!$A$1,MATCH(Sheet1!A1,'JUL-21'!$A:$A,0),2,22,1),{"*I. *ax*"},OFFSET('JUL-21'!$A$1,MATCH(Sheet1!A1,'JUL-21'!$A:$A,0),3,22,1))),0) -> 0 | S9: {=+IFERROR(IF(OFFSET('JUL-21'!$B$1,MATCH(Sheet1!A1,'JUL-21'!B:B,0)-2,0,1,1)=Sheet1!J9,IF(MID(IFERROR(OFFSET('JUL-21'!$B$1,MATCH(Sheet1!A1,'JUL-21'!$B:$B,0)-1,-1,1,1),"GROSS ERROR"),11,FIND(" ",OFFSET('JUL-21'!$B$1,MATCH(Sheet1!A1,'JUL-21'!$B:$B,0)-1,-1,1,1),12)-11)-Q9=0,"","NET MISMATCH"),"GROSS MISMATCH"),"")} | BH9: =+G2 -> PAN | BI9: =+A1 -> 0 | BJ9: {=+IFERROR(OFFSET('JUL-21'!$B$1,MATCH(Sheet1!A1,'JUL-21'!$B:$B,0)+1,0,1,1),"")} | BK9: =+J9 -> 0 | BL9: =+R9 -> 0 | BM9: {=IFERROR(OFFSET('JUL-21'!$A$1,MATCH(Sheet1!A1,'JUL-21'!$A:$A,0)-2,0,1,1),"")}
A10: 6 | B10: 44409 | C10: =IFERROR(SUM(SUMIF(OFFSET('AUG-21'!$A$1,MATCH(Sheet1!A1,'AUG-21'!$A:$A,0),0,22,1),{"BA*C","BASIC??"},OFFSET('AUG-21'!$A$1,MATCH(Sheet1!A1,'AUG-21'!$A:$A,0),1,22,1))),0) -> 0 | D10: =IFERROR(SUM(SUMIF(OFFSET('AUG-21'!$A$1,MATCH(Sheet1!A1,'AUG-21'!$A:$A,0),0,22,1),{"DA*C","D. *"},OFFSET('AUG-21'!$A$1,MATCH(Sheet1!A1,'AUG-21'!$A:$A,0),1,22,1))),0) -> 0 | E10: =IFERROR(SUM(SUMIF(OFFSET('AUG-21'!$A$1,MATCH(Sheet1!A1,'AUG-21'!$A:$A,0),0,22,1),{"H. R. A."},OFFSET('AUG-21'!$A$1,MATCH(Sheet1!A1,'AUG-21'!$A:$A,0),1,22,1))),0) -> 0 | F10: {=IFERROR(SUM(SUMIF(OFFSET('AUG-21'!$A$1,MATCH(Sheet1!A1,'AUG-21'!$A:$A,0),0,22,1),{"SP*AY*","S D A*","O.A.*","CLA (5th Pay)*","REF. Allow*","Trans.Allw.*","LF*","P. O.*","ARM*","Conv.A*","Otr.Allow*","Trans_Arrear*","BMIA*","Incentives*","Fit Allow*","KMA","NON-*","U.*","ME*A","PG*","Per.Tra"},OFFSET('AUG-21'!$A$1,MATCH(Sheet1!A1,'AUG-21'!$A:$A,0),1,22,1))),0)} -> 0 | G10: =IFERROR(SUM(SUMIF(OFFSET('AUG-21'!$A$1,MATCH(Sheet1!A1,'AUG-21'!$A:$A,0),0,22,1),{"WA"},OFFSET('AUG-21'!$A$1,MATCH(Sheet1!A1,'AUG-21'!$A:$A,0),1,22,1))),0) -> 0 | H10: =IFERROR(SUM(SUMIF(OFFSET('AUG-21'!$A$1,MATCH(Sheet1!A1,'AUG-21'!$A:$A,0),0,22,1),{"DCPS","GROSS_ADJUST"},OFFSET('AUG-21'!$A$1,MATCH(Sheet1!A1,'AUG-21'!$A:$A,0),1,22,1))),0) -> 0 | I10: {=+IFERROR(SUM(SUMIF(OFFSET('AUG-21'!$A$1,MATCH(Sheet1!A1,'AUG-21'!$A:$A,0),0,22,1),{"7th Pay* Arr*","Basic Arr*","DA Arr"},OFFSET('AUG-21'!$A$1,MATCH(Sheet1!A1,'AUG-21'!$A:$A,0),1,22,1))),0)} -> 0 | J10: =SUM(C10:I10) -> 0 | K10: =IFERROR(SUM(SUMIF(OFFSET('AUG-21'!$A$1,MATCH(Sheet1!A1,'AUG-21'!$A:$A,0),2,22,1),{"*Pro*ax*"},OFFSET('AUG-21'!$A$1,MATCH(Sheet1!A1,'AUG-21'!$A:$A,0),3,22,1))),0) -> 0 | L10: =IFERROR(SUM(SUMIF(OFFSET('AUG-21'!$A$1,MATCH(Sheet1!A1,'AUG-21'!$A:$A,0),2,22,1),{"GPF_G*","DCPS","*7thPay GP*"},OFFSET('AUG-21'!$A$1,MATCH(Sheet1!A1,'AUG-21'!$A:$A,0),3,22,1))),0) -> 0 | M10: =IFERROR(SUM(SUMIF(OFFSET('AUG-21'!$A$1,MATCH(Sheet1!A1,'AUG-21'!$A:$A,0),2,22,1),{"*GIS","GIS*R"},OFFSET('AUG-21'!$A$1,MATCH(Sheet1!A1,'AUG-21'!$A:$A,0),3,22,1))),0) -> 0 | N10: =IFERROR(SUM(SUMIF(OFFSET('AUG-21'!$A$1,MATCH(Sheet1!A1,'AUG-21'!$A:$A,0),5,22,1),{"LI*1"},OFFSET('AUG-21'!$A$1,MATCH(Sheet1!A1,'AUG-21'!$A:$A,0),6,22,1))),0) -> 0 | O10: {=IFERROR(SUM(SUMIF(OFFSET('AUG-21'!$A$1,MATCH(Sheet1!A1,'AUG-21'!$A:$A,0),2,22,1),{"HB*USE","HB*INT"},OFFSET('AUG-21'!$A$1,MATCH(Sheet1!A1,'AUG-21'!$A:$A,0),3,22,1))),0)} -> 0 | P10: {=IFERROR(SUM(SUMIF(OFFSET('AUG-21'!$A$1,MATCH(Sheet1!A1,'AUG-21'!$A:$A,0),5,22,1),{"OTHE*1","CO.*1","OTHE*2","WEL*ND","BAN*1","CLU*ND","RD*1","LI*2","MIS*US","*TAINAN*","MCA*INT*","MAIN*NANCE*","*C M Relief Fund*","Co. Op. Hsg Soc.*","GPF_ADV*","Co. Op. Cr. Soc. 2*","DCPS DA","DCPS Pay","MCA Int"},OFFSET('AUG-21'!$A$1,MATCH(Sheet1!A1,'AUG-21'!$A:$A,0),6,22,1)))+SUM(SUMIF(OFFSET('AUG-21'!$A$1,MATCH(Sheet1!A1,'AUG-21'!$A:$A,0),2,22,1),{"MCA","COM*DV*","HB*ND","CO*SOC","HRR","SRV*H","ACC*CY","F.A","STAMP_REVENUE","*C M Relief Fund*","GPF_ADV*","Co. Op. Cr. Soc. 2*","DCPS DA","DCPS Pay","MCA Int"},OFFSET('AUG-21'!$A$1,MATCH(Sheet1!A1,'AUG-21'!$A:$A,0),3,22,1))),0)} -> 0 | Q10: =+J10-H10-K10-L10-M10-N10-O10-P10-R10 -> 0 | R10: {=IFERROR(SUM(SUMIF(OFFSET('AUG-21'!$A$1,MATCH(Sheet1!A1,'AUG-21'!$A:$A,0),2,22,1),{"*I. *ax*"},OFFSET('AUG-21'!$A$1,MATCH(Sheet1!A1,'AUG-21'!$A:$A,0),3,22,1))),0)} -> 0 | S10: {=+IFERROR(IF(OFFSET('AUG-21'!$B$1,MATCH(Sheet1!A1,'AUG-21'!B:B,0)-2,0,1,1)=Sheet1!J10,IF(MID(IFERROR(OFFSET('AUG-21'!$B$1,MATCH(Sheet1!A1,'AUG-21'!$B:$B,0)-1,-1,1,1),"GROSS ERROR"),11,FIND(" ",OFFSET('AUG-21'!$B$1,MATCH(Sheet1!A1,'AUG-21'!$B:$B,0)-1,-1,1,1),12)-11)-Q10=0,"","NET MISMATCH"),"GROSS MISMATCH"),"")} | BH10: =+G2 -> PAN | BI10: =+A1 -> 0 | BJ10: {=IFERROR(OFFSET('AUG-21'!$B$1,MATCH(Sheet1!A1,'AUG-21'!$B:$B,0)+1,0,1,1),"")} | BK10: =+J10 -> 0 | BL10: =+R10 -> 0 | BM10: {=IFERROR(OFFSET('AUG-21'!$A$1,MATCH(Sheet1!A1,'AUG-21'!$A:$A,0)-2,0,1,1),"")}
A11: 7 | B11: 44440 | C11: =IFERROR(SUM(SUMIF(OFFSET('SEP-21'!$A$1,MATCH(Sheet1!A1,'SEP-21'!$A:$A,0),0,22,1),{"BA*C","BASIC??"},OFFSET('SEP-21'!$A$1,MATCH(Sheet1!A1,'SEP-21'!$A:$A,0),1,22,1))),0) -> 0 | D11: =IFERROR(SUM(SUMIF(OFFSET('SEP-21'!$A$1,MATCH(Sheet1!A1,'SEP-21'!$A:$A,0),0,22,1),{"DA*C","D. *"},OFFSET('SEP-21'!$A$1,MATCH(Sheet1!A1,'SEP-21'!$A:$A,0),1,22,1))),0) -> 0 | E11: =IFERROR(SUM(SUMIF(OFFSET('SEP-21'!$A$1,MATCH(Sheet1!A1,'SEP-21'!$A:$A,0),0,22,1),{"H. R. A."},OFFSET('SEP-21'!$A$1,MATCH(Sheet1!A1,'SEP-21'!$A:$A,0),1,22,1))),0) -> 0 | F11: {=IFERROR(SUM(SUMIF(OFFSET('SEP-21'!$A$1,MATCH(Sheet1!A1,'SEP-21'!$A:$A,0),0,22,1),{"SP*AY*","S D A*","O.A.*","CLA (5th Pay)*","REF. Allow*","Trans.Allw.*","LF*","P. O.*","ARM*","Conv.A*","Otr.Allow*","Trans_Arrear*","BMIA*","Incentives*","Fit Allow*","KMA","NON-*","U.*","ME*A","PG*","Per.Tra"},OFFSET('SEP-21'!$A$1,MATCH(Sheet1!A1,'SEP-21'!$A:$A,0),1,22,1))),0)} -> 0 | G11: =IFERROR(SUM(SUMIF(OFFSET('SEP-21'!$A$1,MATCH(Sheet1!A1,'SEP-21'!$A:$A,0),0,22,1),{"WA"},OFFSET('SEP-21'!$A$1,MATCH(Sheet1!A1,'SEP-21'!$A:$A,0),1,22,1))),0) -> 0 | H11: =IFERROR(SUM(SUMIF(OFFSET('SEP-21'!$A$1,MATCH(Sheet1!A1,'SEP-21'!$A:$A,0),0,22,1),{"DCPS","GROSS_ADJUST"},OFFSET('SEP-21'!$A$1,MATCH(Sheet1!A1,'SEP-21'!$A:$A,0),1,22,1))),0) -> 0 | I11: {=++IFERROR(SUM(SUMIF(OFFSET('SEP-21'!$A$1,MATCH(Sheet1!A1,'SEP-21'!$A:$A,0),0,22,1),{"Basic*Arr*","7th Pay* Arr*"},OFFSET('SEP-21'!$A$1,MATCH(Sheet1!A1,'SEP-21'!$A:$A,0),1,22,1))),0)} -> 0 | J11: =SUM(C11:I11) -> 0 | K11: =IFERROR(SUM(SUMIF(OFFSET('SEP-21'!$A$1,MATCH(Sheet1!A1,'SEP-21'!$A:$A,0),2,22,1),{"*Pro*ax*"},OFFSET('SEP-21'!$A$1,MATCH(Sheet1!A1,'SEP-21'!$A:$A,0),3,22,1))),0) -> 0 | L11: =IFERROR(SUM(SUMIF(OFFSET('SEP-21'!$A$1,MATCH(Sheet1!A1,'SEP-21'!$A:$A,0),2,22,1),{"GPF_G*","DCPS"},OFFSET('SEP-21'!$A$1,MATCH(Sheet1!A1,'SEP-21'!$A:$A,0),3,22,1))),0) -> 0 | M11: =IFERROR(SUM(SUMIF(OFFSET('SEP-21'!$A$1,MATCH(Sheet1!A1,'SEP-21'!$A:$A,0),2,22,1),{"*GIS","GIS*R"},OFFSET('SEP-21'!$A$1,MATCH(Sheet1!A1,'SEP-21'!$A:$A,0),3,22,1))),0) -> 0 | N11: =IFERROR(SUM(SUMIF(OFFSET('SEP-21'!$A$1,MATCH(Sheet1!A1,'SEP-21'!$A:$A,0),5,22,1),{"LI*1"},OFFSET('SEP-21'!$A$1,MATCH(Sheet1!A1,'SEP-21'!$A:$A,0),6,22,1))),0) -> 0 | O11: {=IFERROR(SUM(SUMIF(OFFSET('SEP-21'!$A$1,MATCH(Sheet1!A1,'SEP-21'!$A:$A,0),2,22,1),{"HB*USE","HB*INT"},OFFSET('SEP-21'!$A$1,MATCH(Sheet1!A1,'SEP-21'!$A:$A,0),3,22,1))),0)} -> 0 | P11: {=IFERROR(SUM(SUMIF(OFFSET('SEP-21'!$A$1,MATCH(Sheet1!A1,'SEP-21'!$A:$A,0),5,22,1),{"OTHE*1","CO.*1","OTHE*2","WEL*ND","BAN*1","CLU*ND","RD*1","LI*2","MIS*US","*TAINAN*","MCA*INT*","MAIN*NANCE*","*C M Relief Fund*","Co. Op. Hsg Soc.*","GPF_ADV*","Co. Op. Cr. Soc. 2*","DCPS DA","DCPS Pay","MCA Int"},OFFSET('SEP-21'!$A$1,MATCH(Sheet1!A1,'SEP-21'!$A:$A,0),6,22,1)))+SUM(SUMIF(OFFSET('SEP-21'!$A$1,MATCH(Sheet1!A1,'SEP-21'!$A:$A,0),2,22,1),{"MCA","COM*DV*","HB*ND","CO*SOC","HRR","SRV*H","ACC*CY","F.A","STAMP_REVENUE","*C M Relief Fund*","GPF_ADV*","Co. Op. Cr. Soc. 2*","DCPS DA","DCPS Pay","MCA Int"},OFFSET('SEP-21'!$A$1,MATCH(Sheet1!A1,'SEP-21'!$A:$A,0),3,22,1))),0)} -> 0 | Q11: =+J11-H11-K11-L11-M11-N11-O11-P11-R11 -> 0 | R11: {=IFERROR(SUM(SUMIF(OFFSET('SEP-21'!$A$1,MATCH(Sheet1!A1,'SEP-21'!$A:$A,0),2,22,1),{"*I. *ax*"},OFFSET('SEP-21'!$A$1,MATCH(Sheet1!A1,'SEP-21'!$A:$A,0),3,22,1))),0)} -> 0 | S11: {=+IFERROR(IF(OFFSET('SEP-21'!$B$1,MATCH(Sheet1!A1,'SEP-21'!B:B,0)-2,0,1,1)=Sheet1!J11,IF(MID(IFERROR(OFFSET('SEP-21'!$B$1,MATCH(Sheet1!A1,'SEP-21'!$B:$B,0)-1,-1,1,1),"GROSS ERROR"),11,FIND(" ",OFFSET('SEP-21'!$B$1,MATCH(Sheet1!A1,'SEP-21'!$B:$B,0)-1,-1,1,1),12)-11)-Q11=0,"","NET MISMATCH"),"GROSS MISMATCH"),"")} | BH11: =+G2 -> PAN | BI11: =+A1 -> 0 | BJ11: {=IFERROR(OFFSET('SEP-21'!$B$1,MATCH(Sheet1!A1,'SEP-21'!$B:$B,0)+1,0,1,1),"")} | BK11: =+J11 -> 0 | BL11: =+R11 -> 0 | BM11: {=IFERROR(OFFSET('SEP-21'!$A$1,MATCH(Sheet1!A1,'SEP-21'!$A:$A,0)-2,0,1,1),"")}
A12: 8 | B12: 44470 | C12: =IFERROR(SUM(SUMIF(OFFSET('OCT-21'!$A$1,MATCH(Sheet1!A1,'OCT-21'!$A:$A,0),0,22,1),{"BA*C","BASIC??"},OFFSET('OCT-21'!$A$1,MATCH(Sheet1!A1,'OCT-21'!$A:$A,0),1,22,1))),0) -> 0 | D12: =IFERROR(SUM(SUMIF(OFFSET('OCT-21'!$A$1,MATCH(Sheet1!A1,'OCT-21'!$A:$A,0),0,22,1),{"DA*C","D. *"},OFFSET('OCT-21'!$A$1,MATCH(Sheet1!A1,'OCT-21'!$A:$A,0),1,22,1))),0) -> 0 | E12: =IFERROR(SUM(SUMIF(OFFSET('OCT-21'!$A$1,MATCH(Sheet1!A1,'OCT-21'!$A:$A,0),0,22,1),{"H. R. A."},OFFSET('OCT-21'!$A$1,MATCH(Sheet1!A1,'OCT-21'!$A:$A,0),1,22,1))),0) -> 0 | F12: {=IFERROR(SUM(SUMIF(OFFSET('OCT-21'!$A$1,MATCH(Sheet1!A1,'OCT-21'!$A:$A,0),0,22,1),{"SP*AY*","S D A*","O.A.*","CLA (5th Pay)*","REF. Allow*","Trans.Allw.*","LF*","P. O.*","ARM*","Conv.A*","Otr.Allow*","Trans_Arrear*","BMIA*","Incentives*","Fit Allow*","KMA","NON-*","U.*","ME*A","PG*","Per.Tra"},OFFSET('OCT-21'!$A$1,MATCH(Sheet1!A1,'OCT-21'!$A:$A,0),1,22,1))),0)} -> 0 | G12: =IFERROR(SUM(SUMIF(OFFSET('OCT-21'!$A$1,MATCH(Sheet1!A1,'OCT-21'!$A:$A,0),0,22,1),{"WA"},OFFSET('OCT-21'!$A$1,MATCH(Sheet1!A1,'OCT-21'!$A:$A,0),1,22,1))),0) -> 0 | H12: =IFERROR(SUM(SUMIF(OFFSET('OCT-21'!$A$1,MATCH(Sheet1!A1,'OCT-21'!$A:$A,0),0,22,1),{"DCPS","GROSS_ADJUST"},OFFSET('OCT-21'!$A$1,MATCH(Sheet1!A1,'OCT-21'!$A:$A,0),1,22,1))),0) -> 0 | I12: {=+IFERROR(SUM(SUMIF(OFFSET('OCT-21'!$A$1,MATCH(Sheet1!A1,'OCT-21'!$A:$A,0),0,22,1),{"Basic*Arr*","7th Pay* Arr*","DA Arr"},OFFSET('OCT-21'!$A$1,MATCH(Sheet1!A1,'OCT-21'!$A:$A,0),1,22,1))),0)} -> 0 | J12: =SUM(C12:I12) -> 0 | K12: =IFERROR(SUM(SUMIF(OFFSET('OCT-21'!$A$1,MATCH(Sheet1!A1,'OCT-21'!$A:$A,0),2,22,1),{"*Pro*ax*"},OFFSET('OCT-21'!$A$1,MATCH(Sheet1!A1,'OCT-21'!$A:$A,0),3,22,1))),0) -> 0 | L12: {=IFERROR(SUM(SUMIF(OFFSET('OCT-21'!$A$1,MATCH(Sheet1!A1,'OCT-21'!$A:$A,0),2,22,1),{"GPF_G*","DCPS","DCPS DA*"},OFFSET('OCT-21'!$A$1,MATCH(Sheet1!A1,'OCT-21'!$A:$A,0),3,22,1))),0)} -> 0 | M12: =IFERROR(SUM(SUMIF(OFFSET('OCT-21'!$A$1,MATCH(Sheet1!A1,'OCT-21'!$A:$A,0),2,22,1),{"*GIS","GIS*R"},OFFSET('OCT-21'!$A$1,MATCH(Sheet1!A1,'OCT-21'!$A:$A,0),3,22,1))),0) -> 0 | N12: =IFERROR(SUM(SUMIF(OFFSET('OCT-21'!$A$1,MATCH(Sheet1!A1,'OCT-21'!$A:$A,0),5,22,1),{"LI*1"},OFFSET('OCT-21'!$A$1,MATCH(Sheet1!A1,'OCT-21'!$A:$A,0),6,22,1))),0) -> 0 | O12: {=IFERROR(SUM(SUMIF(OFFSET('OCT-21'!$A$1,MATCH(Sheet1!A1,'OCT-21'!$A:$A,0),2,22,1),{"HB*USE","HB*INT"},OFFSET('OCT-21'!$A$1,MATCH(Sheet1!A1,'OCT-21'!$A:$A,0),3,22,1))),0)} -> 0 | P12: {=IFERROR(SUM(SUMIF(OFFSET('OCT-21'!$A$1,MATCH(Sheet1!A1,'OCT-21'!$A:$A,0),5,22,1),{"OTHE*1","CO.*1","OTHE*2","WEL*ND","BAN*1","CLU*ND","RD*1","LI*2","MIS*US","*TAINAN*","MCA*INT*","MAIN*NANCE*","*C M Relief Fund*","Co. Op. Hsg Soc.*","GPF_ADV*","Co. Op. Cr. Soc. 2*","DCPS Pay"},OFFSET('OCT-21'!$A$1,MATCH(Sheet1!A1,'OCT-21'!$A:$A,0),6,22,1)))+SUM(SUMIF(OFFSET('OCT-21'!$A$1,MATCH(Sheet1!A1,'OCT-21'!$A:$A,0),2,22,1),{"MCA","COM*DV*","HB*ND","CO*SOC","HRR","SRV*H","ACC*CY","F.A","STAMP_REVENUE","*C M Relief Fund*","GPF_ADV*","Co. Op. Cr. Soc. 2*","DCPS Pay"},OFFSET('OCT-21'!$A$1,MATCH(Sheet1!A1,'OCT-21'!$A:$A,0),3,22,1))),0)} -> 0 | Q12: =+J12-H12-K12-L12-M12-N12-O12-P12-R12 -> 0 | R12: {=IFERROR(SUM(SUMIF(OFFSET('OCT-21'!$A$1,MATCH(Sheet1!A1,'OCT-21'!$A:$A,0),2,22,1),{"*I. *ax*"},OFFSET('OCT-21'!$A$1,MATCH(Sheet1!A1,'OCT-21'!$A:$A,0),3,22,1))),0)} -> 0 | S12: {=+IFERROR(IF(OFFSET('OCT-21'!$B$1,MATCH(Sheet1!A1,'OCT-21'!B:B,0)-2,0,1,1)=Sheet1!J12,IF(MID(IFERROR(OFFSET('OCT-21'!$B$1,MATCH(Sheet1!A1,'OCT-21'!$B:$B,0)-1,-1,1,1),"GROSS ERROR"),11,FIND(" ",OFFSET('OCT-21'!$B$1,MATCH(Sheet1!A1,'OCT-21'!$B:$B,0)-1,-1,1,1),12)-11)-Q12=0,"","NET MISMATCH"),"GROSS MISMATCH"),"")} | BH12: =+G2 -> PAN | BI12: =+A1 -> 0 | BJ12: {=+IFERROR(OFFSET('OCT-21'!$B$1,MATCH(Sheet1!A1,'OCT-21'!$B:$B,0)+1,0,1,1),"")} | BK12: =+J12 -> 0 | BL12: =+R12 -> 0 | BM12: {=IFERROR(OFFSET('OCT-21'!$A$1,MATCH(Sheet1!A1,'OCT-21'!$A:$A,0)-2,0,1,1),"")}
A13: 9 | B13: 44501 | C13: =IFERROR(SUM(SUMIF(OFFSET('NOV-21'!$A$1,MATCH(Sheet1!A1,'NOV-21'!$A:$A,0),0,22,1),{"BA*C","BASIC??"},OFFSET('NOV-21'!$A$1,MATCH(Sheet1!A1,'NOV-21'!$A:$A,0),1,22,1))),0) -> 0 | D13: =IFERROR(SUM(SUMIF(OFFSET('NOV-21'!$A$1,MATCH(Sheet1!A1,'NOV-21'!$A:$A,0),0,22,1),{"DA*C","D. *"},OFFSET('NOV-21'!$A$1,MATCH(Sheet1!A1,'NOV-21'!$A:$A,0),1,22,1))),0) -> 0 | E13: =IFERROR(SUM(SUMIF(OFFSET('NOV-21'!$A$1,MATCH(Sheet1!A1,'NOV-21'!$A:$A,0),0,22,1),{"H. R. A."},OFFSET('NOV-21'!$A$1,MATCH(Sheet1!A1,'NOV-21'!$A:$A,0),1,22,1))),0) -> 0 | F13: {=IFERROR(SUM(SUMIF(OFFSET('NOV-21'!$A$1,MATCH(Sheet1!A1,'NOV-21'!$A:$A,0),0,22,1),{"SP*AY*","S D A*","O.A.*","CLA (5th Pay)*","REF. Allow*","Trans.Allw.*","LF*","P. O.*","ARM*","Conv.A*","Otr.Allow*","Trans_Arrear*","BMIA*","Incentives*","Fit Allow*","KMA","NON-*","U.*","ME*A","PG*","Per.Tra"},OFFSET('NOV-21'!$A$1,MATCH(Sheet1!A1,'NOV-21'!$A:$A,0),1,22,1))),0)} -> 0 | G13: =IFERROR(SUM(SUMIF(OFFSET('NOV-21'!$A$1,MATCH(Sheet1!A1,'NOV-21'!$A:$A,0),0,22,1),{"WA"},OFFSET('NOV-21'!$A$1,MATCH(Sheet1!A1,'NOV-21'!$A:$A,0),1,22,1))),0) -> 0 | H13: =IFERROR(SUM(SUMIF(OFFSET('NOV-21'!$A$1,MATCH(Sheet1!A1,'NOV-21'!$A:$A,0),0,22,1),{"DCPS","GROSS_ADJUST"},OFFSET('NOV-21'!$A$1,MATCH(Sheet1!A1,'NOV-21'!$A:$A,0),1,22,1))),0) -> 0 | I13: {=+IFERROR(SUM(SUMIF(OFFSET('NOV-21'!$A$1,MATCH(Sheet1!A1,'NOV-21'!$A:$A,0),0,22,1),{"Basic*Arr*","7th Pay* Arr*","DA Arr"},OFFSET('NOV-21'!$A$1,MATCH(Sheet1!A1,'NOV-21'!$A:$A,0),1,22,1))),0)} -> 0 | J13: =SUM(C13:I13) -> 0 | K13: =IFERROR(SUM(SUMIF(OFFSET('NOV-21'!$A$1,MATCH(Sheet1!A1,'NOV-21'!$A:$A,0),2,22,1),{"*Pro*ax*"},OFFSET('NOV-21'!$A$1,MATCH(Sheet1!A1,'NOV-21'!$A:$A,0),3,22,1))),0) -> 0 | L13: =IFERROR(SUM(SUMIF(OFFSET('NOV-21'!$A$1,MATCH(Sheet1!A1,'NOV-21'!$A:$A,0),2,22,1),{"GPF_G*","DCPS"},OFFSET('NOV-21'!$A$1,MATCH(Sheet1!A1,'NOV-21'!$A:$A,0),3,22,1))),0) -> 0 | M13: =IFERROR(SUM(SUMIF(OFFSET('NOV-21'!$A$1,MATCH(Sheet1!A1,'NOV-21'!$A:$A,0),2,22,1),{"*GIS","GIS*R"},OFFSET('NOV-21'!$A$1,MATCH(Sheet1!A1,'NOV-21'!$A:$A,0),3,22,1))),0) -> 0 | N13: =IFERROR(SUM(SUMIF(OFFSET('NOV-21'!$A$1,MATCH(Sheet1!A1,'NOV-21'!$A:$A,0),5,22,1),{"LI*1"},OFFSET('NOV-21'!$A$1,MATCH(Sheet1!A1,'NOV-21'!$A:$A,0),6,22,1))),0) -> 0 | O13: {=IFERROR(SUM(SUMIF(OFFSET('NOV-21'!$A$1,MATCH(Sheet1!A1,'NOV-21'!$A:$A,0),2,22,1),{"HB*USE","HB*INT"},OFFSET('NOV-21'!$A$1,MATCH(Sheet1!A1,'NOV-21'!$A:$A,0),3,22,1))),0)} -> 0 | P13: {=IFERROR(SUM(SUMIF(OFFSET('NOV-21'!$A$1,MATCH(Sheet1!A1,'NOV-21'!$A:$A,0),5,22,1),{"OTHE*1","CO.*1","OTHE*2","WEL*ND","BAN*1","CLU*ND","RD*1","LI*2","MIS*US","*TAINAN*","MCA*INT*","MAIN*NANCE*","*C M Relief Fund*","Co. Op. Hsg Soc.*","GPF_ADV*","Co. Op. Cr. Soc. 2*","DCPS DA","DCPS Pay","MCA Int"},OFFSET('NOV-21'!$A$1,MATCH(Sheet1!A1,'NOV-21'!$A:$A,0),6,22,1)))+SUM(SUMIF(OFFSET('NOV-21'!$A$1,MATCH(Sheet1!A1,'NOV-21'!$A:$A,0),2,22,1),{"MCA","COM*DV*","HB*ND","CO*SOC","HRR","SRV*H","ACC*CY","F.A","STAMP_REVENUE","*C M Relief Fund*","GPF_ADV*","Co. Op. Cr. Soc. 2*","DCPS DA","DCPS Pay","MCA Int"},OFFSET('NOV-21'!$A$1,MATCH(Sheet1!A1,'NOV-21'!$A:$A,0),3,22,1))),0)} -> 0 | Q13: =+J13-H13-K13-L13-M13-N13-O13-P13-R13 -> 0 | R13: {=IFERROR(SUM(SUMIF(OFFSET('NOV-21'!$A$1,MATCH(Sheet1!A1,'NOV-21'!$A:$A,0),2,22,1),{"*I. *ax*"},OFFSET('NOV-21'!$A$1,MATCH(Sheet1!A1,'NOV-21'!$A:$A,0),3,22,1))),0)} -> 0 | S13: {=+IFERROR(IF(OFFSET('NOV-21'!$B$1,MATCH(Sheet1!A1,'NOV-21'!B:B,0)-2,0,1,1)=Sheet1!J13,IF(MID(IFERROR(OFFSET('NOV-21'!$B$1,MATCH(Sheet1!A1,'NOV-21'!$B:$B,0)-1,-1,1,1),"GROSS ERROR"),11,FIND(" ",OFFSET('NOV-21'!$B$1,MATCH(Sheet1!A1,'NOV-21'!$B:$B,0)-1,-1,1,1),12)-11)-Q13=0,"","NET MISMATCH"),"GROSS MISMATCH"),"")} | BH13: =+G2 -> PAN | BI13: =+A1 -> 0 | BJ13: {=+IFERROR(OFFSET('NOV-21'!$B$1,MATCH(Sheet1!A1,'NOV-21'!$B:$B,0)+1,0,1,1),"")} | BK13: =+J13 -> 0 | BL13: =+R13 -> 0 | BM13: {=IFERROR(OFFSET('NOV-21'!$A$1,MATCH(Sheet1!A1,'NOV-21'!$A:$A,0)-2,0,1,1),"")}
A14: 10 | B14: 44531 | C14: =IFERROR(SUM(SUMIF(OFFSET('DEC-21'!$A$1,MATCH(Sheet1!A1,'DEC-21'!$A:$A,0),0,22,1),{"BA*C","BASIC??"},OFFSET('DEC-21'!$A$1,MATCH(Sheet1!A1,'DEC-21'!$A:$A,0),1,22,1))),0) -> 0 | D14: =IFERROR(SUM(SUMIF(OFFSET('DEC-21'!$A$1,MATCH(Sheet1!A1,'DEC-21'!$A:$A,0),0,22,1),{"DA*C","D. *"},OFFSET('DEC-21'!$A$1,MATCH(Sheet1!A1,'DEC-21'!$A:$A,0),1,22,1))),0) -> 0 | E14: =IFERROR(SUM(SUMIF(OFFSET('DEC-21'!$A$1,MATCH(Sheet1!A1,'DEC-21'!$A:$A,0),0,22,1),{"H. R. A."},OFFSET('DEC-21'!$A$1,MATCH(Sheet1!A1,'DEC-21'!$A:$A,0),1,22,1))),0) -> 0 | F14: {=IFERROR(SUM(SUMIF(OFFSET('DEC-21'!$A$1,MATCH(Sheet1!A1,'DEC-21'!$A:$A,0),0,22,1),{"SP*AY*","S D A*","O.A.*","CLA (5th Pay)*","REF. Allow*","Trans.Allw.*","LF*","P. O.*","ARM*","Conv.A*","Otr.Allow*","Trans_Arrear*","BMIA*","Incentives*","Fit Allow*","KMA","NON-*","U.*","ME*A","PG*","Per.Tra"},OFFSET('DEC-21'!$A$1,MATCH(Sheet1!A1,'DEC-21'!$A:$A,0),1,22,1))),0)} -> 0 | G14: =IFERROR(SUM(SUMIF(OFFSET('DEC-21'!$A$1,MATCH(Sheet1!A1,'DEC-21'!$A:$A,0),0,22,1),{"WA"},OFFSET('DEC-21'!$A$1,MATCH(Sheet1!A1,'DEC-21'!$A:$A,0),1,22,1))),0) -> 0 | H14: =IFERROR(SUM(SUMIF(OFFSET('DEC-21'!$A$1,MATCH(Sheet1!A1,'DEC-21'!$A:$A,0),0,22,1),{"DCPS","GROSS_ADJUST"},OFFSET('DEC-21'!$A$1,MATCH(Sheet1!A1,'DEC-21'!$A:$A,0),1,22,1))),0) -> 0 | I14: {=+IFERROR(SUM(SUMIF(OFFSET('DEC-21'!$A$1,MATCH(Sheet1!A1,'DEC-21'!$A:$A,0),0,22,1),{"Basic*Arr*","7th Pay* Arr*"},OFFSET('DEC-21'!$A$1,MATCH(Sheet1!A1,'DEC-21'!$A:$A,0),1,22,1))),0)} -> 0 | J14: =SUM(C14:I14) -> 0 | K14: =IFERROR(SUM(SUMIF(OFFSET('DEC-21'!$A$1,MATCH(Sheet1!A1,'DEC-21'!$A:$A,0),2,22,1),{"*Pro*ax*"},OFFSET('DEC-21'!$A$1,MATCH(Sheet1!A1,'DEC-21'!$A:$A,0),3,22,1))),0) -> 0 | L14: =IFERROR(SUM(SUMIF(OFFSET('DEC-21'!$A$1,MATCH(Sheet1!A1,'DEC-21'!$A:$A,0),2,22,1),{"GPF_G*","DCPS"},OFFSET('DEC-21'!$A$1,MATCH(Sheet1!A1,'DEC-21'!$A:$A,0),3,22,1))),0) -> 0 | M14: =IFERROR(SUM(SUMIF(OFFSET('DEC-21'!$A$1,MATCH(Sheet1!A1,'DEC-21'!$A:$A,0),2,22,1),{"*GIS","GIS*R"},OFFSET('DEC-21'!$A$1,MATCH(Sheet1!A1,'DEC-21'!$A:$A,0),3,22,1))),0) -> 0 | N14: =IFERROR(SUM(SUMIF(OFFSET('DEC-21'!$A$1,MATCH(Sheet1!A1,'DEC-21'!$A:$A,0),5,22,1),{"LI*1"},OFFSET('DEC-21'!$A$1,MATCH(Sheet1!A1,'DEC-21'!$A:$A,0),6,22,1))),0) -> 0 | O14: {=IFERROR(SUM(SUMIF(OFFSET('DEC-21'!$A$1,MATCH(Sheet1!A1,'DEC-21'!$A:$A,0),2,22,1),{"HB*USE","HB*INT"},OFFSET('DEC-21'!$A$1,MATCH(Sheet1!A1,'DEC-21'!$A:$A,0),3,22,1))),0)} -> 0 | P14: {=IFERROR(SUM(SUMIF(OFFSET('DEC-21'!$A$1,MATCH(Sheet1!A1,'DEC-21'!$A:$A,0),5,22,1),{"OTHE*1","CO.*1","OTHE*2","WEL*ND","BAN*1","CLU*ND","RD*1","LI*2","MIS*US","*TAINAN*","MCA*INT*","MAIN*NANCE*","*C M Relief Fund*","Co. Op. Hsg Soc.*","GPF_ADV*","Co. Op. Cr. Soc. 2*","DCPS DA","DCPS Pay","MCA Int"},OFFSET('DEC-21'!$A$1,MATCH(Sheet1!A1,'DEC-21'!$A:$A,0),6,22,1)))+SUM(SUMIF(OFFSET('DEC-21'!$A$1,MATCH(Sheet1!A1,'DEC-21'!$A:$A,0),2,22,1),{"MCA","COM*DV*","HB*ND","CO*SOC","HRR","SRV*H","ACC*CY","F.A","STAMP_REVENUE","*C M Relief Fund*","GPF_ADV*","Co. Op. Cr. Soc. 2*","DCPS DA","DCPS Pay","MCA Int"},OFFSET('DEC-21'!$A$1,MATCH(Sheet1!A1,'DEC-21'!$A:$A,0),3,22,1))),0)} -> 0 | Q14: =+J14-H14-K14-L14-M14-N14-O14-P14-R14 -> 0 | R14: {=IFERROR(SUM(SUMIF(OFFSET('DEC-21'!$A$1,MATCH(Sheet1!A1,'DEC-21'!$A:$A,0),2,22,1),{"*I. *ax*"},OFFSET('DEC-21'!$A$1,MATCH(Sheet1!A1,'DEC-21'!$A:$A,0),3,22,1))),0)} -> 0 | S14: {=+IFERROR(IF(OFFSET('DEC-21'!$B$1,MATCH(Sheet1!A1,'DEC-21'!B:B,0)-2,0,1,1)=Sheet1!J14,IF(MID(IFERROR(OFFSET('DEC-21'!$B$1,MATCH(Sheet1!A1,'DEC-21'!$B:$B,0)-1,-1,1,1),"GROSS ERROR"),11,FIND(" ",OFFSET('DEC-21'!$B$1,MATCH(Sheet1!A1,'DEC-21'!$B:$B,0)-1,-1,1,1),12)-11)-Q14=0,"","NET MISMATCH"),"GROSS MISMATCH"),"")} | BH14: =+G2 -> PAN | BI14: =+A1 -> 0 | BJ14: {=+IFERROR(OFFSET('DEC-21'!$B$1,MATCH(Sheet1!A1,'DEC-21'!$B:$B,0)+1,0,1,1),"")} | BK14: =+J14 -> 0 | BL14: =+R14 -> 0 | BM14: {=IFERROR(OFFSET('DEC-21'!$A$1,MATCH(Sheet1!A1,'DEC-21'!$A:$A,0)-2,0,1,1),"")}
A15: 11 | B15: 44562 | C15: =IFERROR(SUM(SUMIF(OFFSET('JAN-22'!$A$1,MATCH(Sheet1!A1,'JAN-22'!$A:$A,0),0,22,1),{"BA*C","BASIC??"},OFFSET('JAN-22'!$A$1,MATCH(Sheet1!A1,'JAN-22'!$A:$A,0),1,22,1))),0) -> 0 | D15: =IFERROR(SUM(SUMIF(OFFSET('JAN-22'!$A$1,MATCH(Sheet1!A1,'JAN-22'!$A:$A,0),0,22,1),{"DA*C","D. *"},OFFSET('JAN-22'!$A$1,MATCH(Sheet1!A1,'JAN-22'!$A:$A,0),1,22,1))),0) -> 0 | E15: =IFERROR(SUM(SUMIF(OFFSET('JAN-22'!$A$1,MATCH(Sheet1!A1,'JAN-22'!$A:$A,0),0,22,1),{"H. R. A."},OFFSET('JAN-22'!$A$1,MATCH(Sheet1!A1,'JAN-22'!$A:$A,0),1,22,1))),0) -> 0 | F15: {=IFERROR(SUM(SUMIF(OFFSET('JAN-22'!$A$1,MATCH(Sheet1!A1,'JAN-22'!$A:$A,0),0,22,1),{"SP*AY*","S D A*","O.A.*","CLA (5th Pay)*","REF. Allow*","Trans.Allw.*","LF*","P. O.*","ARM*","Conv.A*","Otr.Allow*","Trans_Arrear*","BMIA*","Incentives*","Fit Allow*","KMA","NON-*","U.*","ME*A","PG*","Per.Tra"},OFFSET('JAN-22'!$A$1,MATCH(Sheet1!A1,'JAN-22'!$A:$A,0),1,22,1))),0)} -> 0 | G15: =IFERROR(SUM(SUMIF(OFFSET('JAN-22'!$A$1,MATCH(Sheet1!A1,'JAN-22'!$A:$A,0),0,22,1),{"WA"},OFFSET('JAN-22'!$A$1,MATCH(Sheet1!A1,'JAN-22'!$A:$A,0),1,22,1))),0) -> 0 | H15: =IFERROR(SUM(SUMIF(OFFSET('JAN-22'!$A$1,MATCH(Sheet1!A1,'JAN-22'!$A:$A,0),0,22,1),{"DCPS","GROSS_ADJUST"},OFFSET('JAN-22'!$A$1,MATCH(Sheet1!A1,'JAN-22'!$A:$A,0),1,22,1))),0) -> 0 | I15: {=+IFERROR(SUM(SUMIF(OFFSET('JAN-22'!$A$1,MATCH(Sheet1!A1,'JAN-22'!$A:$A,0),0,22,1),{"Basic*Arr*","7th Pay* Arr*"},OFFSET('JAN-22'!$A$1,MATCH(Sheet1!A1,'JAN-22'!$A:$A,0),1,22,1))),0)} -> 0 | J15: =SUM(C15:I15) -> 0 | K15: =IFERROR(SUM(SUMIF(OFFSET('JAN-22'!$A$1,MATCH(Sheet1!A1,'JAN-22'!$A:$A,0),2,22,1),{"*Pro*ax*"},OFFSET('JAN-22'!$A$1,MATCH(Sheet1!A1,'JAN-22'!$A:$A,0),3,22,1))),0) -> 0 | L15: =IFERROR(SUM(SUMIF(OFFSET('JAN-22'!$A$1,MATCH(Sheet1!A1,'JAN-22'!$A:$A,0),2,22,1),{"GPF_G*","DCPS"},OFFSET('JAN-22'!$A$1,MATCH(Sheet1!A1,'JAN-22'!$A:$A,0),3,22,1))),0) -> 0 | M15: {=IFERROR(SUM(SUMIF(OFFSET('JAN-22'!$A$1,MATCH(Sheet1!A1,'JAN-22'!$A:$A,0),2,22,1),{"*GIS","GIS*R"},OFFSET('JAN-22'!$A$1,MATCH(Sheet1!A1,'JAN-22'!$A:$A,0),3,22,1))),0)} -> 0 | N15: =IFERROR(SUM(SUMIF(OFFSET('JAN-22'!$A$1,MATCH(Sheet1!A1,'JAN-22'!$A:$A,0),5,22,1),{"LI*1"},OFFSET('JAN-22'!$A$1,MATCH(Sheet1!A1,'JAN-22'!$A:$A,0),6,22,1))),0) -> 0 | O15: {=IFERROR(SUM(SUMIF(OFFSET('JAN-22'!$A$1,MATCH(Sheet1!A1,'JAN-22'!$A:$A,0),2,22,1),{"HB*USE","HB*INT"},OFFSET('JAN-22'!$A$1,MATCH(Sheet1!A1,'JAN-22'!$A:$A,0),3,22,1))),0)} -> 0 | P15: {=IFERROR(SUM(SUMIF(OFFSET('JAN-22'!$A$1,MATCH(Sheet1!A1,'JAN-22'!$A:$A,0),5,22,1),{"OTHE*1","CO.*1","OTHE*2","WEL*ND","BAN*1","CLU*ND","RD*1","LI*2","MIS*US","*TAINAN*","MCA*INT*","MAIN*NANCE*","*C M Relief Fund*","Co. Op. Hsg Soc.*","GPF_ADV*","Co. Op. Cr. Soc. 2*","DCPS DA","DCPS Pay","MCA Int"},OFFSET('JAN-22'!$A$1,MATCH(Sheet1!A1,'JAN-22'!$A:$A,0),6,22,1)))+SUM(SUMIF(OFFSET('JAN-22'!$A$1,MATCH(Sheet1!A1,'JAN-22'!$A:$A,0),2,22,1),{"MCA","COM*DV*","HB*ND","CO*SOC","HRR","SRV*H","ACC*CY","F.A","STAMP_REVENUE","*C M Relief Fund*","GPF_ADV*","Co. Op. Cr. Soc. 2*","DCPS DA","DCPS Pay","MCA Int"},OFFSET('JAN-22'!$A$1,MATCH(Sheet1!A1,'JAN-22'!$A:$A,0),3,22,1))),0)} -> 0 | Q15: =+J15-H15-K15-L15-M15-N15-O15-P15-R15 -> 0 | R15: {=IFERROR(SUM(SUMIF(OFFSET('JAN-22'!$A$1,MATCH(Sheet1!A1,'JAN-22'!$A:$A,0),2,22,1),{"*I. *ax*"},OFFSET('JAN-22'!$A$1,MATCH(Sheet1!A1,'JAN-22'!$A:$A,0),3,22,1))),0)} -> 0 | S15: {=+IFERROR(IF(OFFSET('JAN-22'!$B$1,MATCH(Sheet1!A1,'JAN-22'!B:B,0)-2,0,1,1)=Sheet1!J15,IF(MID(IFERROR(OFFSET('JAN-22'!$B$1,MATCH(Sheet1!A1,'JAN-22'!$B:$B,0)-1,-1,1,1),"GROSS ERROR"),11,FIND(" ",OFFSET('JAN-22'!$B$1,MATCH(Sheet1!A1,'JAN-22'!$B:$B,0)-1,-1,1,1),12)-11)-Q15=0,"","NET MISMATCH"),"GROSS MISMATCH"),"")} | BH15: =+G2 -> PAN | BI15: =+A1 -> 0 | BJ15: {=IFERROR(OFFSET('JAN-22'!$B$1,MATCH(Sheet1!A1,'JAN-22'!$B:$B,0)+1,0,1,1),"")} | BK15: =+J15 -> 0 | BL15: =+R15 -> 0 | BM15: {=IFERROR(OFFSET('JAN-22'!$A$1,MATCH(Sheet1!A1,'JAN-22'!$A:$A,0)-2,0,1,1),"")}
A16: 12 | B16: 44593 | C16: =IFERROR(SUM(SUMIF(OFFSET('FEB-22'!$A$1,MATCH(Sheet1!$A$1,'FEB-22'!$A:$A,0),0,22,1),{"BA*C","BASIC??"},OFFSET('FEB-22'!$A$1,MATCH(Sheet1!$A$1,'FEB-22'!$A:$A,0),1,22,1))),0) -> 0 | D16: =IFERROR(SUM(SUMIF(OFFSET('FEB-22'!$A$1,MATCH(Sheet1!$A$1,'FEB-22'!$A:$A,0),0,22,1),{"DA*C","D. *"},OFFSET('FEB-22'!$A$1,MATCH(Sheet1!$A$1,'FEB-22'!$A:$A,0),1,22,1))),0) -> 0 | E16: =IFERROR(SUM(SUMIF(OFFSET('FEB-22'!$A$1,MATCH(Sheet1!$A$1,'FEB-22'!$A:$A,0),0,22,1),{"H. R. A."},OFFSET('FEB-22'!$A$1,MATCH(Sheet1!$A$1,'FEB-22'!$A:$A,0),1,22,1))),0) -> 0 | F16: {=IFERROR(SUM(SUMIF(OFFSET('FEB-22'!$A$1,MATCH(Sheet1!$A$1,'FEB-22'!$A:$A,0),0,22,1),{"SP*AY*","S D A*","O.A.*","CLA (5th Pay)*","REF. Allow*","Trans.Allw.*","LF*","P. O.*","ARM*","Conv.A*","Otr.Allow*","Trans_Arrear*","BMIA*","Incentives*","Fit Allow*","KMA","NON-*","U.*","ME*A","PG*","Per.Tra"},OFFSET('FEB-22'!$A$1,MATCH(Sheet1!$A$1,'FEB-22'!$A:$A,0),1,22,1))),0)} -> 0 | G16: =IFERROR(SUM(SUMIF(OFFSET('FEB-22'!$A$1,MATCH(Sheet1!$A$1,'FEB-22'!$A:$A,0),0,22,1),{"WA"},OFFSET('FEB-22'!$A$1,MATCH(Sheet1!$A$1,'FEB-22'!$A:$A,0),1,22,1))),0) -> 0 | H16: =IFERROR(SUM(SUMIF(OFFSET('FEB-22'!$A$1,MATCH(Sheet1!$A$1,'FEB-22'!$A:$A,0),0,22,1),{"DCPS","GROSS_ADJUST"},OFFSET('FEB-22'!$A$1,MATCH(Sheet1!$A$1,'FEB-22'!$A:$A,0),1,22,1))),0) -> 0 | I16: {=+IFERROR(SUM(SUMIF(OFFSET('FEB-22'!$A$1,MATCH(Sheet1!$A$1,'FEB-22'!$A:$A,0),0,22,1),{"Basic*Arr*","7th Pay* Arr*"},OFFSET('FEB-22'!$A$1,MATCH(Sheet1!$A$1,'FEB-22'!$A:$A,0),1,22,1))),0)} -> 0 | J16: =SUM(C16:I16) -> 0 | K16: =IFERROR(SUM(SUMIF(OFFSET('FEB-22'!$A$1,MATCH(Sheet1!$A$1,'FEB-22'!$A:$A,0),2,22,1),{"*Pro*ax*"},OFFSET('FEB-22'!$A$1,MATCH(Sheet1!$A$1,'FEB-22'!$A:$A,0),3,22,1))),0) -> 0 | L16: =IFERROR(SUM(SUMIF(OFFSET('FEB-22'!$A$1,MATCH(Sheet1!$A$1,'FEB-22'!$A:$A,0),2,22,1),{"GPF_G*","DCPS"},OFFSET('FEB-22'!$A$1,MATCH(Sheet1!$A$1,'FEB-22'!$A:$A,0),3,22,1))),0) -> 0 | M16: {=IFERROR(SUM(SUMIF(OFFSET('FEB-22'!$A$1,MATCH(Sheet1!$A$1,'FEB-22'!$A:$A,0),2,22,1),{"*GIS","GIS*R"},OFFSET('FEB-22'!$A$1,MATCH(Sheet1!$A$1,'FEB-22'!$A:$A,0),3,22,1))),0)} -> 0 | N16: =IFERROR(SUM(SUMIF(OFFSET('FEB-22'!$A$1,MATCH(Sheet1!$A$1,'FEB-22'!$A:$A,0),5,22,1),{"LI*1"},OFFSET('FEB-22'!$A$1,MATCH(Sheet1!$A$1,'FEB-22'!$A:$A,0),6,22,1))),0) -> 0 | O16: {=IFERROR(SUM(SUMIF(OFFSET('FEB-22'!$A$1,MATCH(Sheet1!$A$1,'FEB-22'!$A:$A,0),2,22,1),{"HB*USE","HB*INT"},OFFSET('FEB-22'!$A$1,MATCH(Sheet1!$A$1,'FEB-22'!$A:$A,0),3,22,1))),0)} -> 0 | P16: {=IFERROR(SUM(SUMIF(OFFSET('FEB-22'!$A$1,MATCH(Sheet1!$A$1,'FEB-22'!$A:$A,0),5,22,1),{"OTHE*1","CO.*1","OTHE*2","WEL*ND","BAN*1","CLU*ND","RD*1","LI*2","MIS*US","*TAINAN*","MCA*INT*","MAIN*NANCE*","*C M Relief Fund*","Co. Op. Hsg Soc.*","GPF_ADV*","Co. Op. Cr. Soc. 2*","DCPS DA","DCPS Pay","MCA Int"},OFFSET('FEB-22'!$A$1,MATCH(Sheet1!$A$1,'FEB-22'!$A:$A,0),6,22,1)))+SUM(SUMIF(OFFSET('FEB-22'!$A$1,MATCH(Sheet1!$A$1,'FEB-22'!$A:$A,0),2,22,1),{"MCA","COM*DV*","HB*ND","CO*SOC","HRR","SRV*H","ACC*CY","F.A","STAMP_REVENUE","*C M Relief Fund*","GPF_ADV*","Co. Op. Cr. Soc. 2*","DCPS DA","DCPS Pay","MCA Int"},OFFSET('FEB-22'!$A$1,MATCH(Sheet1!$A$1,'FEB-22'!$A:$A,0),3,22,1))),0)} -> 0 | Q16: =+J16-H16-K16-L16-M16-N16-O16-P16-R16 -> 0 | R16: {=IFERROR(SUM(SUMIF(OFFSET('FEB-22'!$A$1,MATCH(Sheet1!$A$1,'FEB-22'!$A:$A,0),2,22,1),{"*I. *ax*"},OFFSET('FEB-22'!$A$1,MATCH(Sheet1!$A$1,'FEB-22'!$A:$A,0),3,22,1))),0)} -> 0 | S16: {=+IFERROR(IF(OFFSET('FEB-22'!$B$1,MATCH(Sheet1!A1,'FEB-22'!B:B,0)-2,0,1,1)=Sheet1!J16,IF(MID(IFERROR(OFFSET('FEB-22'!$B$1,MATCH(Sheet1!A1,'FEB-22'!$B:$B,0)-1,-1,1,1),"GROSS ERROR"),11,FIND(" ",OFFSET('FEB-22'!$B$1,MATCH(Sheet1!A1,'FEB-22'!$B:$B,0)-1,-1,1,1),12)-11)-Q16=0,"","NET MISMATCH"),"GROSS MISMATCH"),"")} | BH16: =+G2 -> PAN | BI16: =+A1 -> 0 | BJ16: {=IFERROR(OFFSET('FEB-22'!$B$1,MATCH(Sheet1!A1,'FEB-22'!$B:$B,0)+1,0,1,1),"")} | BK16: =+J16 -> 0 | BL16: =+R16 -> 0 | BM16: {=IFERROR(OFFSET('FEB-22'!$A$1,MATCH(Sheet1!A1,'FEB-22'!$A:$A,0)-2,0,1,1),"")}
A17: 13 | B17: SUPP | C17: =IFERROR(SUM(SUMIF(OFFSET(SUPP!$A$1,MATCH(Sheet1!A1,SUPP!$A:$A,0),0,22,1),{"BA*C","BASIC??"},OFFSET(SUPP!$A$1,MATCH(Sheet1!A1,SUPP!$A:$A,0),1,22,1))),0) -> 0 | D17: {=+IFERROR(SUM(SUMIF(OFFSET(SUPP!$A$1,MATCH(Sheet1!A1,SUPP!$A:$A,0),0,22,1),{"DA*C","D. *"},OFFSET(SUPP!$A$1,MATCH(Sheet1!A1,SUPP!$A:$A,0),1,22,1))),0)} -> 0 | E17: =IFERROR(SUM(SUMIF(OFFSET(SUPP!$A$1,MATCH(Sheet1!A1,SUPP!$A:$A,0),0,22,1),{"H. R. A."},OFFSET(SUPP!$A$1,MATCH(Sheet1!A1,SUPP!$A:$A,0),1,22,1))),0) -> 0 | F17: {=IFERROR(SUM(SUMIF(OFFSET(SUPP!$A$1,MATCH(Sheet1!A1,SUPP!$A:$A,0),0,22,1),{"SP*AY*","S D A*","O.A.*","CLA (5th Pay)*","REF. Allow*","Trans.Allw.*","LF*","P. O.*","ARM*","Conv.A*","Otr.Allow*","Trans_Arrear*","BMIA*","Incentives*","Fit Allow*","KMA","NON-*","U.*","ME*A","PG*","Per.Tra"},OFFSET(SUPP!$A$1,MATCH(Sheet1!A1,SUPP!$A:$A,0),1,22,1))),0)} -> 0 | G17: =+IFERROR(SUM(SUMIF(OFFSET(SUPP!$A$1,MATCH(Sheet1!A1,SUPP!$A:$A,0),0,22,1),{"WA"},OFFSET(SUPP!$A$1,MATCH(Sheet1!A1,SUPP!$A:$A,0),1,22,1))),0) -> 0 | H17: {=+IFERROR(SUM(SUMIF(OFFSET(SUPP!$A$1,MATCH(Sheet1!A1,SUPP!$A:$A,0),0,22,1),{"DCPS","GROSS_ADJUST"},OFFSET(SUPP!$A$1,MATCH(Sheet1!A1,SUPP!$A:$A,0),1,22,1))),0)} -> 0 | I17: {=+IFERROR(SUM(SUMIF(OFFSET(SUPP!$A$1,MATCH(Sheet1!A1,SUPP!$A:$A,0),0,22,1),{"Basic*Arr*","7th Pay* Arr*"},OFFSET(SUPP!$A$1,MATCH(Sheet1!A1,SUPP!$A:$A,0),1,22,1))),0)} -> 0 | J17: =SUM(C17:I17) -> 0 | K17: {=+IFERROR(SUM(SUMIF(OFFSET(SUPP!$A$1,MATCH(Sheet1!A1,SUPP!$A:$A,0),2,22,1),{"*Pro*ax*"},OFFSET(SUPP!$A$1,MATCH(Sheet1!A1,SUPP!$A:$A,0),3,22,1))),0)} -> 0 | L17: =IFERROR(SUM(SUMIF(OFFSET(SUPP!$A$1,MATCH(Sheet1!A1,SUPP!$A:$A,0),2,22,1),{"GPF_G*","DCPS"},OFFSET(SUPP!$A$1,MATCH(Sheet1!A1,SUPP!$A:$A,0),3,22,1))),0) -> 0 | M17: {=+IFERROR(SUM(SUMIF(OFFSET(SUPP!$A$1,MATCH(Sheet1!A1,SUPP!$A:$A,0),2,22,1),{"*GIS","GIS*R"},OFFSET(SUPP!$A$1,MATCH(Sheet1!A1,SUPP!$A:$A,0),3,22,1))),0)} -> 0 | N17: {=+IFERROR(SUM(SUMIF(OFFSET(SUPP!$A$1,MATCH(Sheet1!A1,SUPP!$A:$A,0),5,22,1),{"LI*1"},OFFSET(SUPP!$A$1,MATCH(Sheet1!A1,SUPP!$A:$A,0),6,22,1))),0)} -> 0 | O17: {=+IFERROR(SUM(SUMIF(OFFSET(SUPP!$A$1,MATCH(Sheet1!A1,SUPP!$A:$A,0),2,22,1),{"HB*USE","HB*INT"},OFFSET(SUPP!$A$1,MATCH(Sheet1!A1,SUPP!$A:$A,0),3,22,1))),0)} -> 0 | P17: {=IFERROR(SUM(SUMIF(OFFSET(SUPP!$A$1,MATCH(Sheet1!A1,SUPP!$A:$A,0),5,22,1),{"OTHE*1","CO.*1","OTHE*2","WEL*ND","BAN*1","CLU*ND","RD*1","LI*2","MIS*US","*TAINAN*","MCA*INT*","MAIN*NANCE*","*C M Relief Fund*","Co. Op. Hsg Soc.*","GPF_ADV*","Co. Op. Cr. Soc. 2*","DCPS DA","DCPS Pay","MCA Int"},OFFSET(SUPP!$A$1,MATCH(Sheet1!A1,SUPP!$A:$A,0),6,22,1)))+SUM(SUMIF(OFFSET(SUPP!$A$1,MATCH(Sheet1!A1,SUPP!$A:$A,0),2,22,1),{"MCA","COM*DV*","HB*ND","CO*SOC","HRR","SRV*H","ACC*CY","F.A","STAMP_REVENUE","*C M Relief Fund*","GPF_ADV*","Co. Op. Cr. Soc. 2*","DCPS DA","DCPS Pay","MCA Int"},OFFSET(SUPP!$A$1,MATCH(Sheet1!A1,SUPP!$A:$A,0),3,22,1))),0)} -> 0 | Q17: =+J17-H17-K17-L17-M17-N17-O17-P17-R17 -> 0 | R17: {=+IFERROR(SUM(SUMIF(OFFSET(SUPP!$A$1,MATCH(Sheet1!A1,SUPP!$A:$A,0),2,22,1),{"*I. *ax*"},OFFSET(SUPP!$A$1,MATCH(Sheet1!A1,SUPP!$A:$A,0),3,22,1))),0)} -> 0 | S17: {=+IFERROR(IF(OFFSET(SUPP!$B$1,MATCH(Sheet1!A1,SUPP!B:B,0)-2,0,1,1)=Sheet1!J17,IF(MID(IFERROR(OFFSET(SUPP!$B$1,MATCH(Sheet1!A1,SUPP!$B:$B,0)-1,-1,1,1),"GROSS ERROR"),11,FIND(" ",OFFSET(SUPP!$B$1,MATCH(Sheet1!A1,SUPP!$B:$B,0)-1,-1,1,1),12)-11)-Q17=0,"","NET MISMATCH"),"GROSS MISMATCH"),"")} | BH17: =+G2 -> PAN | BI17: =+A1 -> 0 | BJ17: {=IFERROR(OFFSET(SUPP!$B$1,MATCH(Sheet1!A1,SUPP!$B:$B,0)+1,0,1,1),"")} | BK17: =+J17 -> 0 | BL17: =+R17 -> 0 | BM17: =IFERROR(OFFSET(SUPP!$A$1,MATCH(Sheet1!A1,SUPP!$A:$A,0)-2,0,1,1),"")
A18: 14 | B18: MED. BILL | C18: 0 | D18: 0 | E18: 0 | F18: 0 | G18: 0 | H18: 0 | I18: =IFERROR(SUM(SUMIF(OFFSET('AUG-21'!$A$1,MATCH(Sheet1!A9,'AUG-21'!$A:$A,0),0,22,1),{"Arr*","7th Pay* Arr*","Basic Arr."},OFFSET('AUG-21'!$A$1,MATCH(Sheet1!A9,'AUG-21'!$A:$A,0),1,22,1))),0) -> 0 | J18: 0 | K18: 0 | L18: 0 | M18: 0 | N18: 0 | O18: 0 | P18: 0 | Q18: =+J18-H18-K18-L18-M18-N18-O18-P18-P38 -> 0 | R18: 0
N19: 0 | O19: 0 | P19: 0 | Q19: =+J19-H19-K19-L19-M19-N19-O19-P19-P39 -> 0 | R19: 0
B20: TOTAL | C20: =SUM(C5:C19) -> 0 | D20: =SUM(D5:D19) -> 0 | E20: =SUM(E5:E19) -> 0 | F20: =SUM(F5:F19) -> 0 | G20: =SUM(G5:G19) -> 0 | H20: =SUM(H5:H19) -> 0 | I20: =SUM(I5:I19) -> 0 | J20: =SUM(J5:J19) -> 0 | ... R20: =SUM(R5:R19) -> 0
B21: GN
B22: NEW
B24: GROSS SALARY | D24: =+J20 -> 0 | G24: SAVINGS U/S. 80C | K24: Taxable Income | M24: =+D35-H37-H46 -> -50000 | AA24: {=+UPPER(G2)} -> PAN | AB24: =+UPPER(A1) -> 0 | AC24: =+M33-M35 -> 0 | AD24: =+R20 -> 0
B25: LESS : | F25: i) | G25: GPF/DCPS Employee | H25: =+IF(H20>0,L20-H40,L20) -> 0 | K25: Old Tax Regime | M25: =IF(AND(N3="M",M24<=250000),0,IF(AND(N3="F",M24<=250000),0,IF(AND(N3="M",M24<=500000),ROUND((M24-250000)*5%,0),IF(AND(N3="F",M24<=500000),ROUND((M24-250000)*5%,0),IF(AND(N3="M",M24<=1000000),12500+ROUND((M24-500000)*20%,0),IF(AND(N3="F",M24<=1000000),12500+ROUND((M24-500000)*20%,0),IF(AND(N3="M",M24>=1000000),112500+ROUND((M24-1000000)*30%,0),112500+ROUND((M24-1000000)*30%,0)))))))) -> 0
B26: STD. DED. | D26: 50000 | F26: ii) | G26: GIS | H26: =+M20 -> 0 | K26: New Tax Regime | M26: =+IF(AND(B21="GN",(D24-H41)<=250000,B22="OLD"),0,IF(AND(B21="SC",(D24-H41)<=300000,B22="OLD"),0,IF(AND(B21="SSC",(D24-H41)<=500000,B22="OLD"),0,IF(AND(B21="GN",B22="OLD",(D24-H41)<=500000),ROUND(((D24-H41)-250000)*5%,0),IF(AND(B22="OLD",B21="SC",(D24-H41)<=500000),ROUND(((D24-H41)-300000)*5%,0),IF(AND(B22="OLD",(D24-H41)<=1000000,B21="GN"),ROUND(((D24-H41)-500000)*20%+(12500),0),IF(AND(B21="SC",B22="OLD",(D24-H41)<=1000000),ROUND(((D24-H41)-500000)*20%+(10000),0),IF(AND(B21="SSC",B22="OLD",(D24-H41)<=1000000),ROUND(((D24-H41)-500000)*20%,0),IF(AND(B22="OLD",B21="GN",(D24-H41)>1000000),ROUND(((D24-H41)-1000000)*30%+(112500),0),IF(AND(B22="OLD",B21="SC",(D24-H41)>1000000),ROUND(((D24-H41)-1000000)*30%+(110000),0),IF(AND(B21="SSC",B22="OLD",(D24-H41)>1000000),ROUND(((D24-H41)-1000000)*30%+(100000),0),IF(AND(B22="NEW",(D24-H41)<=250000),0,IF(AND(B22="NEW",(D24-H41)<=500000),ROUND(((D24-H41)-250000)*5%,0),IF(AND(B22="NEW",(D24-H41)<=750000),ROUND(((D24-H41)-500000)*10%+(12500),0),IF(AND(B22="NEW",(D24-H41)<=1000000),ROUND(((D24-H41)-750000)*15%+(37500),0),IF(AND(B22="NEW",(D24-H41)<=1250000),ROUND(((D24-H41)-1000000)*20%+(75000),0),IF(AND(B22="NEW",(D24-H41)<=1500000),ROUND(((D24-H41)-1250000)*25%+(125000),0),IF(AND(B22="NEW",(D24-H41)>1500000),ROUND(((D24-H41)-1500000)*30%+(187500),0))))))))))))))))))) -> 0
B27: WA | D27: =+G20 -> 0 | F27: iii) | G27: L.I.C. [Salary] | H27: =+N20 -> 0
B28: Professional Tax | D28: =+K20 -> 0 | F28: iv | G28: L.I.C. [Individual] | H28: 0 | K28: Tax on Total Income | M28: =+IF(M25>M26,M26,M25) -> 0
B29: Other Allowance | D29: 0 | F29: v) | G29: Housing Loan Principal | H29: =+IF(O4="HBA HOUSE",O20,0) -> 0
B30: H. R. A. Exempt | D30: =IF(C42=0,0,MIN(D39:D43)) -> 0 | F30: vi) | G30: Educational Fees | H30: 0 | K30: (-) : Rebate 87 | M30: =IF(M24>500000,0,IF(M28>=12500,12500,M28)) -> 0
B31: B.D.D.S Allowance | D31: 0 | F31: vii) | G31: Mutual Fund | H31: 0 | K31: Tax on Total Inc. | M31: =+M28-M30 -> 0
B32: House Loan Int. | D32: =+IF(O4=B32,O20,0) -> 0 | F32: viii) | G32: PLI | H32: 0 | K32: (+) 4% Edu.Cess | M32: =ROUND(M31*4%,0) -> 0
F33: ix) | G33: Sukanya Yojna | H33: 0 | K33: Tax Payable | M33: =+M31+M32 -> 0
B34: Total Deductions | D34: =SUM(D26:D31)+IF(D32>200000, 200000,D32 ) -> 50000 | F34: x) | G34: PPF | H34: 0 | K34: (-) Already paid | M34: =+R20 -> 0
B35: BALANCE | D35: =+D24-D34 -> -50000 | F35: xI) | G35: SBI Life Insurance | H35: 0 | K35: (-) Relief 89 | M35: 0
G36: Total Savings | H36: =SUM(H25:H35) -> 0
G37: Eligible Savings | H37: =+IF(H36<=150000,H36,150000) -> 0
B38: HRA CALCULATION | K38: Total Tax Payable | M38: =+M33-M34-M35 -> 0
B39: HRA RECEIVED | D39: =+E20 -> 0 | G39: SAVINGS CHAPTER VIA
B40: BASIC + DA 40 % | D40: =+(C20+D20)*40/100 -> 0 | F40: i) | G40: 80CCD (1B) | H40: =+IF(AND(H20>0,L20>50000),50000,IF(H20>0,L20,0)) -> 0
B41: BASIC +DA 10 % | C41: =+(C20+D20)*10/100 -> 0 | F41: ii) | G41: DCPS Employer | H41: =+H20 -> 0
B42: RENT PAID | C42: 0 | F42: iii) | G42: 80G /( C. M. Fund) | H42: {=IFERROR(SUM(SUMIF(OFFSET('MAY-21'!$A$1,MATCH(Sheet1!A1,'MAY-21'!$A:$A,0),5,22,1),{"*C M Relief Fund*"},OFFSET('MAY-21'!$A$1,MATCH(Sheet1!A1,'MAY-21'!$A:$A,0),6,22,1)))+SUM(SUMIF(OFFSET('MAY-21'!$A$1,MATCH(Sheet1!A1,'MAY-21'!$A:$A,0),2,22,1),{"*C M Relief Fund*"},OFFSET('MAY-21'!$A$1,MATCH(Sheet1!A1,'MAY-21'!$A:$A,0),3,22,1))),0)} -> 0
B43: BASIC +DA 10 % - RENT PAID | D43: =+IF(C42>C41,C42-C41, 0) -> 0 | F43: iv) | G43: 80D - Mediclaim Policy | H43: 0
F44: v) | G44: 80U - Handicapped | H44: 0
F45: vi) | G45: 80E - Edu. Loan Intrest | H45: 0
H46: =SUM(H40:H45) -> 0
A47: =+INDEX('EMP NAMES'!D:D,Sheet1!U51) | I47: =+IF(M71=M74,"OLD","NEW") -> OLD
G48: =IFERROR(INDEX('EMP NAMES'!E:E,Sheet1!U51),"PAN") -> PAN
N49: M
A50: SR. | B50: MONTH | C50: BASIC | D50: DA | E50: H. R. A. | F50: TA/SDA/CLA/RA/ETC | G50: WA | H50: DCPS Employer | I50: Basic Arr. / 7th Pay DCPS/NPS Arr | J50: Total Emolument | K50: PT | L50: GPF/DCPS Employee | M50: GIS | N50: LIC | O50: HBA HOUSE | P50: OTHER | Q50: NET | R50: I. TAX | S50: GROSS TOTAL ERROR | U50: SR | V50: 115BAC Section Applicable (New Tax Regime) | W50: PAN NO. | X50: NAME OF EMPLOYEE | Y50: Salary as per provisions contained in section 17(1) | Z50: Value of perquisites [section 17(2)] (as per FormNo.12BA, wherever applicable) | AA50: Reported total amount of salary received from other employer(s) | AB50: GROSS SALARY | AC50: STD DED | AD50: PT | AE50: HRA | AF50: OTHER ALLOWANCES 10 | AG50: NET | AH50: HSG. INT | AI50: OTHER INCOME | AJ50: NET | AK50: 80C INVESTMENT | AL50: 80C ELIGIBLE | AM50: 80CCD1 GROSS | AN50: 80CCD1 ELIGIBLE | AO50: 80CCD1(B) ELIGIBLE | AP50: 80CCD2 ELIGIBLE | AQ50: 80D | AR50: 80E | AS50: 80G | AT50: OTHERS | AU50: TOTAL ELIGIBLE SAVING | AV50: TAXABLE | AW50: TAX | AX50: REBATE | AY50: CESS | AZ50: RELIEF | BA50: TOTAL TAX | BB50: TDS-CURRENT | BC50: TDS-PREV. | BD50: TOTAL | BE50: R/P
A51: 1 | B51: 44256 | C51: =IFERROR(SUM(SUMIF(OFFSET('MAR-21'!$A$1,MATCH(Sheet1!A47,'MAR-21'!$A:$A,0),0,22,1),{"BA*C","BASIC??"},OFFSET('MAR-21'!$A$1,MATCH(Sheet1!A47,'MAR-21'!$A:$A,0),1,22,1))),0) -> 0 | D51: =IFERROR(SUM(SUMIF(OFFSET('MAR-21'!$A$1,MATCH(Sheet1!A47,'MAR-21'!$A:$A,0),0,22,1),{"DA*C","D. *"},OFFSET('MAR-21'!$A$1,MATCH(Sheet1!A47,'MAR-21'!$A:$A,0),1,22,1))),0) -> 0 | E51: =IFERROR(SUM(SUMIF(OFFSET('MAR-21'!$A$1,MATCH(Sheet1!A47,'MAR-21'!$A:$A,0),0,22,1),{"H. R. A."},OFFSET('MAR-21'!$A$1,MATCH(Sheet1!A47,'MAR-21'!$A:$A,0),1,22,1))),0) -> 0 | F51: {=IFERROR(SUM(SUMIF(OFFSET('MAR-21'!$A$1,MATCH(Sheet1!A47,'MAR-21'!$A:$A,0),0,22,1),{"SP*AY*","S D A*","O.A.*","CLA (5th Pay)*","REF. Allow*","Trans.Allw.*","LF*","P. O.*","ARM*","Conv.A*","Otr.Allow*","Trans_Arrear*","BMIA*","Incentives*","Fit Allow*","KMA","NON-*","U.*","ME*A","PG*","Per.Tra"},OFFSET('MAR-21'!$A$1,MATCH(Sheet1!A47,'MAR-21'!$A:$A,0),1,22,1))),0)} -> 0 | G51: =IFERROR(SUM(SUMIF(OFFSET('MAR-21'!$A$1,MATCH(Sheet1!A47,'MAR-21'!$A:$A,0),0,22,1),{"WA"},OFFSET('MAR-21'!$A$1,MATCH(Sheet1!A47,'MAR-21'!$A:$A,0),1,22,1))),0) -> 0 | H51: =IFERROR(SUM(SUMIF(OFFSET('MAR-21'!$A$1,MATCH(Sheet1!A47,'MAR-21'!$A:$A,0),0,22,1),{"DCPS","GROSS_ADJUST"},OFFSET('MAR-21'!$A$1,MATCH(Sheet1!A47,'MAR-21'!$A:$A,0),1,22,1))),0) -> 0 | I51: {=+IFERROR(SUM(SUMIF(OFFSET('MAR-21'!$A$1,MATCH(Sheet1!A47,'MAR-21'!$A:$A,0),0,22,1),{"Basic*Arr*","7th Pay* Arr*"},OFFSET('MAR-21'!$A$1,MATCH(Sheet1!A47,'MAR-21'!$A:$A,0),1,22,1))),0)} -> 0 | J51: =+SUM(C51:I51) -> 0 | K51: =IFERROR(SUM(SUMIF(OFFSET('MAR-21'!$A$1,MATCH(Sheet1!A47,'MAR-21'!$A:$A,0),2,22,1),{"*Pro*ax*"},OFFSET('MAR-21'!$A$1,MATCH(Sheet1!A47,'MAR-21'!$A:$A,0),3,22,1))),0) -> 0 | L51: =IFERROR(SUM(SUMIF(OFFSET('MAR-21'!$A$1,MATCH(Sheet1!A47,'MAR-21'!$A:$A,0),2,22,1),{"GPF_G*","DCPS"},OFFSET('MAR-21'!$A$1,MATCH(Sheet1!A47,'MAR-21'!$A:$A,0),3,22,1))),0) -> 0 | M51: =IFERROR(SUM(SUMIF(OFFSET('MAR-21'!$A$1,MATCH(Sheet1!A47,'MAR-21'!$A:$A,0),2,22,1),{"*GIS","GIS*R"},OFFSET('MAR-21'!$A$1,MATCH(Sheet1!A47,'MAR-21'!$A:$A,0),3,22,1))),0) -> 0 | N51: =IFERROR(SUM(SUMIF(OFFSET('MAR-21'!$A$1,MATCH(Sheet1!A47,'MAR-21'!$A:$A,0),5,22,1),{"LI*1"},OFFSET('MAR-21'!$A$1,MATCH(Sheet1!A47,'MAR-21'!$A:$A,0),6,22,1))),0) -> 0 | O51: {=IFERROR(SUM(SUMIF(OFFSET('MAR-21'!$A$1,MATCH(Sheet1!A47,'MAR-21'!$A:$A,0),2,22,1),{"*HB*USE","HB*INT"},OFFSET('MAR-21'!$A$1,MATCH(Sheet1!A47,'MAR-21'!$A:$A,0),3,22,1))),0)} -> 0 | P51: {=IFERROR(SUM(SUMIF(OFFSET('MAR-21'!$A$1,MATCH(Sheet1!A47,'MAR-21'!$A:$A,0),5,22,1),{"OTHE*1","CO.*1","OTHE*2","WEL*ND","BAN*1","CLU*ND","RD*1","LI*2","MIS*US","*TAINAN*","MCA*INT*","MAIN*NANCE*","*C M Relief Fund*","Co. Op. Hsg Soc.*","GPF_ADV*","Co. Op. Cr. Soc. 2*","DCPS DA","DCPS Pay","MCA Int"},OFFSET('MAR-21'!$A$1,MATCH(Sheet1!A47,'MAR-21'!$A:$A,0),6,22,1)))+SUM(SUMIF(OFFSET('MAR-21'!$A$1,MATCH(Sheet1!A47,'MAR-21'!$A:$A,0),2,22,1),{"MCA","COM*DV*","HB*ND","CO*SOC","HRR","SRV*H","ACC*CY","F.A","STAMP_REVENUE","*C M Relief Fund*","GPF_ADV*","Co. Op. Cr. Soc. 2*","DCPS DA","DCPS Pay","MCA Int"},OFFSET('MAR-21'!$A$1,MATCH(Sheet1!A47,'MAR-21'!$A:$A,0),3,22,1))),0)} -> 0 | Q51: =+J51-H51-K51-L51-M51-N51-O51-P51-R51 -> 0 | R51: =IFERROR(SUM(SUMIF(OFFSET('MAR-21'!$A$1,MATCH(Sheet1!A47,'MAR-21'!$A:$A,0),2,22,1),{"*I.*ax*"},OFFSET('MAR-21'!$A$1,MATCH(Sheet1!A47,'MAR-21'!$A:$A,0),3,22,1))),0) -> 0 | S51: {=+IFERROR(IF(OFFSET('MAR-21'!$B$1,MATCH(Sheet1!A47,'MAR-21'!B:B,0)-2,0,1,1)=Sheet1!J51,IF(MID(IFERROR(OFFSET('MAR-21'!$B$1,MATCH(Sheet1!A47,'MAR-21'!$B:$B,0)-1,-1,1,1),"GROSS ERROR"),11,FIND(" ",OFFSET('MAR-21'!$B$1,MATCH(Sheet1!A47,'MAR-21'!$B:$B,0)-1,-1,1,1),12)-11)-Q51=0,"","NET MISMATCH"),"GROSS MISMATCH"),"")} | U51: =+U5+1 -> 3 | V51: =+IF(M71=M74,"NO","YES") -> NO | W51: =+G48 -> PAN | X51: =+A47 | Y51: =+D70 -> 0 | Z51: 0 | AA51: 0 | AB51: =+SUM(Y51:AA51) -> 0 | AC51: =+D72 -> 50000 | AD51: =+D74 -> 0 | AE51: =+D76 -> 0 | AF51: =+D75+D73+D77 -> 0 | AG51: =+AB51-SUM(AC51:AF51) -> -50000 | AH51: =+IF(D78>=200000,-200000,-D78) -> 0 | AI51: 0 | AJ51: =+AG51+AH51+AI51 -> -50000 | AK51: =+IF(H87>0,H82-H71,H82) -> 0 | AL51: {=+IF(IF(AND((AK51+AN51)>=150000,AK51>=150000),150000-AN51,AK51)<0,0,IF(AND((AK51+AN51)>=150000,AK51>=150000),150000-AN51,IF(AND(SUM(AK51+AN51)>150000,AK51<150000),150000-AN51,AK51)))} -> 0 | AM51: =+IF(H66>0,L66,0) -> 0 | AN51: =+AM51-AO51 -> 0 | AO51: =+IF(AND(H66>0,L66>50000),50000,IF(H66>0,L66,0)) -> 0 | AP51: =+H66 -> 0 | AQ51: =+H89 -> 0 | AR51: =+H91 -> 0 | AS51: =+H88 -> 0 | AT51: =+H90 -> 0 | AU51: =+SUM(AQ51:AT51)+AP51+AO51+AN51+AL51 -> 0 | AV51: =+AJ51-AU51 -> -50000 | AW51: =+M74 -> 0 | AX51: =+M76 -> 0 | AY51: =+M78 -> 0 | AZ51: =+M81 -> 0 | BA51: =+AW51-AX51+AY51-AZ51 -> 0 | BB51: =+M80 -> 0 | BC51: 0 | BD51: =+BB51+BC51 -> 0 | BE51: =+BA51-BD51 -> 0 | BF51: =+IF(AV51=M70,"","NOT OK") | BH51: =+G48 -> PAN | BI51: =+A47 | BJ51: {=IFERROR(OFFSET('MAR-21'!$B$1,MATCH(Sheet1!A47,'MAR-21'!$B:$B,0)+1,0,1,1),"")} | BK51: =+J51 -> 0 | BL51: =+R51 -> 0 | BM51: {=IFERROR(OFFSET('MAR-21'!$A$1,MATCH(Sheet1!A47,'MAR-21'!$A:$A,0)-2,0,1,1),"")}
A52: 2 | B52: 44287 | C52: =IFERROR(SUM(SUMIF(OFFSET('APR-21'!$A$1,MATCH(Sheet1!A47,'APR-21'!$A:$A,0),0,22,1),{"BA*C","BASIC??"},OFFSET('APR-21'!$A$1,MATCH(Sheet1!A47,'APR-21'!$A:$A,0),1,22,1))),0) -> 0 | D52: =IFERROR(SUM(SUMIF(OFFSET('APR-21'!$A$1,MATCH(Sheet1!A47,'APR-21'!$A:$A,0),0,22,1),{"DA*C","D. *"},OFFSET('APR-21'!$A$1,MATCH(Sheet1!A47,'APR-21'!$A:$A,0),1,22,1))),0) -> 0 | E52: =IFERROR(SUM(SUMIF(OFFSET('APR-21'!$A$1,MATCH(Sheet1!A47,'APR-21'!$A:$A,0),0,22,1),{"H. R. A."},OFFSET('APR-21'!$A$1,MATCH(Sheet1!A47,'APR-21'!$A:$A,0),1,22,1))),0) -> 0 | F52: =IFERROR(SUM(SUMIF(OFFSET('APR-21'!$A$1,MATCH(Sheet1!A47,'APR-21'!$A:$A,0),0,22,1),{"SP*AY*","S D A*","O.A.*","CLA (5th Pay)*","REF. Allow*","Trans.Allw.*","LF*","P. O.*","ARM*","Conv.A*","Otr.Allow*","Trans_Arrear*","BMIA*","Incentives*","Fit Allow*","KMA","NON-*","U.*","ME*A","PG*","Per.Tra"},OFFSET('APR-21'!$A$1,MATCH(Sheet1!A47,'APR-21'!$A:$A,0),1,22,1))),0) -> 0 | G52: =IFERROR(SUM(SUMIF(OFFSET('APR-21'!$A$1,MATCH(Sheet1!A47,'APR-21'!$A:$A,0),0,22,1),{"WA"},OFFSET('APR-21'!$A$1,MATCH(Sheet1!A47,'APR-21'!$A:$A,0),1,22,1))),0) -> 0 | H52: =IFERROR(SUM(SUMIF(OFFSET('APR-21'!$A$1,MATCH(Sheet1!A47,'APR-21'!$A:$A,0),0,22,1),{"DCPS","GROSS_ADJUST"},OFFSET('APR-21'!$A$1,MATCH(Sheet1!A47,'APR-21'!$A:$A,0),1,22,1))),0) -> 0 | I52: {=+IFERROR(SUM(SUMIF(OFFSET('APR-21'!$A$1,MATCH(Sheet1!A47,'APR-21'!$A:$A,0),0,22,1),{"Arr*","7th Pay* Arr*","Basic Arr."},OFFSET('APR-21'!$A$1,MATCH(Sheet1!A47,'APR-21'!$A:$A,0),1,22,1))),0)} -> 0 | J52: =SUM(C52:I52) -> 0 | K52: =IFERROR(SUM(SUMIF(OFFSET('APR-21'!$A$1,MATCH(Sheet1!A47,'APR-21'!$A:$A,0),2,22,1),{"*Pro*ax*"},OFFSET('APR-21'!$A$1,MATCH(Sheet1!A47,'APR-21'!$A:$A,0),3,22,1))),0) -> 0 | L52: =IFERROR(SUM(SUMIF(OFFSET('APR-21'!$A$1,MATCH(Sheet1!A47,'APR-21'!$A:$A,0),2,22,1),{"GPF_G*","DCPS"},OFFSET('APR-21'!$A$1,MATCH(Sheet1!A47,'APR-21'!$A:$A,0),3,22,1))),0) -> 0 | M52: =IFERROR(SUM(SUMIF(OFFSET('APR-21'!$A$1,MATCH(Sheet1!A47,'APR-21'!$A:$A,0),2,22,1),{"*GIS","GIS*R"},OFFSET('APR-21'!$A$1,MATCH(Sheet1!A47,'APR-21'!$A:$A,0),3,22,1))),0) -> 0 | N52: =IFERROR(SUM(SUMIF(OFFSET('APR-21'!$A$1,MATCH(Sheet1!A47,'APR-21'!$A:$A,0),5,22,1),{"LI*1"},OFFSET('APR-21'!$A$1,MATCH(Sheet1!A47,'APR-21'!$A:$A,0),6,22,1))),0) -> 0 | O52: {=IFERROR(SUM(SUMIF(OFFSET('APR-21'!$A$1,MATCH(Sheet1!A47,'APR-21'!$A:$A,0),2,22,1),{"HB*USE","HB*INT"},OFFSET('APR-21'!$A$1,MATCH(Sheet1!A47,'APR-21'!$A:$A,0),3,22,1))),0)} -> 0 | P52: {=IFERROR(SUM(SUMIF(OFFSET('APR-21'!$A$1,MATCH(Sheet1!A47,'APR-21'!$A:$A,0),5,22,1),{"OTHE*1","CO.*1","OTHE*2","WEL*ND","BAN*1","CLU*ND","RD*1","LI*2","MIS*US","*TAINAN*","MCA*INT*","MAIN*NANCE*","*C M Relief Fund*","Co. Op. Hsg Soc.*","GPF_ADV*","Co. Op. Cr. Soc. 2*","DCPS DA","DCPS Pay","MCA Int"},OFFSET('APR-21'!$A$1,MATCH(Sheet1!A47,'APR-21'!$A:$A,0),6,22,1)))+SUM(SUMIF(OFFSET('APR-21'!$A$1,MATCH(Sheet1!A47,'APR-21'!$A:$A,0),2,22,1),{"MCA","COM*DV*","HB*ND","CO*SOC","HRR","SRV*H","ACC*CY","F.A","STAMP_REVENUE","*C M Relief Fund*","GPF_ADV*","Co. Op. Cr. Soc. 2*","DCPS DA","DCPS Pay","MCA Int"},OFFSET('APR-21'!$A$1,MATCH(Sheet1!A47,'APR-21'!$A:$A,0),3,22,1))),0)} -> 0 | Q52: =+J52-H52-K52-L52-M52-N52-O52-P52-R52 -> 0 | R52: {=IFERROR(SUM(SUMIF(OFFSET('APR-21'!$A$1,MATCH(Sheet1!A47,'APR-21'!$A:$A,0),2,22,1),{"*I. *ax*"},OFFSET('APR-21'!$A$1,MATCH(Sheet1!A47,'APR-21'!$A:$A,0),3,22,1))),0)} -> 0 | S52: {=+IFERROR(IF(OFFSET('APR-21'!$B$1,MATCH(Sheet1!A47,'APR-21'!B:B,0)-2,0,1,1)=Sheet1!J52,IF(MID(IFERROR(OFFSET('APR-21'!$B$1,MATCH(Sheet1!A47,'APR-21'!$B:$B,0)-1,-1,1,1),"GROSS ERROR"),11,FIND(" ",OFFSET('APR-21'!$B$1,MATCH(Sheet1!A47,'APR-21'!$B:$B,0)-1,-1,1,1),12)-11)-Q52=0,"","NET MISMATCH"),"GROSS MISMATCH"),"")} | BH52: =+G48 -> PAN | BI52: =+A47 | BJ52: {=IFERROR(OFFSET('APR-21'!$B$1,MATCH(Sheet1!A47,'APR-21'!$B:$B,0)+1,0,1,1),"")} | BK52: =+J52 -> 0 | BL52: =+R52 -> 0 | BM52: {=IFERROR(OFFSET('APR-21'!$A$1,MATCH(Sheet1!A47,'APR-21'!$A:$A,0)-2,0,1,1),"")}
A53: 3 | B53: 44317 | C53: =IFERROR(SUM(SUMIF(OFFSET('MAY-21'!$A$1,MATCH(Sheet1!A47,'MAY-21'!$A:$A,0),0,22,1),{"BA*C","BASIC??"},OFFSET('MAY-21'!$A$1,MATCH(Sheet1!A47,'MAY-21'!$A:$A,0),1,22,1))),0) -> 0 | D53: =IFERROR(SUM(SUMIF(OFFSET('MAY-21'!$A$1,MATCH(Sheet1!A47,'MAY-21'!$A:$A,0),0,22,1),{"DA*C","D. *"},OFFSET('MAY-21'!$A$1,MATCH(Sheet1!A47,'MAY-21'!$A:$A,0),1,22,1))),0) -> 0 | E53: =IFERROR(SUM(SUMIF(OFFSET('MAY-21'!$A$1,MATCH(Sheet1!A47,'MAY-21'!$A:$A,0),0,22,1),{"H. R. A."},OFFSET('MAY-21'!$A$1,MATCH(Sheet1!A47,'MAY-21'!$A:$A,0),1,22,1))),0) -> 0 | F53: {=IFERROR(SUM(SUMIF(OFFSET('MAY-21'!$A$1,MATCH(Sheet1!A47,'MAY-21'!$A:$A,0),0,22,1),{"SP*AY*","S D A*","O.A.*","CLA (5th Pay)*","REF. Allow*","Trans.Allw.*","LF*","P. O.*","ARM*","Conv.A*","Otr.Allow*","Trans_Arrear*","BMIA*","Incentives*","Fit Allow*","KMA","NON-*","U.*","ME*A","PG*","Per.Tra"},OFFSET('MAY-21'!$A$1,MATCH(Sheet1!A47,'MAY-21'!$A:$A,0),1,22,1))),0)} -> 0 | G53: =IFERROR(SUM(SUMIF(OFFSET('MAY-21'!$A$1,MATCH(Sheet1!A47,'MAY-21'!$A:$A,0),0,22,1),{"WA"},OFFSET('MAY-21'!$A$1,MATCH(Sheet1!A47,'MAY-21'!$A:$A,0),1,22,1))),0) -> 0 | H53: =IFERROR(SUM(SUMIF(OFFSET('MAY-21'!$A$1,MATCH(Sheet1!A47,'MAY-21'!$A:$A,0),0,22,1),{"DCPS","GROSS_ADJUST"},OFFSET('MAY-21'!$A$1,MATCH(Sheet1!A47,'MAY-21'!$A:$A,0),1,22,1))),0) -> 0 | I53: {=+IFERROR(SUM(SUMIF(OFFSET('MAY-21'!$A$1,MATCH(Sheet1!A47,'MAY-21'!$A:$A,0),0,22,1),{"Arr*","7th Pay* Arr*","Basic Arr.","DA Arr"},OFFSET('MAY-21'!$A$1,MATCH(Sheet1!A47,'MAY-21'!$A:$A,0),1,22,1))),0)} -> 0 | J53: =SUM(C53:I53) -> 0 | K53: =IFERROR(SUM(SUMIF(OFFSET('MAY-21'!$A$1,MATCH(Sheet1!A47,'MAY-21'!$A:$A,0),2,22,1),{"*Pro*ax*"},OFFSET('MAY-21'!$A$1,MATCH(Sheet1!A47,'MAY-21'!$A:$A,0),3,22,1))),0) -> 0 | L53: =IFERROR(SUM(SUMIF(OFFSET('MAY-21'!$A$1,MATCH(Sheet1!A47,'MAY-21'!$A:$A,0),2,22,1),{"GPF_G*","DCPS"},OFFSET('MAY-21'!$A$1,MATCH(Sheet1!A47,'MAY-21'!$A:$A,0),3,22,1))),0) -> 0 | M53: =IFERROR(SUM(SUMIF(OFFSET('MAY-21'!$A$1,MATCH(Sheet1!A47,'MAY-21'!$A:$A,0),2,22,1),{"*GIS","GIS*R"},OFFSET('MAY-21'!$A$1,MATCH(Sheet1!A47,'MAY-21'!$A:$A,0),3,22,1))),0) -> 0 | N53: =IFERROR(SUM(SUMIF(OFFSET('MAY-21'!$A$1,MATCH(Sheet1!A47,'MAY-21'!$A:$A,0),5,22,1),{"LI*1"},OFFSET('MAY-21'!$A$1,MATCH(Sheet1!A47,'MAY-21'!$A:$A,0),6,22,1))),0) -> 0 | O53: {=IFERROR(SUM(SUMIF(OFFSET('MAY-21'!$A$1,MATCH(Sheet1!A47,'MAY-21'!$A:$A,0),2,22,1),{"HB*USE","HB*INT"},OFFSET('MAY-21'!$A$1,MATCH(Sheet1!A47,'MAY-21'!$A:$A,0),3,22,1))),0)} -> 0 | P53: {=IFERROR(SUM(SUMIF(OFFSET('MAY-21'!$A$1,MATCH(Sheet1!A47,'MAY-21'!$A:$A,0),5,22,1),{"OTHE*1","CO.*1","OTHE*2","WEL*ND","BAN*1","CLU*ND","RD*1","LI*2","MIS*US","*TAINAN*","MCA*INT*","MAIN*NANCE*","*C M Relief Fund*","Co. Op. Hsg Soc.*","GPF_ADV*","Co. Op. Cr. Soc. 2*","DCPS DA","DCPS Pay","MCA Int"},OFFSET('MAY-21'!$A$1,MATCH(Sheet1!A47,'MAY-21'!$A:$A,0),6,22,1)))+SUM(SUMIF(OFFSET('MAY-21'!$A$1,MATCH(Sheet1!A47,'MAY-21'!$A:$A,0),2,22,1),{"MCA","COM*DV*","HB*ND","CO*SOC","HRR","SRV*H","ACC*CY","F.A","STAMP_REVENUE","*C M Relief Fund*","GPF_ADV*","Co. Op. Cr. Soc. 2*","DCPS DA","DCPS Pay","MCA Int"},OFFSET('MAY-21'!$A$1,MATCH(Sheet1!A47,'MAY-21'!$A:$A,0),3,22,1))),0)} -> 0 | Q53: =+J53-H53-K53-L53-M53-N53-O53-P53-R53 -> 0 | R53: =IFERROR(SUM(SUMIF(OFFSET('MAY-21'!$A$1,MATCH(Sheet1!A47,'MAY-21'!$A:$A,0),2,22,1),{"*I. *ax*"},OFFSET('MAY-21'!$A$1,MATCH(Sheet1!A47,'MAY-21'!$A:$A,0),3,22,1))),0) -> 0 | S53: {=+IFERROR(IF(OFFSET('MAY-21'!$B$1,MATCH(Sheet1!A47,'MAY-21'!B:B,0)-2,0,1,1)=Sheet1!J53,IF(MID(IFERROR(OFFSET('MAY-21'!$B$1,MATCH(Sheet1!A47,'MAY-21'!$B:$B,0)-1,-1,1,1),"GROSS ERROR"),11,FIND(" ",OFFSET('MAY-21'!$B$1,MATCH(Sheet1!A47,'MAY-21'!$B:$B,0)-1,-1,1,1),12)-11)-Q53=0,"","NET MISMATCH"),"GROSS MISMATCH"),"")} | BH53: =+G48 -> PAN | BI53: =+A47 | BJ53: {=IFERROR(OFFSET('MAY-21'!$B$1,MATCH(Sheet1!A47,'MAY-21'!$B:$B,0)+1,0,1,1),"")} | BK53: =+J53 -> 0 | BL53: =+R53 -> 0 | BM53: {=+IFERROR(OFFSET('MAY-21'!$A$1,MATCH(Sheet1!A47,'MAY-21'!$A:$A,0)-2,0,1,1),"")}
A54: 4 | B54: 44348 | C54: =IFERROR(SUM(SUMIF(OFFSET('JUN-21'!$A$1,MATCH(Sheet1!A47,'JUN-21'!$A:$A,0),0,22,1),{"BA*C","BASIC??"},OFFSET('JUN-21'!$A$1,MATCH(Sheet1!A47,'JUN-21'!$A:$A,0),1,22,1))),0) -> 0 | D54: =IFERROR(SUM(SUMIF(OFFSET('JUN-21'!$A$1,MATCH(Sheet1!A47,'JUN-21'!$A:$A,0),0,22,1),{"DA*C","D. *"},OFFSET('JUN-21'!$A$1,MATCH(Sheet1!A47,'JUN-21'!$A:$A,0),1,22,1))),0) -> 0 | E54: =IFERROR(SUM(SUMIF(OFFSET('JUN-21'!$A$1,MATCH(Sheet1!A47,'JUN-21'!$A:$A,0),0,22,1),{"H. R. A."},OFFSET('JUN-21'!$A$1,MATCH(Sheet1!A47,'JUN-21'!$A:$A,0),1,22,1))),0) -> 0 | F54: {=IFERROR(SUM(SUMIF(OFFSET('JUN-21'!$A$1,MATCH(Sheet1!A47,'JUN-21'!$A:$A,0),0,22,1),{"SP*AY*","S D A*","O.A.*","CLA (5th Pay)*","REF. Allow*","Trans.Allw.*","LF*","P. O.*","ARM*","Conv.A*","Otr.Allow*","Trans_Arrear*","BMIA*","Incentives*","Fit Allow*","KMA","NON-*","U.*","ME*A","PG*","Per.Tra"},OFFSET('JUN-21'!$A$1,MATCH(Sheet1!A47,'JUN-21'!$A:$A,0),1,22,1))),0)} -> 0 | G54: =IFERROR(SUM(SUMIF(OFFSET('JUN-21'!$A$1,MATCH(Sheet1!A47,'JUN-21'!$A:$A,0),0,22,1),{"WA"},OFFSET('JUN-21'!$A$1,MATCH(Sheet1!A47,'JUN-21'!$A:$A,0),1,22,1))),0) -> 0 | H54: =IFERROR(SUM(SUMIF(OFFSET('JUN-21'!$A$1,MATCH(Sheet1!A47,'JUN-21'!$A:$A,0),0,22,1),{"DCPS","GROSS_ADJUST"},OFFSET('JUN-21'!$A$1,MATCH(Sheet1!A47,'JUN-21'!$A:$A,0),1,22,1))),0) -> 0 | I54: {=+IFERROR(SUM(SUMIF(OFFSET('JUN-21'!$A$1,MATCH(Sheet1!A47,'JUN-21'!$A:$A,0),0,22,1),{"Basic*Arr*","7th Pay* Arr*"},OFFSET('JUN-21'!$A$1,MATCH(Sheet1!A47,'JUN-21'!$A:$A,0),1,22,1))),0)} -> 0 | J54: =SUM(C54:I54) -> 0 | K54: =IFERROR(SUM(SUMIF(OFFSET('JUN-21'!$A$1,MATCH(Sheet1!A47,'JUN-21'!$A:$A,0),2,22,1),{"*Pro*ax*"},OFFSET('JUN-21'!$A$1,MATCH(Sheet1!A47,'JUN-21'!$A:$A,0),3,22,1))),0) -> 0 | L54: =IFERROR(SUM(SUMIF(OFFSET('JUN-21'!$A$1,MATCH(Sheet1!A47,'JUN-21'!$A:$A,0),2,22,1),{"GPF_G*","DCPS"},OFFSET('JUN-21'!$A$1,MATCH(Sheet1!A47,'JUN-21'!$A:$A,0),3,22,1))),0) -> 0 | M54: =IFERROR(SUM(SUMIF(OFFSET('JUN-21'!$A$1,MATCH(Sheet1!A47,'JUN-21'!$A:$A,0),2,22,1),{"*GIS","GIS*R"},OFFSET('JUN-21'!$A$1,MATCH(Sheet1!A47,'JUN-21'!$A:$A,0),3,22,1))),0) -> 0 | N54: =IFERROR(SUM(SUMIF(OFFSET('JUN-21'!$A$1,MATCH(Sheet1!A47,'JUN-21'!$A:$A,0),5,22,1),{"LI*1"},OFFSET('JUN-21'!$A$1,MATCH(Sheet1!A47,'JUN-21'!$A:$A,0),6,22,1))),0) -> 0 | O54: {=IFERROR(SUM(SUMIF(OFFSET('JUN-21'!$A$1,MATCH(Sheet1!A47,'JUN-21'!$A:$A,0),2,22,1),{"HB*USE","HB*INT"},OFFSET('JUN-21'!$A$1,MATCH(Sheet1!A47,'JUN-21'!$A:$A,0),3,22,1))),0)} -> 0 | P54: {=IFERROR(SUM(SUMIF(OFFSET('JUN-21'!$A$1,MATCH(Sheet1!A47,'JUN-21'!$A:$A,0),5,22,1),{"OTHE*1","CO.*1","OTHE*2","WEL*ND","BAN*1","CLU*ND","RD*1","LI*2","MIS*US","*TAINAN*","MCA*INT*","MAIN*NANCE*","*C M Relief Fund*","Co. Op. Hsg Soc.*","GPF_ADV*","Co. Op. Cr. Soc. 2*","DCPS DA","DCPS Pay","MCA Int"},OFFSET('JUN-21'!$A$1,MATCH(Sheet1!A47,'JUN-21'!$A:$A,0),6,22,1)))+SUM(SUMIF(OFFSET('JUN-21'!$A$1,MATCH(Sheet1!A47,'JUN-21'!$A:$A,0),2,22,1),{"MCA","COM*DV*","HB*ND","CO*SOC","HRR","SRV*H","ACC*CY","F.A","STAMP_REVENUE","*C M Relief Fund*","GPF_ADV*","Co. Op. Cr. Soc. 2*","DCPS DA","DCPS Pay","MCA Int"},OFFSET('JUN-21'!$A$1,MATCH(Sheet1!A47,'JUN-21'!$A:$A,0),3,22,1))),0)} -> 0 | Q54: =+J54-H54-K54-L54-M54-N54-O54-P54-R54 -> 0 | R54: {=IFERROR(SUM(SUMIF(OFFSET('JUN-21'!$A$1,MATCH(Sheet1!A47,'JUN-21'!$A:$A,0),2,22,1),{"*I. *ax*"},OFFSET('JUN-21'!$A$1,MATCH(Sheet1!A47,'JUN-21'!$A:$A,0),3,22,1))),0)} -> 0 | S54: {=+IFERROR(IF(OFFSET('JUN-21'!$B$1,MATCH(Sheet1!A47,'JUN-21'!B:B,0)-2,0,1,1)=Sheet1!J54,IF(MID(IFERROR(OFFSET('JUN-21'!$B$1,MATCH(Sheet1!A47,'JUN-21'!$B:$B,0)-1,-1,1,1),"GROSS ERROR"),11,FIND(" ",OFFSET('JUN-21'!$B$1,MATCH(Sheet1!A47,'JUN-21'!$B:$B,0)-1,-1,1,1),12)-11)-Q54=0,"","NET MISMATCH"),"GROSS MISMATCH"),"")} | BH54: =+G48 -> PAN | BI54: =+A47 | BJ54: {=IFERROR(OFFSET('JUN-21'!$B$1,MATCH(Sheet1!A47,'JUN-21'!$B:$B,0)+1,0,1,1),"")} | BK54: =+J54 -> 0 | BL54: =+R54 -> 0 | BM54: {=IFERROR(OFFSET('JUN-21'!$A$1,MATCH(Sheet1!A47,'JUN-21'!$A:$A,0)-2,0,1,1),"")}
A55: 5 | B55: 44378 | C55: =IFERROR(SUM(SUMIF(OFFSET('JUL-21'!$A$1,MATCH(Sheet1!A47,'JUL-21'!$A:$A,0),0,22,1),{"BA*C","BASIC??"},OFFSET('JUL-21'!$A$1,MATCH(Sheet1!A47,'JUL-21'!$A:$A,0),1,22,1))),0) -> 0 | D55: =IFERROR(SUM(SUMIF(OFFSET('JUL-21'!$A$1,MATCH(Sheet1!A47,'JUL-21'!$A:$A,0),0,22,1),{"DA*C","D. *"},OFFSET('JUL-21'!$A$1,MATCH(Sheet1!A47,'JUL-21'!$A:$A,0),1,22,1))),0) -> 0 | E55: =IFERROR(SUM(SUMIF(OFFSET('JUL-21'!$A$1,MATCH(Sheet1!A47,'JUL-21'!$A:$A,0),0,22,1),{"H. R. A."},OFFSET('JUL-21'!$A$1,MATCH(Sheet1!A47,'JUL-21'!$A:$A,0),1,22,1))),0) -> 0 | F55: {=IFERROR(SUM(SUMIF(OFFSET('JUL-21'!$A$1,MATCH(Sheet1!A47,'JUL-21'!$A:$A,0),0,22,1),{"SP*AY*","S D A*","O.A.*","CLA (5th Pay)*","REF. Allow*","Trans.Allw.*","LF*","P. O.*","ARM*","Conv.A*","Otr.Allow*","Trans_Arrear*","BMIA*","Incentives*","Fit Allow*","KMA","NON-*","U.*","ME*A","PG*","Per.Tra"},OFFSET('JUL-21'!$A$1,MATCH(Sheet1!A47,'JUL-21'!$A:$A,0),1,22,1))),0)} -> 0 | G55: =IFERROR(SUM(SUMIF(OFFSET('JUL-21'!$A$1,MATCH(Sheet1!A47,'JUL-21'!$A:$A,0),0,22,1),{"WA"},OFFSET('JUL-21'!$A$1,MATCH(Sheet1!A47,'JUL-21'!$A:$A,0),1,22,1))),0) -> 0 | H55: =IFERROR(SUM(SUMIF(OFFSET('JUL-21'!$A$1,MATCH(Sheet1!A47,'JUL-21'!$A:$A,0),0,22,1),{"DCPS","GROSS_ADJUST"},OFFSET('JUL-21'!$A$1,MATCH(Sheet1!A47,'JUL-21'!$A:$A,0),1,22,1))),0) -> 0 | I55: {=++IFERROR(SUM(SUMIF(OFFSET('JUL-21'!$A$1,MATCH(Sheet1!A47,'JUL-21'!$A:$A,0),0,22,1),{"Basic*Arr*","7th Pay* Arr*"},OFFSET('JUL-21'!$A$1,MATCH(Sheet1!A47,'JUL-21'!$A:$A,0),1,22,1))),0)} -> 0 | J55: =SUM(C55:I55) -> 0 | K55: =IFERROR(SUM(SUMIF(OFFSET('JUL-21'!$A$1,MATCH(Sheet1!A47,'JUL-21'!$A:$A,0),2,22,1),{"*Pro*ax*"},OFFSET('JUL-21'!$A$1,MATCH(Sheet1!A47,'JUL-21'!$A:$A,0),3,22,1))),0) -> 0 | L55: =IFERROR(SUM(SUMIF(OFFSET('JUL-21'!$A$1,MATCH(Sheet1!A47,'JUL-21'!$A:$A,0),2,22,1),{"GPF_G*","DCPS"},OFFSET('JUL-21'!$A$1,MATCH(Sheet1!A47,'JUL-21'!$A:$A,0),3,22,1))),0) -> 0 | M55: =IFERROR(SUM(SUMIF(OFFSET('JUL-21'!$A$1,MATCH(Sheet1!A47,'JUL-21'!$A:$A,0),2,22,1),{"*GIS","GIS*R"},OFFSET('JUL-21'!$A$1,MATCH(Sheet1!A47,'JUL-21'!$A:$A,0),3,22,1))),0) -> 0 | N55: =IFERROR(SUM(SUMIF(OFFSET('JUL-21'!$A$1,MATCH(Sheet1!A47,'JUL-21'!$A:$A,0),5,22,1),{"LI*1"},OFFSET('JUL-21'!$A$1,MATCH(Sheet1!A47,'JUL-21'!$A:$A,0),6,22,1))),0) -> 0 | O55: {=IFERROR(SUM(SUMIF(OFFSET('JUL-21'!$A$1,MATCH(Sheet1!A47,'JUL-21'!$A:$A,0),2,22,1),{"HB*USE","HB*INT"},OFFSET('JUL-21'!$A$1,MATCH(Sheet1!A47,'JUL-21'!$A:$A,0),3,22,1))),0)} -> 0 | P55: {=IFERROR(SUM(SUMIF(OFFSET('JUL-21'!$A$1,MATCH(Sheet1!A47,'JUL-21'!$A:$A,0),5,22,1),{"OTHE*1","CO.*1","OTHE*2","WEL*ND","BAN*1","CLU*ND","RD*1","LI*2","MIS*US","*TAINAN*","MCA*INT*","MAIN*NANCE*","*C M Relief Fund*","Co. Op. Hsg Soc.*","GPF_ADV*","Co. Op. Cr. Soc. 2*","DCPS DA","DCPS Pay","MCA Int"},OFFSET('JUL-21'!$A$1,MATCH(Sheet1!A47,'JUL-21'!$A:$A,0),6,22,1)))+SUM(SUMIF(OFFSET('JUL-21'!$A$1,MATCH(Sheet1!A47,'JUL-21'!$A:$A,0),2,22,1),{"MCA","COM*DV*","HB*ND","CO*SOC","HRR","SRV*H","ACC*CY","F.A","STAMP_REVENUE","*C M Relief Fund*","GPF_ADV*","Co. Op. Cr. Soc. 2*","DCPS DA","DCPS Pay","MCA Int"},OFFSET('JUL-21'!$A$1,MATCH(Sheet1!A47,'JUL-21'!$A:$A,0),3,22,1))),0)} -> 0 | Q55: =+J55-H55-K55-L55-M55-N55-O55-P55-R55 -> 0 | R55: =IFERROR(SUM(SUMIF(OFFSET('JUL-21'!$A$1,MATCH(Sheet1!A47,'JUL-21'!$A:$A,0),2,22,1),{"*I. *ax*"},OFFSET('JUL-21'!$A$1,MATCH(Sheet1!A47,'JUL-21'!$A:$A,0),3,22,1))),0) -> 0 | S55: {=+IFERROR(IF(OFFSET('JUL-21'!$B$1,MATCH(Sheet1!A47,'JUL-21'!B:B,0)-2,0,1,1)=Sheet1!J55,IF(MID(IFERROR(OFFSET('JUL-21'!$B$1,MATCH(Sheet1!A47,'JUL-21'!$B:$B,0)-1,-1,1,1),"GROSS ERROR"),11,FIND(" ",OFFSET('JUL-21'!$B$1,MATCH(Sheet1!A47,'JUL-21'!$B:$B,0)-1,-1,1,1),12)-11)-Q55=0,"","NET MISMATCH"),"GROSS MISMATCH"),"")} | BH55: =+G48 -> PAN | BI55: =+A47 | BJ55: {=+IFERROR(OFFSET('JUL-21'!$B$1,MATCH(Sheet1!A47,'JUL-21'!$B:$B,0)+1,0,1,1),"")} | BK55: =+J55 -> 0 | BL55: =+R55 -> 0 | BM55: {=IFERROR(OFFSET('JUL-21'!$A$1,MATCH(Sheet1!A47,'JUL-21'!$A:$A,0)-2,0,1,1),"")}
A56: 6 | B56: 44409 | C56: =IFERROR(SUM(SUMIF(OFFSET('AUG-21'!$A$1,MATCH(Sheet1!A47,'AUG-21'!$A:$A,0),0,22,1),{"BA*C","BASIC??"},OFFSET('AUG-21'!$A$1,MATCH(Sheet1!A47,'AUG-21'!$A:$A,0),1,22,1))),0) -> 0 | D56: =IFERROR(SUM(SUMIF(OFFSET('AUG-21'!$A$1,MATCH(Sheet1!A47,'AUG-21'!$A:$A,0),0,22,1),{"DA*C","D. *"},OFFSET('AUG-21'!$A$1,MATCH(Sheet1!A47,'AUG-21'!$A:$A,0),1,22,1))),0) -> 0 | E56: =IFERROR(SUM(SUMIF(OFFSET('AUG-21'!$A$1,MATCH(Sheet1!A47,'AUG-21'!$A:$A,0),0,22,1),{"H. R. A."},OFFSET('AUG-21'!$A$1,MATCH(Sheet1!A47,'AUG-21'!$A:$A,0),1,22,1))),0) -> 0 | F56: {=IFERROR(SUM(SUMIF(OFFSET('AUG-21'!$A$1,MATCH(Sheet1!A47,'AUG-21'!$A:$A,0),0,22,1),{"SP*AY*","S D A*","O.A.*","CLA (5th Pay)*","REF. Allow*","Trans.Allw.*","LF*","P. O.*","ARM*","Conv.A*","Otr.Allow*","Trans_Arrear*","BMIA*","Incentives*","Fit Allow*","KMA","NON-*","U.*","ME*A","PG*","Per.Tra"},OFFSET('AUG-21'!$A$1,MATCH(Sheet1!A47,'AUG-21'!$A:$A,0),1,22,1))),0)} -> 0 | G56: =IFERROR(SUM(SUMIF(OFFSET('AUG-21'!$A$1,MATCH(Sheet1!A47,'AUG-21'!$A:$A,0),0,22,1),{"WA"},OFFSET('AUG-21'!$A$1,MATCH(Sheet1!A47,'AUG-21'!$A:$A,0),1,22,1))),0) -> 0 | H56: =IFERROR(SUM(SUMIF(OFFSET('AUG-21'!$A$1,MATCH(Sheet1!A47,'AUG-21'!$A:$A,0),0,22,1),{"DCPS","GROSS_ADJUST"},OFFSET('AUG-21'!$A$1,MATCH(Sheet1!A47,'AUG-21'!$A:$A,0),1,22,1))),0) -> 0 | I56: {=+IFERROR(SUM(SUMIF(OFFSET('AUG-21'!$A$1,MATCH(Sheet1!A47,'AUG-21'!$A:$A,0),0,22,1),{"7th Pay* Arr*","Basic Arr*","DA Arr"},OFFSET('AUG-21'!$A$1,MATCH(Sheet1!A47,'AUG-21'!$A:$A,0),1,22,1))),0)} -> 0 | J56: =SUM(C56:I56) -> 0 | K56: =IFERROR(SUM(SUMIF(OFFSET('AUG-21'!$A$1,MATCH(Sheet1!A47,'AUG-21'!$A:$A,0),2,22,1),{"*Pro*ax*"},OFFSET('AUG-21'!$A$1,MATCH(Sheet1!A47,'AUG-21'!$A:$A,0),3,22,1))),0) -> 0 | L56: =IFERROR(SUM(SUMIF(OFFSET('AUG-21'!$A$1,MATCH(Sheet1!A47,'AUG-21'!$A:$A,0),2,22,1),{"GPF_G*","DCPS","*7thPay GP*"},OFFSET('AUG-21'!$A$1,MATCH(Sheet1!A47,'AUG-21'!$A:$A,0),3,22,1))),0) -> 0 | M56: =IFERROR(SUM(SUMIF(OFFSET('AUG-21'!$A$1,MATCH(Sheet1!A47,'AUG-21'!$A:$A,0),2,22,1),{"*GIS","GIS*R"},OFFSET('AUG-21'!$A$1,MATCH(Sheet1!A47,'AUG-21'!$A:$A,0),3,22,1))),0) -> 0 | N56: =IFERROR(SUM(SUMIF(OFFSET('AUG-21'!$A$1,MATCH(Sheet1!A47,'AUG-21'!$A:$A,0),5,22,1),{"LI*1"},OFFSET('AUG-21'!$A$1,MATCH(Sheet1!A47,'AUG-21'!$A:$A,0),6,22,1))),0) -> 0 | O56: {=IFERROR(SUM(SUMIF(OFFSET('AUG-21'!$A$1,MATCH(Sheet1!A47,'AUG-21'!$A:$A,0),2,22,1),{"HB*USE","HB*INT"},OFFSET('AUG-21'!$A$1,MATCH(Sheet1!A47,'AUG-21'!$A:$A,0),3,22,1))),0)} -> 0 | P56: {=IFERROR(SUM(SUMIF(OFFSET('AUG-21'!$A$1,MATCH(Sheet1!A47,'AUG-21'!$A:$A,0),5,22,1),{"OTHE*1","CO.*1","OTHE*2","WEL*ND","BAN*1","CLU*ND","RD*1","LI*2","MIS*US","*TAINAN*","MCA*INT*","MAIN*NANCE*","*C M Relief Fund*","Co. Op. Hsg Soc.*","GPF_ADV*","Co. Op. Cr. Soc. 2*","DCPS DA","DCPS Pay","MCA Int"},OFFSET('AUG-21'!$A$1,MATCH(Sheet1!A47,'AUG-21'!$A:$A,0),6,22,1)))+SUM(SUMIF(OFFSET('AUG-21'!$A$1,MATCH(Sheet1!A47,'AUG-21'!$A:$A,0),2,22,1),{"MCA","COM*DV*","HB*ND","CO*SOC","HRR","SRV*H","ACC*CY","F.A","STAMP_REVENUE","*C M Relief Fund*","GPF_ADV*","Co. Op. Cr. Soc. 2*","DCPS DA","DCPS Pay","MCA Int"},OFFSET('AUG-21'!$A$1,MATCH(Sheet1!A47,'AUG-21'!$A:$A,0),3,22,1))),0)} -> 0 | Q56: =+J56-H56-K56-L56-M56-N56-O56-P56-R56 -> 0 | R56: {=IFERROR(SUM(SUMIF(OFFSET('AUG-21'!$A$1,MATCH(Sheet1!A47,'AUG-21'!$A:$A,0),2,22,1),{"*I. *ax*"},OFFSET('AUG-21'!$A$1,MATCH(Sheet1!A47,'AUG-21'!$A:$A,0),3,22,1))),0)} -> 0 | S56: {=+IFERROR(IF(OFFSET('AUG-21'!$B$1,MATCH(Sheet1!A47,'AUG-21'!B:B,0)-2,0,1,1)=Sheet1!J56,IF(MID(IFERROR(OFFSET('AUG-21'!$B$1,MATCH(Sheet1!A47,'AUG-21'!$B:$B,0)-1,-1,1,1),"GROSS ERROR"),11,FIND(" ",OFFSET('AUG-21'!$B$1,MATCH(Sheet1!A47,'AUG-21'!$B:$B,0)-1,-1,1,1),12)-11)-Q56=0,"","NET MISMATCH"),"GROSS MISMATCH"),"")} | BH56: =+G48 -> PAN | BI56: =+A47 | BJ56: {=IFERROR(OFFSET('AUG-21'!$B$1,MATCH(Sheet1!A47,'AUG-21'!$B:$B,0)+1,0,1,1),"")} | BK56: =+J56 -> 0 | BL56: =+R56 -> 0 | BM56: {=IFERROR(OFFSET('AUG-21'!$A$1,MATCH(Sheet1!A47,'AUG-21'!$A:$A,0)-2,0,1,1),"")}
A57: 7 | B57: 44440 | C57: =IFERROR(SUM(SUMIF(OFFSET('SEP-21'!$A$1,MATCH(Sheet1!A47,'SEP-21'!$A:$A,0),0,22,1),{"BA*C","BASIC??"},OFFSET('SEP-21'!$A$1,MATCH(Sheet1!A47,'SEP-21'!$A:$A,0),1,22,1))),0) -> 0 | D57: =IFERROR(SUM(SUMIF(OFFSET('SEP-21'!$A$1,MATCH(Sheet1!A47,'SEP-21'!$A:$A,0),0,22,1),{"DA*C","D. *"},OFFSET('SEP-21'!$A$1,MATCH(Sheet1!A47,'SEP-21'!$A:$A,0),1,22,1))),0) -> 0 | E57: =IFERROR(SUM(SUMIF(OFFSET('SEP-21'!$A$1,MATCH(Sheet1!A47,'SEP-21'!$A:$A,0),0,22,1),{"H. R. A."},OFFSET('SEP-21'!$A$1,MATCH(Sheet1!A47,'SEP-21'!$A:$A,0),1,22,1))),0) -> 0 | F57: {=IFERROR(SUM(SUMIF(OFFSET('SEP-21'!$A$1,MATCH(Sheet1!A47,'SEP-21'!$A:$A,0),0,22,1),{"SP*AY*","S D A*","O.A.*","CLA (5th Pay)*","REF. Allow*","Trans.Allw.*","LF*","P. O.*","ARM*","Conv.A*","Otr.Allow*","Trans_Arrear*","BMIA*","Incentives*","Fit Allow*","KMA","NON-*","U.*","ME*A","PG*","Per.Tra"},OFFSET('SEP-21'!$A$1,MATCH(Sheet1!A47,'SEP-21'!$A:$A,0),1,22,1))),0)} -> 0 | G57: =IFERROR(SUM(SUMIF(OFFSET('SEP-21'!$A$1,MATCH(Sheet1!A47,'SEP-21'!$A:$A,0),0,22,1),{"WA"},OFFSET('SEP-21'!$A$1,MATCH(Sheet1!A47,'SEP-21'!$A:$A,0),1,22,1))),0) -> 0 | H57: =IFERROR(SUM(SUMIF(OFFSET('SEP-21'!$A$1,MATCH(Sheet1!A47,'SEP-21'!$A:$A,0),0,22,1),{"DCPS","GROSS_ADJUST"},OFFSET('SEP-21'!$A$1,MATCH(Sheet1!A47,'SEP-21'!$A:$A,0),1,22,1))),0) -> 0 | I57: {=++IFERROR(SUM(SUMIF(OFFSET('SEP-21'!$A$1,MATCH(Sheet1!A47,'SEP-21'!$A:$A,0),0,22,1),{"Basic*Arr*","7th Pay* Arr*"},OFFSET('SEP-21'!$A$1,MATCH(Sheet1!A47,'SEP-21'!$A:$A,0),1,22,1))),0)} -> 0 | J57: =SUM(C57:I57) -> 0 | K57: =IFERROR(SUM(SUMIF(OFFSET('SEP-21'!$A$1,MATCH(Sheet1!A47,'SEP-21'!$A:$A,0),2,22,1),{"*Pro*ax*"},OFFSET('SEP-21'!$A$1,MATCH(Sheet1!A47,'SEP-21'!$A:$A,0),3,22,1))),0) -> 0 | L57: =IFERROR(SUM(SUMIF(OFFSET('SEP-21'!$A$1,MATCH(Sheet1!A47,'SEP-21'!$A:$A,0),2,22,1),{"GPF_G*","DCPS"},OFFSET('SEP-21'!$A$1,MATCH(Sheet1!A47,'SEP-21'!$A:$A,0),3,22,1))),0) -> 0 | M57: =IFERROR(SUM(SUMIF(OFFSET('SEP-21'!$A$1,MATCH(Sheet1!A47,'SEP-21'!$A:$A,0),2,22,1),{"*GIS","GIS*R"},OFFSET('SEP-21'!$A$1,MATCH(Sheet1!A47,'SEP-21'!$A:$A,0),3,22,1))),0) -> 0 | N57: =IFERROR(SUM(SUMIF(OFFSET('SEP-21'!$A$1,MATCH(Sheet1!A47,'SEP-21'!$A:$A,0),5,22,1),{"LI*1"},OFFSET('SEP-21'!$A$1,MATCH(Sheet1!A47,'SEP-21'!$A:$A,0),6,22,1))),0) -> 0 | O57: {=IFERROR(SUM(SUMIF(OFFSET('SEP-21'!$A$1,MATCH(Sheet1!A47,'SEP-21'!$A:$A,0),2,22,1),{"HB*USE","HB*INT"},OFFSET('SEP-21'!$A$1,MATCH(Sheet1!A47,'SEP-21'!$A:$A,0),3,22,1))),0)} -> 0 | P57: {=IFERROR(SUM(SUMIF(OFFSET('SEP-21'!$A$1,MATCH(Sheet1!A47,'SEP-21'!$A:$A,0),5,22,1),{"OTHE*1","CO.*1","OTHE*2","WEL*ND","BAN*1","CLU*ND","RD*1","LI*2","MIS*US","*TAINAN*","MCA*INT*","MAIN*NANCE*","*C M Relief Fund*","Co. Op. Hsg Soc.*","GPF_ADV*","Co. Op. Cr. Soc. 2*","DCPS DA","DCPS Pay","MCA Int"},OFFSET('SEP-21'!$A$1,MATCH(Sheet1!A47,'SEP-21'!$A:$A,0),6,22,1)))+SUM(SUMIF(OFFSET('SEP-21'!$A$1,MATCH(Sheet1!A47,'SEP-21'!$A:$A,0),2,22,1),{"MCA","COM*DV*","HB*ND","CO*SOC","HRR","SRV*H","ACC*CY","F.A","STAMP_REVENUE","*C M Relief Fund*","GPF_ADV*","Co. Op. Cr. Soc. 2*","DCPS DA","DCPS Pay","MCA Int"},OFFSET('SEP-21'!$A$1,MATCH(Sheet1!A47,'SEP-21'!$A:$A,0),3,22,1))),0)} -> 0 | Q57: =+J57-H57-K57-L57-M57-N57-O57-P57-R57 -> 0 | R57: {=IFERROR(SUM(SUMIF(OFFSET('SEP-21'!$A$1,MATCH(Sheet1!A47,'SEP-21'!$A:$A,0),2,22,1),{"*I. *ax*"},OFFSET('SEP-21'!$A$1,MATCH(Sheet1!A47,'SEP-21'!$A:$A,0),3,22,1))),0)} -> 0 | S57: {=+IFERROR(IF(OFFSET('SEP-21'!$B$1,MATCH(Sheet1!A47,'SEP-21'!B:B,0)-2,0,1,1)=Sheet1!J57,IF(MID(IFERROR(OFFSET('SEP-21'!$B$1,MATCH(Sheet1!A47,'SEP-21'!$B:$B,0)-1,-1,1,1),"GROSS ERROR"),11,FIND(" ",OFFSET('SEP-21'!$B$1,MATCH(Sheet1!A47,'SEP-21'!$B:$B,0)-1,-1,1,1),12)-11)-Q57=0,"","NET MISMATCH"),"GROSS MISMATCH"),"")} | BH57: =+G48 -> PAN | BI57: =+A47 | BJ57: {=IFERROR(OFFSET('SEP-21'!$B$1,MATCH(Sheet1!A47,'SEP-21'!$B:$B,0)+1,0,1,1),"")} | BK57: =+J57 -> 0 | BL57: =+R57 -> 0 | BM57: {=IFERROR(OFFSET('SEP-21'!$A$1,MATCH(Sheet1!A47,'SEP-21'!$A:$A,0)-2,0,1,1),"")}
A58: 8 | B58: 44470 | C58: =IFERROR(SUM(SUMIF(OFFSET('OCT-21'!$A$1,MATCH(Sheet1!A47,'OCT-21'!$A:$A,0),0,22,1),{"BA*C","BASIC??"},OFFSET('OCT-21'!$A$1,MATCH(Sheet1!A47,'OCT-21'!$A:$A,0),1,22,1))),0) -> 0 | D58: =IFERROR(SUM(SUMIF(OFFSET('OCT-21'!$A$1,MATCH(Sheet1!A47,'OCT-21'!$A:$A,0),0,22,1),{"DA*C","D. *"},OFFSET('OCT-21'!$A$1,MATCH(Sheet1!A47,'OCT-21'!$A:$A,0),1,22,1))),0) -> 0 | E58: =IFERROR(SUM(SUMIF(OFFSET('OCT-21'!$A$1,MATCH(Sheet1!A47,'OCT-21'!$A:$A,0),0,22,1),{"H. R. A."},OFFSET('OCT-21'!$A$1,MATCH(Sheet1!A47,'OCT-21'!$A:$A,0),1,22,1))),0) -> 0 | F58: {=IFERROR(SUM(SUMIF(OFFSET('OCT-21'!$A$1,MATCH(Sheet1!A47,'OCT-21'!$A:$A,0),0,22,1),{"SP*AY*","S D A*","O.A.*","CLA (5th Pay)*","REF. Allow*","Trans.Allw.*","LF*","P. O.*","ARM*","Conv.A*","Otr.Allow*","Trans_Arrear*","BMIA*","Incentives*","Fit Allow*","KMA","NON-*","U.*","ME*A","PG*","Per.Tra"},OFFSET('OCT-21'!$A$1,MATCH(Sheet1!A47,'OCT-21'!$A:$A,0),1,22,1))),0)} -> 0 | G58: =IFERROR(SUM(SUMIF(OFFSET('OCT-21'!$A$1,MATCH(Sheet1!A47,'OCT-21'!$A:$A,0),0,22,1),{"WA"},OFFSET('OCT-21'!$A$1,MATCH(Sheet1!A47,'OCT-21'!$A:$A,0),1,22,1))),0) -> 0 | H58: =IFERROR(SUM(SUMIF(OFFSET('OCT-21'!$A$1,MATCH(Sheet1!A47,'OCT-21'!$A:$A,0),0,22,1),{"DCPS","GROSS_ADJUST"},OFFSET('OCT-21'!$A$1,MATCH(Sheet1!A47,'OCT-21'!$A:$A,0),1,22,1))),0) -> 0 | I58: {=+IFERROR(SUM(SUMIF(OFFSET('OCT-21'!$A$1,MATCH(Sheet1!A47,'OCT-21'!$A:$A,0),0,22,1),{"Basic*Arr*","7th Pay* Arr*","DA Arr"},OFFSET('OCT-21'!$A$1,MATCH(Sheet1!A47,'OCT-21'!$A:$A,0),1,22,1))),0)} -> 0 | J58: =SUM(C58:I58) -> 0 | K58: =IFERROR(SUM(SUMIF(OFFSET('OCT-21'!$A$1,MATCH(Sheet1!A47,'OCT-21'!$A:$A,0),2,22,1),{"*Pro*ax*"},OFFSET('OCT-21'!$A$1,MATCH(Sheet1!A47,'OCT-21'!$A:$A,0),3,22,1))),0) -> 0 | L58: {=IFERROR(SUM(SUMIF(OFFSET('OCT-21'!$A$1,MATCH(Sheet1!A47,'OCT-21'!$A:$A,0),2,22,1),{"GPF_G*","DCPS","DCPS DA*"},OFFSET('OCT-21'!$A$1,MATCH(Sheet1!A47,'OCT-21'!$A:$A,0),3,22,1))),0)} -> 0 | M58: =IFERROR(SUM(SUMIF(OFFSET('OCT-21'!$A$1,MATCH(Sheet1!A47,'OCT-21'!$A:$A,0),2,22,1),{"*GIS","GIS*R"},OFFSET('OCT-21'!$A$1,MATCH(Sheet1!A47,'OCT-21'!$A:$A,0),3,22,1))),0) -> 0 | N58: =IFERROR(SUM(SUMIF(OFFSET('OCT-21'!$A$1,MATCH(Sheet1!A47,'OCT-21'!$A:$A,0),5,22,1),{"LI*1"},OFFSET('OCT-21'!$A$1,MATCH(Sheet1!A47,'OCT-21'!$A:$A,0),6,22,1))),0) -> 0 | O58: {=IFERROR(SUM(SUMIF(OFFSET('OCT-21'!$A$1,MATCH(Sheet1!A47,'OCT-21'!$A:$A,0),2,22,1),{"HB*USE","HB*INT"},OFFSET('OCT-21'!$A$1,MATCH(Sheet1!A47,'OCT-21'!$A:$A,0),3,22,1))),0)} -> 0 | P58: {=IFERROR(SUM(SUMIF(OFFSET('OCT-21'!$A$1,MATCH(Sheet1!A47,'OCT-21'!$A:$A,0),5,22,1),{"OTHE*1","CO.*1","OTHE*2","WEL*ND","BAN*1","CLU*ND","RD*1","LI*2","MIS*US","*TAINAN*","MCA*INT*","MAIN*NANCE*","*C M Relief Fund*","Co. Op. Hsg Soc.*","GPF_ADV*","Co. Op. Cr. Soc. 2*","DCPS Pay"},OFFSET('OCT-21'!$A$1,MATCH(Sheet1!A47,'OCT-21'!$A:$A,0),6,22,1)))+SUM(SUMIF(OFFSET('OCT-21'!$A$1,MATCH(Sheet1!A47,'OCT-21'!$A:$A,0),2,22,1),{"MCA","COM*DV*","HB*ND","CO*SOC","HRR","SRV*H","ACC*CY","F.A","STAMP_REVENUE","*C M Relief Fund*","GPF_ADV*","Co. Op. Cr. Soc. 2*","DCPS Pay"},OFFSET('OCT-21'!$A$1,MATCH(Sheet1!A47,'OCT-21'!$A:$A,0),3,22,1))),0)} -> 0 | Q58: =+J58-H58-K58-L58-M58-N58-O58-P58-R58 -> 0 | R58: {=IFERROR(SUM(SUMIF(OFFSET('OCT-21'!$A$1,MATCH(Sheet1!A47,'OCT-21'!$A:$A,0),2,22,1),{"*I. *ax*"},OFFSET('OCT-21'!$A$1,MATCH(Sheet1!A47,'OCT-21'!$A:$A,0),3,22,1))),0)} -> 0 | S58: {=+IFERROR(IF(OFFSET('OCT-21'!$B$1,MATCH(Sheet1!A47,'OCT-21'!B:B,0)-2,0,1,1)=Sheet1!J58,IF(MID(IFERROR(OFFSET('OCT-21'!$B$1,MATCH(Sheet1!A47,'OCT-21'!$B:$B,0)-1,-1,1,1),"GROSS ERROR"),11,FIND(" ",OFFSET('OCT-21'!$B$1,MATCH(Sheet1!A47,'OCT-21'!$B:$B,0)-1,-1,1,1),12)-11)-Q58=0,"","NET MISMATCH"),"GROSS MISMATCH"),"")} | BH58: =+G48 -> PAN | BI58: =+A47 | BJ58: {=+IFERROR(OFFSET('OCT-21'!$B$1,MATCH(Sheet1!A47,'OCT-21'!$B:$B,0)+1,0,1,1),"")} | BK58: =+J58 -> 0 | BL58: =+R58 -> 0 | BM58: {=IFERROR(OFFSET('OCT-21'!$A$1,MATCH(Sheet1!A47,'OCT-21'!$A:$A,0)-2,0,1,1),"")}
A59: 9 | B59: 44501 | C59: =IFERROR(SUM(SUMIF(OFFSET('NOV-21'!$A$1,MATCH(Sheet1!A47,'NOV-21'!$A:$A,0),0,22,1),{"BA*C","BASIC??"},OFFSET('NOV-21'!$A$1,MATCH(Sheet1!A47,'NOV-21'!$A:$A,0),1,22,1))),0) -> 0 | D59: =IFERROR(SUM(SUMIF(OFFSET('NOV-21'!$A$1,MATCH(Sheet1!A47,'NOV-21'!$A:$A,0),0,22,1),{"DA*C","D. *"},OFFSET('NOV-21'!$A$1,MATCH(Sheet1!A47,'NOV-21'!$A:$A,0),1,22,1))),0) -> 0 | E59: =IFERROR(SUM(SUMIF(OFFSET('NOV-21'!$A$1,MATCH(Sheet1!A47,'NOV-21'!$A:$A,0),0,22,1),{"H. R. A."},OFFSET('NOV-21'!$A$1,MATCH(Sheet1!A47,'NOV-21'!$A:$A,0),1,22,1))),0) -> 0 | F59: {=IFERROR(SUM(SUMIF(OFFSET('NOV-21'!$A$1,MATCH(Sheet1!A47,'NOV-21'!$A:$A,0),0,22,1),{"SP*AY*","S D A*","O.A.*","CLA (5th Pay)*","REF. Allow*","Trans.Allw.*","LF*","P. O.*","ARM*","Conv.A*","Otr.Allow*","Trans_Arrear*","BMIA*","Incentives*","Fit Allow*","KMA","NON-*","U.*","ME*A","PG*","Per.Tra"},OFFSET('NOV-21'!$A$1,MATCH(Sheet1!A47,'NOV-21'!$A:$A,0),1,22,1))),0)} -> 0 | G59: =IFERROR(SUM(SUMIF(OFFSET('NOV-21'!$A$1,MATCH(Sheet1!A47,'NOV-21'!$A:$A,0),0,22,1),{"WA"},OFFSET('NOV-21'!$A$1,MATCH(Sheet1!A47,'NOV-21'!$A:$A,0),1,22,1))),0) -> 0 | H59: =IFERROR(SUM(SUMIF(OFFSET('NOV-21'!$A$1,MATCH(Sheet1!A47,'NOV-21'!$A:$A,0),0,22,1),{"DCPS","GROSS_ADJUST"},OFFSET('NOV-21'!$A$1,MATCH(Sheet1!A47,'NOV-21'!$A:$A,0),1,22,1))),0) -> 0 | I59: {=+IFERROR(SUM(SUMIF(OFFSET('NOV-21'!$A$1,MATCH(Sheet1!A47,'NOV-21'!$A:$A,0),0,22,1),{"Basic*Arr*","7th Pay* Arr*","DA Arr"},OFFSET('NOV-21'!$A$1,MATCH(Sheet1!A47,'NOV-21'!$A:$A,0),1,22,1))),0)} -> 0 | J59: =SUM(C59:I59) -> 0 | K59: =IFERROR(SUM(SUMIF(OFFSET('NOV-21'!$A$1,MATCH(Sheet1!A47,'NOV-21'!$A:$A,0),2,22,1),{"*Pro*ax*"},OFFSET('NOV-21'!$A$1,MATCH(Sheet1!A47,'NOV-21'!$A:$A,0),3,22,1))),0) -> 0 | L59: =IFERROR(SUM(SUMIF(OFFSET('NOV-21'!$A$1,MATCH(Sheet1!A47,'NOV-21'!$A:$A,0),2,22,1),{"GPF_G*","DCPS"},OFFSET('NOV-21'!$A$1,MATCH(Sheet1!A47,'NOV-21'!$A:$A,0),3,22,1))),0) -> 0 | M59: =IFERROR(SUM(SUMIF(OFFSET('NOV-21'!$A$1,MATCH(Sheet1!A47,'NOV-21'!$A:$A,0),2,22,1),{"*GIS","GIS*R"},OFFSET('NOV-21'!$A$1,MATCH(Sheet1!A47,'NOV-21'!$A:$A,0),3,22,1))),0) -> 0 | N59: =IFERROR(SUM(SUMIF(OFFSET('NOV-21'!$A$1,MATCH(Sheet1!A47,'NOV-21'!$A:$A,0),5,22,1),{"LI*1"},OFFSET('NOV-21'!$A$1,MATCH(Sheet1!A47,'NOV-21'!$A:$A,0),6,22,1))),0) -> 0 | O59: {=IFERROR(SUM(SUMIF(OFFSET('NOV-21'!$A$1,MATCH(Sheet1!A47,'NOV-21'!$A:$A,0),2,22,1),{"HB*USE","HB*INT"},OFFSET('NOV-21'!$A$1,MATCH(Sheet1!A47,'NOV-21'!$A:$A,0),3,22,1))),0)} -> 0 | P59: {=IFERROR(SUM(SUMIF(OFFSET('NOV-21'!$A$1,MATCH(Sheet1!A47,'NOV-21'!$A:$A,0),5,22,1),{"OTHE*1","CO.*1","OTHE*2","WEL*ND","BAN*1","CLU*ND","RD*1","LI*2","MIS*US","*TAINAN*","MCA*INT*","MAIN*NANCE*","*C M Relief Fund*","Co. Op. Hsg Soc.*","GPF_ADV*","Co. Op. Cr. Soc. 2*","DCPS DA","DCPS Pay","MCA Int"},OFFSET('NOV-21'!$A$1,MATCH(Sheet1!A47,'NOV-21'!$A:$A,0),6,22,1)))+SUM(SUMIF(OFFSET('NOV-21'!$A$1,MATCH(Sheet1!A47,'NOV-21'!$A:$A,0),2,22,1),{"MCA","COM*DV*","HB*ND","CO*SOC","HRR","SRV*H","ACC*CY","F.A","STAMP_REVENUE","*C M Relief Fund*","GPF_ADV*","Co. Op. Cr. Soc. 2*","DCPS DA","DCPS Pay","MCA Int"},OFFSET('NOV-21'!$A$1,MATCH(Sheet1!A47,'NOV-21'!$A:$A,0),3,22,1))),0)} -> 0 | Q59: =+J59-H59-K59-L59-M59-N59-O59-P59-R59 -> 0 | R59: {=IFERROR(SUM(SUMIF(OFFSET('NOV-21'!$A$1,MATCH(Sheet1!A47,'NOV-21'!$A:$A,0),2,22,1),{"*I. *ax*"},OFFSET('NOV-21'!$A$1,MATCH(Sheet1!A47,'NOV-21'!$A:$A,0),3,22,1))),0)} -> 0 | S59: {=+IFERROR(IF(OFFSET('NOV-21'!$B$1,MATCH(Sheet1!A47,'NOV-21'!B:B,0)-2,0,1,1)=Sheet1!J59,IF(MID(IFERROR(OFFSET('NOV-21'!$B$1,MATCH(Sheet1!A47,'NOV-21'!$B:$B,0)-1,-1,1,1),"GROSS ERROR"),11,FIND(" ",OFFSET('NOV-21'!$B$1,MATCH(Sheet1!A47,'NOV-21'!$B:$B,0)-1,-1,1,1),12)-11)-Q59=0,"","NET MISMATCH"),"GROSS MISMATCH"),"")} | BH59: =+G48 -> PAN | BI59: =+A47 | BJ59: {=+IFERROR(OFFSET('NOV-21'!$B$1,MATCH(Sheet1!A47,'NOV-21'!$B:$B,0)+1,0,1,1),"")} | BK59: =+J59 -> 0 | BL59: =+R59 -> 0 | BM59: {=IFERROR(OFFSET('NOV-21'!$A$1,MATCH(Sheet1!A47,'NOV-21'!$A:$A,0)-2,0,1,1),"")}
A60: 10 | B60: 44531 | C60: =IFERROR(SUM(SUMIF(OFFSET('DEC-21'!$A$1,MATCH(Sheet1!A47,'DEC-21'!$A:$A,0),0,22,1),{"BA*C","BASIC??"},OFFSET('DEC-21'!$A$1,MATCH(Sheet1!A47,'DEC-21'!$A:$A,0),1,22,1))),0) -> 0 | D60: =IFERROR(SUM(SUMIF(OFFSET('DEC-21'!$A$1,MATCH(Sheet1!A47,'DEC-21'!$A:$A,0),0,22,1),{"DA*C","D. *"},OFFSET('DEC-21'!$A$1,MATCH(Sheet1!A47,'DEC-21'!$A:$A,0),1,22,1))),0) -> 0 | E60: =IFERROR(SUM(SUMIF(OFFSET('DEC-21'!$A$1,MATCH(Sheet1!A47,'DEC-21'!$A:$A,0),0,22,1),{"H. R. A."},OFFSET('DEC-21'!$A$1,MATCH(Sheet1!A47,'DEC-21'!$A:$A,0),1,22,1))),0) -> 0 | F60: {=IFERROR(SUM(SUMIF(OFFSET('DEC-21'!$A$1,MATCH(Sheet1!A47,'DEC-21'!$A:$A,0),0,22,1),{"SP*AY*","S D A*","O.A.*","CLA (5th Pay)*","REF. Allow*","Trans.Allw.*","LF*","P. O.*","ARM*","Conv.A*","Otr.Allow*","Trans_Arrear*","BMIA*","Incentives*","Fit Allow*","KMA","NON-*","U.*","ME*A","PG*","Per.Tra"},OFFSET('DEC-21'!$A$1,MATCH(Sheet1!A47,'DEC-21'!$A:$A,0),1,22,1))),0)} -> 0 | G60: =IFERROR(SUM(SUMIF(OFFSET('DEC-21'!$A$1,MATCH(Sheet1!A47,'DEC-21'!$A:$A,0),0,22,1),{"WA"},OFFSET('DEC-21'!$A$1,MATCH(Sheet1!A47,'DEC-21'!$A:$A,0),1,22,1))),0) -> 0 | H60: =IFERROR(SUM(SUMIF(OFFSET('DEC-21'!$A$1,MATCH(Sheet1!A47,'DEC-21'!$A:$A,0),0,22,1),{"DCPS","GROSS_ADJUST"},OFFSET('DEC-21'!$A$1,MATCH(Sheet1!A47,'DEC-21'!$A:$A,0),1,22,1))),0) -> 0 | I60: {=+IFERROR(SUM(SUMIF(OFFSET('DEC-21'!$A$1,MATCH(Sheet1!A47,'DEC-21'!$A:$A,0),0,22,1),{"Basic*Arr*","7th Pay* Arr*"},OFFSET('DEC-21'!$A$1,MATCH(Sheet1!A47,'DEC-21'!$A:$A,0),1,22,1))),0)} -> 0 | J60: =SUM(C60:I60) -> 0 | K60: =IFERROR(SUM(SUMIF(OFFSET('DEC-21'!$A$1,MATCH(Sheet1!A47,'DEC-21'!$A:$A,0),2,22,1),{"*Pro*ax*"},OFFSET('DEC-21'!$A$1,MATCH(Sheet1!A47,'DEC-21'!$A:$A,0),3,22,1))),0) -> 0 | L60: =IFERROR(SUM(SUMIF(OFFSET('DEC-21'!$A$1,MATCH(Sheet1!A47,'DEC-21'!$A:$A,0),2,22,1),{"GPF_G*","DCPS"},OFFSET('DEC-21'!$A$1,MATCH(Sheet1!A47,'DEC-21'!$A:$A,0),3,22,1))),0) -> 0 | M60: =IFERROR(SUM(SUMIF(OFFSET('DEC-21'!$A$1,MATCH(Sheet1!A47,'DEC-21'!$A:$A,0),2,22,1),{"*GIS","GIS*R"},OFFSET('DEC-21'!$A$1,MATCH(Sheet1!A47,'DEC-21'!$A:$A,0),3,22,1))),0) -> 0 | N60: =IFERROR(SUM(SUMIF(OFFSET('DEC-21'!$A$1,MATCH(Sheet1!A47,'DEC-21'!$A:$A,0),5,22,1),{"LI*1"},OFFSET('DEC-21'!$A$1,MATCH(Sheet1!A47,'DEC-21'!$A:$A,0),6,22,1))),0) -> 0 | O60: {=IFERROR(SUM(SUMIF(OFFSET('DEC-21'!$A$1,MATCH(Sheet1!A47,'DEC-21'!$A:$A,0),2,22,1),{"HB*USE","HB*INT"},OFFSET('DEC-21'!$A$1,MATCH(Sheet1!A47,'DEC-21'!$A:$A,0),3,22,1))),0)} -> 0 | P60: {=IFERROR(SUM(SUMIF(OFFSET('DEC-21'!$A$1,MATCH(Sheet1!A47,'DEC-21'!$A:$A,0),5,22,1),{"OTHE*1","CO.*1","OTHE*2","WEL*ND","BAN*1","CLU*ND","RD*1","LI*2","MIS*US","*TAINAN*","MCA*INT*","MAIN*NANCE*","*C M Relief Fund*","Co. Op. Hsg Soc.*","GPF_ADV*","Co. Op. Cr. Soc. 2*","DCPS DA","DCPS Pay","MCA Int"},OFFSET('DEC-21'!$A$1,MATCH(Sheet1!A47,'DEC-21'!$A:$A,0),6,22,1)))+SUM(SUMIF(OFFSET('DEC-21'!$A$1,MATCH(Sheet1!A47,'DEC-21'!$A:$A,0),2,22,1),{"MCA","COM*DV*","HB*ND","CO*SOC","HRR","SRV*H","ACC*CY","F.A","STAMP_REVENUE","*C M Relief Fund*","GPF_ADV*","Co. Op. Cr. Soc. 2*","DCPS DA","DCPS Pay","MCA Int"},OFFSET('DEC-21'!$A$1,MATCH(Sheet1!A47,'DEC-21'!$A:$A,0),3,22,1))),0)} -> 0 | Q60: =+J60-H60-K60-L60-M60-N60-O60-P60-R60 -> 0 | R60: {=IFERROR(SUM(SUMIF(OFFSET('DEC-21'!$A$1,MATCH(Sheet1!A47,'DEC-21'!$A:$A,0),2,22,1),{"*I. *ax*"},OFFSET('DEC-21'!$A$1,MATCH(Sheet1!A47,'DEC-21'!$A:$A,0),3,22,1))),0)} -> 0 | S60: {=+IFERROR(IF(OFFSET('DEC-21'!$B$1,MATCH(Sheet1!A47,'DEC-21'!B:B,0)-2,0,1,1)=Sheet1!J60,IF(MID(IFERROR(OFFSET('DEC-21'!$B$1,MATCH(Sheet1!A47,'DEC-21'!$B:$B,0)-1,-1,1,1),"GROSS ERROR"),11,FIND(" ",OFFSET('DEC-21'!$B$1,MATCH(Sheet1!A47,'DEC-21'!$B:$B,0)-1,-1,1,1),12)-11)-Q60=0,"","NET MISMATCH"),"GROSS MISMATCH"),"")} | BH60: =+G48 -> PAN | BI60: =+A47 | BJ60: {=+IFERROR(OFFSET('DEC-21'!$B$1,MATCH(Sheet1!A47,'DEC-21'!$B:$B,0)+1,0,1,1),"")} | BK60: =+J60 -> 0 | BL60: =+R60 -> 0 | BM60: {=IFERROR(OFFSET('DEC-21'!$A$1,MATCH(Sheet1!A47,'DEC-21'!$A:$A,0)-2,0,1,1),"")}
A61: 11 | B61: 44562 | C61: =IFERROR(SUM(SUMIF(OFFSET('JAN-22'!$A$1,MATCH(Sheet1!A47,'JAN-22'!$A:$A,0),0,22,1),{"BA*C","BASIC??"},OFFSET('JAN-22'!$A$1,MATCH(Sheet1!A47,'JAN-22'!$A:$A,0),1,22,1))),0) -> 0 | D61: =IFERROR(SUM(SUMIF(OFFSET('JAN-22'!$A$1,MATCH(Sheet1!A47,'JAN-22'!$A:$A,0),0,22,1),{"DA*C","D. *"},OFFSET('JAN-22'!$A$1,MATCH(Sheet1!A47,'JAN-22'!$A:$A,0),1,22,1))),0) -> 0 | E61: =IFERROR(SUM(SUMIF(OFFSET('JAN-22'!$A$1,MATCH(Sheet1!A47,'JAN-22'!$A:$A,0),0,22,1),{"H. R. A."},OFFSET('JAN-22'!$A$1,MATCH(Sheet1!A47,'JAN-22'!$A:$A,0),1,22,1))),0) -> 0 | F61: {=IFERROR(SUM(SUMIF(OFFSET('JAN-22'!$A$1,MATCH(Sheet1!A47,'JAN-22'!$A:$A,0),0,22,1),{"SP*AY*","S D A*","O.A.*","CLA (5th Pay)*","REF. Allow*","Trans.Allw.*","LF*","P. O.*","ARM*","Conv.A*","Otr.Allow*","Trans_Arrear*","BMIA*","Incentives*","Fit Allow*","KMA","NON-*","U.*","ME*A","PG*","Per.Tra"},OFFSET('JAN-22'!$A$1,MATCH(Sheet1!A47,'JAN-22'!$A:$A,0),1,22,1))),0)} -> 0 | G61: =IFERROR(SUM(SUMIF(OFFSET('JAN-22'!$A$1,MATCH(Sheet1!A47,'JAN-22'!$A:$A,0),0,22,1),{"WA"},OFFSET('JAN-22'!$A$1,MATCH(Sheet1!A47,'JAN-22'!$A:$A,0),1,22,1))),0) -> 0 | H61: =IFERROR(SUM(SUMIF(OFFSET('JAN-22'!$A$1,MATCH(Sheet1!A47,'JAN-22'!$A:$A,0),0,22,1),{"DCPS","GROSS_ADJUST"},OFFSET('JAN-22'!$A$1,MATCH(Sheet1!A47,'JAN-22'!$A:$A,0),1,22,1))),0) -> 0 | I61: {=+IFERROR(SUM(SUMIF(OFFSET('JAN-22'!$A$1,MATCH(Sheet1!A47,'JAN-22'!$A:$A,0),0,22,1),{"Basic*Arr*","7th Pay* Arr*"},OFFSET('JAN-22'!$A$1,MATCH(Sheet1!A47,'JAN-22'!$A:$A,0),1,22,1))),0)} -> 0 | J61: =SUM(C61:I61) -> 0 | K61: =IFERROR(SUM(SUMIF(OFFSET('JAN-22'!$A$1,MATCH(Sheet1!A47,'JAN-22'!$A:$A,0),2,22,1),{"*Pro*ax*"},OFFSET('JAN-22'!$A$1,MATCH(Sheet1!A47,'JAN-22'!$A:$A,0),3,22,1))),0) -> 0 | L61: =IFERROR(SUM(SUMIF(OFFSET('JAN-22'!$A$1,MATCH(Sheet1!A47,'JAN-22'!$A:$A,0),2,22,1),{"GPF_G*","DCPS"},OFFSET('JAN-22'!$A$1,MATCH(Sheet1!A47,'JAN-22'!$A:$A,0),3,22,1))),0) -> 0 | M61: {=IFERROR(SUM(SUMIF(OFFSET('JAN-22'!$A$1,MATCH(Sheet1!A47,'JAN-22'!$A:$A,0),2,22,1),{"*GIS","GIS*R"},OFFSET('JAN-22'!$A$1,MATCH(Sheet1!A47,'JAN-22'!$A:$A,0),3,22,1))),0)} -> 0 | N61: =IFERROR(SUM(SUMIF(OFFSET('JAN-22'!$A$1,MATCH(Sheet1!A47,'JAN-22'!$A:$A,0),5,22,1),{"LI*1"},OFFSET('JAN-22'!$A$1,MATCH(Sheet1!A47,'JAN-22'!$A:$A,0),6,22,1))),0) -> 0 | O61: {=IFERROR(SUM(SUMIF(OFFSET('JAN-22'!$A$1,MATCH(Sheet1!A47,'JAN-22'!$A:$A,0),2,22,1),{"HB*USE","HB*INT"},OFFSET('JAN-22'!$A$1,MATCH(Sheet1!A47,'JAN-22'!$A:$A,0),3,22,1))),0)} -> 0 | P61: {=IFERROR(SUM(SUMIF(OFFSET('JAN-22'!$A$1,MATCH(Sheet1!A47,'JAN-22'!$A:$A,0),5,22,1),{"OTHE*1","CO.*1","OTHE*2","WEL*ND","BAN*1","CLU*ND","RD*1","LI*2","MIS*US","*TAINAN*","MCA*INT*","MAIN*NANCE*","*C M Relief Fund*","Co. Op. Hsg Soc.*","GPF_ADV*","Co. Op. Cr. Soc. 2*","DCPS DA","DCPS Pay","MCA Int"},OFFSET('JAN-22'!$A$1,MATCH(Sheet1!A47,'JAN-22'!$A:$A,0),6,22,1)))+SUM(SUMIF(OFFSET('JAN-22'!$A$1,MATCH(Sheet1!A47,'JAN-22'!$A:$A,0),2,22,1),{"MCA","COM*DV*","HB*ND","CO*SOC","HRR","SRV*H","ACC*CY","F.A","STAMP_REVENUE","*C M Relief Fund*","GPF_ADV*","Co. Op. Cr. Soc. 2*","DCPS DA","DCPS Pay","MCA Int"},OFFSET('JAN-22'!$A$1,MATCH(Sheet1!A47,'JAN-22'!$A:$A,0),3,22,1))),0)} -> 0 | Q61: =+J61-H61-K61-L61-M61-N61-O61-P61-R61 -> 0 | R61: {=IFERROR(SUM(SUMIF(OFFSET('JAN-22'!$A$1,MATCH(Sheet1!A47,'JAN-22'!$A:$A,0),2,22,1),{"*I. *ax*"},OFFSET('JAN-22'!$A$1,MATCH(Sheet1!A47,'JAN-22'!$A:$A,0),3,22,1))),0)} -> 0 | S61: {=+IFERROR(IF(OFFSET('JAN-22'!$B$1,MATCH(Sheet1!A47,'JAN-22'!B:B,0)-2,0,1,1)=Sheet1!J61,IF(MID(IFERROR(OFFSET('JAN-22'!$B$1,MATCH(Sheet1!A47,'JAN-22'!$B:$B,0)-1,-1,1,1),"GROSS ERROR"),11,FIND(" ",OFFSET('JAN-22'!$B$1,MATCH(Sheet1!A47,'JAN-22'!$B:$B,0)-1,-1,1,1),12)-11)-Q61=0,"","NET MISMATCH"),"GROSS MISMATCH"),"")} | BH61: =+G48 -> PAN | BI61: =+A47 | BJ61: {=IFERROR(OFFSET('JAN-22'!$B$1,MATCH(Sheet1!A47,'JAN-22'!$B:$B,0)+1,0,1,1),"")} | BK61: =+J61 -> 0 | BL61: =+R61 -> 0 | BM61: {=IFERROR(OFFSET('JAN-22'!$A$1,MATCH(Sheet1!A47,'JAN-22'!$A:$A,0)-2,0,1,1),"")}
A62: 12 | B62: 44593 | C62: =IFERROR(SUM(SUMIF(OFFSET('FEB-22'!$A$1,MATCH(Sheet1!A47,'FEB-22'!$A:$A,0),0,22,1),{"BA*C","BASIC??"},OFFSET('FEB-22'!$A$1,MATCH(Sheet1!A47,'FEB-22'!$A:$A,0),1,22,1))),0) -> 0 | D62: =IFERROR(SUM(SUMIF(OFFSET('FEB-22'!$A$1,MATCH(Sheet1!A47,'FEB-22'!$A:$A,0),0,22,1),{"DA*C","D. *"},OFFSET('FEB-22'!$A$1,MATCH(Sheet1!A47,'FEB-22'!$A:$A,0),1,22,1))),0) -> 0 | E62: =IFERROR(SUM(SUMIF(OFFSET('FEB-22'!$A$1,MATCH(Sheet1!A47,'FEB-22'!$A:$A,0),0,22,1),{"H. R. A."},OFFSET('FEB-22'!$A$1,MATCH(Sheet1!A47,'FEB-22'!$A:$A,0),1,22,1))),0) -> 0 | F62: {=IFERROR(SUM(SUMIF(OFFSET('FEB-22'!$A$1,MATCH(Sheet1!A47,'FEB-22'!$A:$A,0),0,22,1),{"SP*AY*","S D A*","O.A.*","CLA (5th Pay)*","REF. Allow*","Trans.Allw.*","LF*","P. O.*","ARM*","Conv.A*","Otr.Allow*","Trans_Arrear*","BMIA*","Incentives*","Fit Allow*","KMA","NON-*","U.*","ME*A","PG*","Per.Tra"},OFFSET('FEB-22'!$A$1,MATCH(Sheet1!A47,'FEB-22'!$A:$A,0),1,22,1))),0)} -> 0 | G62: =IFERROR(SUM(SUMIF(OFFSET('FEB-22'!$A$1,MATCH(Sheet1!A47,'FEB-22'!$A:$A,0),0,22,1),{"WA"},OFFSET('FEB-22'!$A$1,MATCH(Sheet1!A47,'FEB-22'!$A:$A,0),1,22,1))),0) -> 0 | H62: =IFERROR(SUM(SUMIF(OFFSET('FEB-22'!$A$1,MATCH(Sheet1!A47,'FEB-22'!$A:$A,0),0,22,1),{"DCPS","GROSS_ADJUST"},OFFSET('FEB-22'!$A$1,MATCH(Sheet1!A47,'FEB-22'!$A:$A,0),1,22,1))),0) -> 0 | I62: {=+IFERROR(SUM(SUMIF(OFFSET('FEB-22'!$A$1,MATCH(Sheet1!A47,'FEB-22'!$A:$A,0),0,22,1),{"Basic*Arr*","7th Pay* Arr*"},OFFSET('FEB-22'!$A$1,MATCH(Sheet1!A47,'FEB-22'!$A:$A,0),1,22,1))),0)} -> 0 | J62: =SUM(C62:I62) -> 0 | K62: =IFERROR(SUM(SUMIF(OFFSET('FEB-22'!$A$1,MATCH(Sheet1!A47,'FEB-22'!$A:$A,0),2,22,1),{"*Pro*ax*"},OFFSET('FEB-22'!$A$1,MATCH(Sheet1!A47,'FEB-22'!$A:$A,0),3,22,1))),0) -> 0 | L62: =IFERROR(SUM(SUMIF(OFFSET('FEB-22'!$A$1,MATCH(Sheet1!A47,'FEB-22'!$A:$A,0),2,22,1),{"GPF_G*","DCPS"},OFFSET('FEB-22'!$A$1,MATCH(Sheet1!A47,'FEB-22'!$A:$A,0),3,22,1))),0) -> 0 | M62: {=IFERROR(SUM(SUMIF(OFFSET('FEB-22'!$A$1,MATCH(Sheet1!A47,'FEB-22'!$A:$A,0),2,22,1),{"*GIS","GIS*R"},OFFSET('FEB-22'!$A$1,MATCH(Sheet1!A47,'FEB-22'!$A:$A,0),3,22,1))),0)} -> 0 | N62: =IFERROR(SUM(SUMIF(OFFSET('FEB-22'!$A$1,MATCH(Sheet1!A47,'FEB-22'!$A:$A,0),5,22,1),{"LI*1"},OFFSET('FEB-22'!$A$1,MATCH(Sheet1!A47,'FEB-22'!$A:$A,0),6,22,1))),0) -> 0 | O62: {=IFERROR(SUM(SUMIF(OFFSET('FEB-22'!$A$1,MATCH(Sheet1!A47,'FEB-22'!$A:$A,0),2,22,1),{"HB*USE","HB*INT"},OFFSET('FEB-22'!$A$1,MATCH(Sheet1!A47,'FEB-22'!$A:$A,0),3,22,1))),0)} -> 0 | P62: {=IFERROR(SUM(SUMIF(OFFSET('FEB-22'!$A$1,MATCH(Sheet1!A47,'FEB-22'!$A:$A,0),5,22,1),{"OTHE*1","CO.*1","OTHE*2","WEL*ND","BAN*1","CLU*ND","RD*1","LI*2","MIS*US","*TAINAN*","MCA*INT*","MAIN*NANCE*","*C M Relief Fund*","Co. Op. Hsg Soc.*","GPF_ADV*","Co. Op. Cr. Soc. 2*","DCPS DA","DCPS Pay","MCA Int"},OFFSET('FEB-22'!$A$1,MATCH(Sheet1!A47,'FEB-22'!$A:$A,0),6,22,1)))+SUM(SUMIF(OFFSET('FEB-22'!$A$1,MATCH(Sheet1!A47,'FEB-22'!$A:$A,0),2,22,1),{"MCA","COM*DV*","HB*ND","CO*SOC","HRR","SRV*H","ACC*CY","F.A","STAMP_REVENUE","*C M Relief Fund*","GPF_ADV*","Co. Op. Cr. Soc. 2*","DCPS DA","DCPS Pay","MCA Int"},OFFSET('FEB-22'!$A$1,MATCH(Sheet1!A47,'FEB-22'!$A:$A,0),3,22,1))),0)} -> 0 | Q62: =+J62-H62-K62-L62-M62-N62-O62-P62-R62 -> 0 | R62: {=IFERROR(SUM(SUMIF(OFFSET('FEB-22'!$A$1,MATCH(Sheet1!A47,'FEB-22'!$A:$A,0),2,22,1),{"*I. *ax*"},OFFSET('FEB-22'!$A$1,MATCH(Sheet1!A47,'FEB-22'!$A:$A,0),3,22,1))),0)} -> 0 | S62: {=+IFERROR(IF(OFFSET('FEB-22'!$B$1,MATCH(Sheet1!A47,'FEB-22'!B:B,0)-2,0,1,1)=Sheet1!J62,IF(MID(IFERROR(OFFSET('FEB-22'!$B$1,MATCH(Sheet1!A47,'FEB-22'!$B:$B,0)-1,-1,1,1),"GROSS ERROR"),11,FIND(" ",OFFSET('FEB-22'!$B$1,MATCH(Sheet1!A47,'FEB-22'!$B:$B,0)-1,-1,1,1),12)-11)-Q62=0,"","NET MISMATCH"),"GROSS MISMATCH"),"")} | BH62: =+G48 -> PAN | BI62: =+A47 | BJ62: {=IFERROR(OFFSET('FEB-22'!$B$1,MATCH(Sheet1!A47,'FEB-22'!$B:$B,0)+1,0,1,1),"")} | BK62: =+J62 -> 0 | BL62: =+R62 -> 0 | BM62: {=IFERROR(OFFSET('FEB-22'!$A$1,MATCH(Sheet1!A47,'FEB-22'!$A:$A,0)-2,0,1,1),"")}
A63: 13 | B63: SUPP | C63: =IFERROR(SUM(SUMIF(OFFSET(SUPP!$A$1,MATCH(Sheet1!A47,SUPP!$A:$A,0),0,22,1),{"BA*C","BASIC??"},OFFSET(SUPP!$A$1,MATCH(Sheet1!A47,SUPP!$A:$A,0),1,22,1))),0) -> 0 | D63: =IFERROR(SUM(SUMIF(OFFSET(SUPP!$A$1,MATCH(Sheet1!A47,SUPP!$A:$A,0),0,22,1),{"DA*C","D. *"},OFFSET(SUPP!$A$1,MATCH(Sheet1!A47,SUPP!$A:$A,0),1,22,1))),0) -> 0 | E63: =IFERROR(SUM(SUMIF(OFFSET(SUPP!$A$1,MATCH(Sheet1!A47,SUPP!$A:$A,0),0,22,1),{"H. R. A."},OFFSET(SUPP!$A$1,MATCH(Sheet1!A47,SUPP!$A:$A,0),1,22,1))),0) -> 0 | F63: {=IFERROR(SUM(SUMIF(OFFSET(SUPP!$A$1,MATCH(Sheet1!A47,SUPP!$A:$A,0),0,22,1),{"SP*AY*","S D A*","O.A.*","CLA (5th Pay)*","REF. Allow*","Trans.Allw.*","LF*","P. O.*","ARM*","Conv.A*","Otr.Allow*","Trans_Arrear*","BMIA*","Incentives*","Fit Allow*","KMA","NON-*","U.*","ME*A","PG*","Per.Tra"},OFFSET(SUPP!$A$1,MATCH(Sheet1!A47,SUPP!$A:$A,0),1,22,1))),0)} -> 0 | G63: =IFERROR(SUM(SUMIF(OFFSET(SUPP!$A$1,MATCH(Sheet1!A47,SUPP!$A:$A,0),0,22,1),{"WA"},OFFSET(SUPP!$A$1,MATCH(Sheet1!A47,SUPP!$A:$A,0),1,22,1))),0) -> 0 | H63: =IFERROR(SUM(SUMIF(OFFSET(SUPP!$A$1,MATCH(Sheet1!A47,SUPP!$A:$A,0),0,22,1),{"DCPS","GROSS_ADJUST"},OFFSET(SUPP!$A$1,MATCH(Sheet1!A47,SUPP!$A:$A,0),1,22,1))),0) -> 0 | I63: {=+IFERROR(SUM(SUMIF(OFFSET(SUPP!$A$1,MATCH(Sheet1!A47,SUPP!$A:$A,0),0,22,1),{"Basic*Arr*","7th Pay* Arr*"},OFFSET(SUPP!$A$1,MATCH(Sheet1!A47,SUPP!$A:$A,0),1,22,1))),0)} -> 0 | J63: =SUM(C63:I63) -> 0 | K63: =IFERROR(SUM(SUMIF(OFFSET(SUPP!$A$1,MATCH(Sheet1!A47,SUPP!$A:$A,0),2,22,1),{"*Pro*ax*"},OFFSET(SUPP!$A$1,MATCH(Sheet1!A47,SUPP!$A:$A,0),3,22,1))),0) -> 0 | L63: =IFERROR(SUM(SUMIF(OFFSET(SUPP!$A$1,MATCH(Sheet1!A47,SUPP!$A:$A,0),2,22,1),{"GPF_G*","DCPS"},OFFSET(SUPP!$A$1,MATCH(Sheet1!A47,SUPP!$A:$A,0),3,22,1))),0) -> 0 | M63: {=IFERROR(SUM(SUMIF(OFFSET(SUPP!$A$1,MATCH(Sheet1!A47,SUPP!$A:$A,0),2,22,1),{"*GIS","GIS*R"},OFFSET(SUPP!$A$1,MATCH(Sheet1!A47,SUPP!$A:$A,0),3,22,1))),0)} -> 0 | N63: =IFERROR(SUM(SUMIF(OFFSET(SUPP!$A$1,MATCH(Sheet1!A47,SUPP!$A:$A,0),5,22,1),{"LI*1"},OFFSET(SUPP!$A$1,MATCH(Sheet1!A47,SUPP!$A:$A,0),6,22,1))),0) -> 0 | O63: {=IFERROR(SUM(SUMIF(OFFSET(SUPP!$A$1,MATCH(Sheet1!A47,SUPP!$A:$A,0),2,22,1),{"HB*USE","HB*INT"},OFFSET(SUPP!$A$1,MATCH(Sheet1!A47,SUPP!$A:$A,0),3,22,1))),0)} -> 0 | P63: {=IFERROR(SUM(SUMIF(OFFSET(SUPP!$A$1,MATCH(Sheet1!A47,SUPP!$A:$A,0),5,22,1),{"OTHE*1","CO.*1","OTHE*2","WEL*ND","BAN*1","CLU*ND","RD*1","LI*2","MIS*US","*TAINAN*","MCA*INT*","MAIN*NANCE*","*C M Relief Fund*","Co. Op. Hsg Soc.*","GPF_ADV*","Co. Op. Cr. Soc. 2*","DCPS DA","DCPS Pay","MCA Int"},OFFSET(SUPP!$A$1,MATCH(Sheet1!A47,SUPP!$A:$A,0),6,22,1)))+SUM(SUMIF(OFFSET(SUPP!$A$1,MATCH(Sheet1!A47,SUPP!$A:$A,0),2,22,1),{"MCA","COM*DV*","HB*ND","CO*SOC","HRR","SRV*H","ACC*CY","F.A","STAMP_REVENUE","*C M Relief Fund*","GPF_ADV*","Co. Op. Cr. Soc. 2*","DCPS DA","DCPS Pay","MCA Int"},OFFSET(SUPP!$A$1,MATCH(Sheet1!A47,SUPP!$A:$A,0),3,22,1))),0)} -> 0 | Q63: =+J63-H63-K63-L63-M63-N63-O63-P63-R63 -> 0 | R63: {=IFERROR(SUM(SUMIF(OFFSET(SUPP!$A$1,MATCH(Sheet1!A47,SUPP!$A:$A,0),2,22,1),{"*I. *ax*"},OFFSET(SUPP!$A$1,MATCH(Sheet1!A47,SUPP!$A:$A,0),3,22,1))),0)} -> 0 | S63: {=+IFERROR(IF(OFFSET(SUPP!$B$1,MATCH(Sheet1!A47,SUPP!B:B,0)-2,0,1,1)=Sheet1!J63,IF(MID(IFERROR(OFFSET(SUPP!$B$1,MATCH(Sheet1!A47,SUPP!$B:$B,0)-1,-1,1,1),"GROSS ERROR"),11,FIND(" ",OFFSET(SUPP!$B$1,MATCH(Sheet1!A47,SUPP!$B:$B,0)-1,-1,1,1),12)-11)-Q63=0,"","NET MISMATCH"),"GROSS MISMATCH"),"")} | BH63: =+G48 -> PAN | BI63: =+A47 | BJ63: {=IFERROR(OFFSET(SUPP!$B$1,MATCH(Sheet1!A47,SUPP!$B:$B,0)+1,0,1,1),"")} | BK63: =+J63 -> 0 | BL63: =+R63 -> 0 | BM63: =IFERROR(OFFSET(SUPP!$A$1,MATCH(Sheet1!A47,SUPP!$A:$A,0)-2,0,1,1),"")
A64: 14 | B64: MED. BILL | C64: 0 | D64: 0 | E64: 0 | F64: 0 | G64: 0 | H64: 0 | I64: =IFERROR(SUM(SUMIF(OFFSET('AUG-21'!$A$1,MATCH(Sheet1!A55,'AUG-21'!$A:$A,0),0,22,1),{"Arr*","7th Pay* Arr*","Basic Arr."},OFFSET('AUG-21'!$A$1,MATCH(Sheet1!A55,'AUG-21'!$A:$A,0),1,22,1))),0) -> 0 | J64: 0 | K64: 0 | L64: 0 | M64: 0 | N64: 0 | O64: 0 | P64: 0 | Q64: =+J64-H64-K64-L64-M64-N64-O64-P64-P84 -> 0 | R64: 0
N65: 0 | O65: 0 | P65: 0 | Q65: =+J65-H65-K65-L65-M65-N65-O65-P65-P85 -> 0 | R65: 0
B66: TOTAL | C66: =SUM(C51:C65) -> 0 | D66: =SUM(D51:D65) -> 0 | E66: =SUM(E51:E65) -> 0 | F66: =SUM(F51:F65) -> 0 | G66: =SUM(G51:G65) -> 0 | H66: =SUM(H51:H65) -> 0 | I66: =SUM(I51:I65) -> 0 | J66: =SUM(J51:J65) -> 0 | ... R66: =SUM(R51:R65) -> 0
B67: GN
B68: NEW
B70: GROSS SALARY | D70: =+J66 -> 0 | G70: SAVINGS U/S. 80C | K70: Taxable Income | M70: =+D81-H83-H92 -> -50000 | U70: {=+UPPER(G48)} -> PAN | AB70: =+UPPER(A47) | AC70: =+M79-M81 -> 0 | AD70: =+R66 -> 0
B71: LESS : | F71: i) | G71: GPF/DCPS Employee | H71: =+IF(H66>0,L66-H86,L66) -> 0 | K71: Old Tax Regime | M71: =IF(AND(N49="M",M70<=250000),0,IF(AND(N49="F",M70<=250000),0,IF(AND(N49="M",M70<=500000),ROUND((M70-250000)*5%,0),IF(AND(N49="F",M70<=500000),ROUND((M70-250000)*5%,0),IF(AND(N49="M",M70<=1000000),12500+ROUND((M70-500000)*20%,0),IF(AND(N49="F",M70<=1000000),12500+ROUND((M70-500000)*20%,0),IF(AND(N49="M",M70>=1000000),112500+ROUND((M70-1000000)*30%,0),112500+ROUND((M70-1000000)*30%,0)))))))) -> 0
B72: STD. DED. | D72: 50000 | F72: ii) | G72: GIS | H72: =+M66 -> 0 | K72: New Tax Regime | M72: =+IF(AND(B67="GN",(D70-H87)<=250000,B68="OLD"),0,IF(AND(B67="SC",(D70-H87)<=300000,B68="OLD"),0,IF(AND(B67="SSC",(D70-H87)<=500000,B68="OLD"),0,IF(AND(B67="GN",B68="OLD",(D70-H87)<=500000),ROUND(((D70-H87)-250000)*5%,0),IF(AND(B68="OLD",B67="SC",(D70-H87)<=500000),ROUND(((D70-H87)-300000)*5%,0),IF(AND(B68="OLD",(D70-H87)<=1000000,B67="GN"),ROUND(((D70-H87)-500000)*20%+(12500),0),IF(AND(B67="SC",B68="OLD",(D70-H87)<=1000000),ROUND(((D70-H87)-500000)*20%+(10000),0),IF(AND(B67="SSC",B68="OLD",(D70-H87)<=1000000),ROUND(((D70-H87)-500000)*20%,0),IF(AND(B68="OLD",B67="GN",(D70-H87)>1000000),ROUND(((D70-H87)-1000000)*30%+(112500),0),IF(AND(B68="OLD",B67="SC",(D70-H87)>1000000),ROUND(((D70-H87)-1000000)*30%+(110000),0),IF(AND(B67="SSC",B68="OLD",(D70-H87)>1000000),ROUND(((D70-H87)-1000000)*30%+(100000),0),IF(AND(B68="NEW",(D70-H87)<=250000),0,IF(AND(B68="NEW",(D70-H87)<=500000),ROUND(((D70-H87)-250000)*5%,0),IF(AND(B68="NEW",(D70-H87)<=750000),ROUND(((D70-H87)-500000)*10%+(12500),0),IF(AND(B68="NEW",(D70-H87)<=1000000),ROUND(((D70-H87)-750000)*15%+(37500),0),IF(AND(B68="NEW",(D70-H87)<=1250000),ROUND(((D70-H87)-1000000)*20%+(75000),0),IF(AND(B68="NEW",(D70-H87)<=1500000),ROUND(((D70-H87)-1250000)*25%+(125000),0),IF(AND(B68="NEW",(D70-H87)>1500000),ROUND(((D70-H87)-1500000)*30%+(187500),0))))))))))))))))))) -> 0
B73: WA | D73: =+G66 -> 0 | F73: iii) | G73: L.I.C. [Salary] | H73: =+N66 -> 0
B74: Professional Tax | D74: =+K66 -> 0 | F74: iv | G74: L.I.C. [Individual] | H74: 0 | K74: Tax on Total Income | M74: =+IF(M71>M72,M72,M71) -> 0
B75: Other Allowance | D75: 0 | F75: v) | G75: Housing Loan Principal | H75: =+IF(O50="HBA HOUSE",O66,0) -> 0
B76: H. R. A. Exempt | D76: =IF(C88=0,0,MIN(D85:D89)) -> 0 | F76: vi) | G76: Educational Fees | H76: 0 | K76: (-) : Rebate 87 | M76: =IF(M70>500000,0,IF(M74>=12500,12500,M74)) -> 0
B77: B.D.D.S Allowance | D77: 0 | F77: vii) | G77: Mutual Fund | H77: 0 | K77: Tax on Total Inc. | M77: =+M74-M76 -> 0
B78: House Loan Int. | D78: =+IF(O50=B78,O66,0) -> 0 | F78: viii) | G78: PLI | H78: 0 | K78: (+) 4% Edu.Cess | M78: =ROUND(M77*4%,0) -> 0
F79: ix) | G79: Sukanya Yojna | H79: 0 | K79: Tax Payable | M79: =+M77+M78 -> 0
B80: Total Deductions | D80: =SUM(D72:D77)+IF(D78>200000, 200000,D78 ) -> 50000 | F80: x) | G80: PPF | H80: 0 | K80: (-) Already paid | M80: =+R66 -> 0
B81: BALANCE | D81: =+D70-D80 -> -50000 | F81: xI) | G81: SBI Life Insurance | H81: 0 | K81: (-) Relief 89 | M81: 0
G82: Total Savings | H82: =SUM(H71:H81) -> 0
G83: Eligible Savings | H83: =+IF(H82<=150000,H82,150000) -> 0
B84: HRA CALCULATION | K84: Total Tax Payable | M84: =+M79-M80-M81 -> 0
B85: HRA RECEIVED | D85: =+E66 -> 0 | G85: SAVINGS CHAPTER VIA
B86: BASIC + DA 40 % | D86: =+(C66+D66)*40/100 -> 0 | F86: i) | G86: 80CCD (1B) | H86: =+IF(AND(H66>0,L66>50000),50000,IF(H66>0,L66,0)) -> 0
B87: BASIC +DA 10 % | C87: =+(C66+D66)*10/100 -> 0 | F87: ii) | G87: DCPS Employer | H87: =+H66 -> 0
B88: RENT PAID | C88: 0 | F88: iii) | G88: 80G /( C. M. Fund) | H88: {=IFERROR(SUM(SUMIF(OFFSET('MAY-21'!$A$1,MATCH(Sheet1!A47,'MAY-21'!$A:$A,0),5,22,1),{"*C M Relief Fund*"},OFFSET('MAY-21'!$A$1,MATCH(Sheet1!A47,'MAY-21'!$A:$A,0),6,22,1)))+SUM(SUMIF(OFFSET('MAY-21'!$A$1,MATCH(Sheet1!A47,'MAY-21'!$A:$A,0),2,22,1),{"*C M Relief Fund*"},OFFSET('MAY-21'!$A$1,MATCH(Sheet1!A47,'MAY-21'!$A:$A,0),3,22,1))),0)} -> 0
B89: BASIC +DA 10 % - RENT PAID | D89: =+IF(C88>C87,C88-C87, 0) -> 0 | F89: iv) | G89: 80D - Mediclaim Policy | H89: 0
F90: v) | G90: 80U - Handicapped | H90: 0
F91: vi) | G91: 80E - Edu. Loan Intrest | H91: 0
H92: =SUM(H86:H91) -> 0
A94: =+INDEX('EMP NAMES'!D:D,Sheet1!U98) | I94: =+IF(M118=M121,"OLD","NEW") -> OLD
G95: =IFERROR(INDEX('EMP NAMES'!E:E,Sheet1!U98),"PAN") -> PAN
N96: M
A97: SR. | B97: MONTH | C97: BASIC | D97: DA | E97: H. R. A. | F97: TA/SDA/CLA/RA/ETC | G97: WA | H97: DCPS Employer | I97: Basic Arr. / 7th Pay DCPS/NPS Arr | J97: Total Emolument | K97: PT | L97: GPF/DCPS Employee | M97: GIS | N97: LIC | O97: HBA HOUSE | P97: OTHER | Q97: NET | R97: I. TAX | S97: GROSS TOTAL ERROR | U97: SR | V97: 115BAC Section Applicable (New Tax Regime) | W97: PAN NO. | X97: NAME OF EMPLOYEE | Y97: Salary as per provisions contained in section 17(1) | Z97: Value of perquisites [section 17(2)] (as per FormNo.12BA, wherever applicable) | AA97: Reported total amount of salary received from other employer(s) | AB97: GROSS SALARY | AC97: STD DED | AD97: PT | AE97: HRA | AF97: OTHER ALLOWANCES 10 | AG97: NET | AH97: HSG. INT | AI97: OTHER INCOME | AJ97: NET | AK97: 80C INVESTMENT | AL97: 80C ELIGIBLE | AM97: 80CCD1 GROSS | AN97: 80CCD1 ELIGIBLE | AO97: 80CCD1(B) ELIGIBLE | AP97: 80CCD2 ELIGIBLE | AQ97: 80D | AR97: 80E | AS97: 80G | AT97: OTHERS | AU97: TOTAL ELIGIBLE SAVING | AV97: TAXABLE | AW97: TAX | AX97: REBATE | AY97: CESS | AZ97: RELIEF | BA97: TOTAL TAX | BB97: TDS-CURRENT | BC97: TDS-PREV. | BD97: TOTAL | BE97: R/P
A98: 1 | B98: 44256 | C98: =IFERROR(SUM(SUMIF(OFFSET('MAR-21'!$A$1,MATCH(Sheet1!A94,'MAR-21'!$A:$A,0),0,22,1),{"BA*C","BASIC??"},OFFSET('MAR-21'!$A$1,MATCH(Sheet1!A94,'MAR-21'!$A:$A,0),1,22,1))),0) -> 0 | D98: =IFERROR(SUM(SUMIF(OFFSET('MAR-21'!$A$1,MATCH(Sheet1!A94,'MAR-21'!$A:$A,0),0,22,1),{"DA*C","D. *"},OFFSET('MAR-21'!$A$1,MATCH(Sheet1!A94,'MAR-21'!$A:$A,0),1,22,1))),0) -> 0 | E98: =IFERROR(SUM(SUMIF(OFFSET('MAR-21'!$A$1,MATCH(Sheet1!A94,'MAR-21'!$A:$A,0),0,22,1),{"H. R. A."},OFFSET('MAR-21'!$A$1,MATCH(Sheet1!A94,'MAR-21'!$A:$A,0),1,22,1))),0) -> 0 | F98: {=IFERROR(SUM(SUMIF(OFFSET('MAR-21'!$A$1,MATCH(Sheet1!A94,'MAR-21'!$A:$A,0),0,22,1),{"SP*AY*","S D A*","O.A.*","CLA (5th Pay)*","REF. Allow*","Trans.Allw.*","LF*","P. O.*","ARM*","Conv.A*","Otr.Allow*","Trans_Arrear*","BMIA*","Incentives*","Fit Allow*","KMA","NON-*","U.*","ME*A","PG*","Per.Tra"},OFFSET('MAR-21'!$A$1,MATCH(Sheet1!A94,'MAR-21'!$A:$A,0),1,22,1))),0)} -> 0 | G98: =IFERROR(SUM(SUMIF(OFFSET('MAR-21'!$A$1,MATCH(Sheet1!A94,'MAR-21'!$A:$A,0),0,22,1),{"WA"},OFFSET('MAR-21'!$A$1,MATCH(Sheet1!A94,'MAR-21'!$A:$A,0),1,22,1))),0) -> 0 | H98: =IFERROR(SUM(SUMIF(OFFSET('MAR-21'!$A$1,MATCH(Sheet1!A94,'MAR-21'!$A:$A,0),0,22,1),{"DCPS","GROSS_ADJUST"},OFFSET('MAR-21'!$A$1,MATCH(Sheet1!A94,'MAR-21'!$A:$A,0),1,22,1))),0) -> 0 | I98: {=+IFERROR(SUM(SUMIF(OFFSET('MAR-21'!$A$1,MATCH(Sheet1!A94,'MAR-21'!$A:$A,0),0,22,1),{"Basic*Arr*","7th Pay* Arr*"},OFFSET('MAR-21'!$A$1,MATCH(Sheet1!A94,'MAR-21'!$A:$A,0),1,22,1))),0)} -> 0 | J98: =+SUM(C98:I98) -> 0 | K98: =IFERROR(SUM(SUMIF(OFFSET('MAR-21'!$A$1,MATCH(Sheet1!A94,'MAR-21'!$A:$A,0),2,22,1),{"*Pro*ax*"},OFFSET('MAR-21'!$A$1,MATCH(Sheet1!A94,'MAR-21'!$A:$A,0),3,22,1))),0) -> 0 | L98: =IFERROR(SUM(SUMIF(OFFSET('MAR-21'!$A$1,MATCH(Sheet1!A94,'MAR-21'!$A:$A,0),2,22,1),{"GPF_G*","DCPS"},OFFSET('MAR-21'!$A$1,MATCH(Sheet1!A94,'MAR-21'!$A:$A,0),3,22,1))),0) -> 0 | M98: =IFERROR(SUM(SUMIF(OFFSET('MAR-21'!$A$1,MATCH(Sheet1!A94,'MAR-21'!$A:$A,0),2,22,1),{"*GIS","GIS*R"},OFFSET('MAR-21'!$A$1,MATCH(Sheet1!A94,'MAR-21'!$A:$A,0),3,22,1))),0) -> 0 | N98: =IFERROR(SUM(SUMIF(OFFSET('MAR-21'!$A$1,MATCH(Sheet1!A94,'MAR-21'!$A:$A,0),5,22,1),{"LI*1"},OFFSET('MAR-21'!$A$1,MATCH(Sheet1!A94,'MAR-21'!$A:$A,0),6,22,1))),0) -> 0 | O98: {=IFERROR(SUM(SUMIF(OFFSET('MAR-21'!$A$1,MATCH(Sheet1!A94,'MAR-21'!$A:$A,0),2,22,1),{"*HB*USE","HB*INT"},OFFSET('MAR-21'!$A$1,MATCH(Sheet1!A94,'MAR-21'!$A:$A,0),3,22,1))),0)} -> 0 | P98: {=IFERROR(SUM(SUMIF(OFFSET('MAR-21'!$A$1,MATCH(Sheet1!A94,'MAR-21'!$A:$A,0),5,22,1),{"OTHE*1","CO.*1","OTHE*2","WEL*ND","BAN*1","CLU*ND","RD*1","LI*2","MIS*US","*TAINAN*","MCA*INT*","MAIN*NANCE*","*C M Relief Fund*","Co. Op. Hsg Soc.*","GPF_ADV*","Co. Op. Cr. Soc. 2*","DCPS DA","DCPS Pay","MCA Int"},OFFSET('MAR-21'!$A$1,MATCH(Sheet1!A94,'MAR-21'!$A:$A,0),6,22,1)))+SUM(SUMIF(OFFSET('MAR-21'!$A$1,MATCH(Sheet1!A94,'MAR-21'!$A:$A,0),2,22,1),{"MCA","COM*DV*","HB*ND","CO*SOC","HRR","SRV*H","ACC*CY","F.A","STAMP_REVENUE","*C M Relief Fund*","GPF_ADV*","Co. Op. Cr. Soc. 2*","DCPS DA","DCPS Pay","MCA Int"},OFFSET('MAR-21'!$A$1,MATCH(Sheet1!A94,'MAR-21'!$A:$A,0),3,22,1))),0)} -> 0 | Q98: =+J98-H98-K98-L98-M98-N98-O98-P98-R98 -> 0 | R98: =IFERROR(SUM(SUMIF(OFFSET('MAR-21'!$A$1,MATCH(Sheet1!A94,'MAR-21'!$A:$A,0),2,22,1),{"*I.*ax*"},OFFSET('MAR-21'!$A$1,MATCH(Sheet1!A94,'MAR-21'!$A:$A,0),3,22,1))),0) -> 0 | S98: {=+IFERROR(IF(OFFSET('MAR-21'!$B$1,MATCH(Sheet1!A94,'MAR-21'!B:B,0)-2,0,1,1)=Sheet1!J98,IF(MID(IFERROR(OFFSET('MAR-21'!$B$1,MATCH(Sheet1!A94,'MAR-21'!$B:$B,0)-1,-1,1,1),"GROSS ERROR"),11,FIND(" ",OFFSET('MAR-21'!$B$1,MATCH(Sheet1!A94,'MAR-21'!$B:$B,0)-1,-1,1,1),12)-11)-Q98=0,"","NET MISMATCH"),"GROSS MISMATCH"),"")} | U98: =+U51+1 -> 4 | V98: =+IF(M118=M121,"NO","YES") -> NO | W98: =+G95 -> PAN | X98: =+A94 | Y98: =+D117 -> 0 | Z98: 0 | AA98: 0 | AB98: =+SUM(Y98:AA98) -> 0 | AC98: =+D119 -> 50000 | AD98: =+D121 -> 0 | AE98: =+D123 -> 0 | AF98: =+D122+D120+D124 -> 0 | AG98: =+AB98-SUM(AC98:AF98) -> -50000 | AH98: =+IF(D125>=200000,-200000,-D125) -> 0 | AI98: 0 | AJ98: =+AG98+AH98+AI98 -> -50000 | AK98: =+IF(H134>0,H129-H118,H129) -> 0 | AL98: {=+IF(IF(AND((AK98+AN98)>=150000,AK98>=150000),150000-AN98,AK98)<0,0,IF(AND((AK98+AN98)>=150000,AK98>=150000),150000-AN98,IF(AND(SUM(AK98+AN98)>150000,AK98<150000),150000-AN98,AK98)))} -> 0 | AM98: =+IF(H113>0,L113,0) -> 0 | AN98: =+AM98-AO98 -> 0 | AO98: =+IF(AND(H113>0,L113>50000),50000,IF(H113>0,L113,0)) -> 0 | AP98: =+H113 -> 0 | AQ98: =+H136 -> 0 | AR98: =+H138 -> 0 | AS98: =+H135 -> 0 | AT98: =+H137 -> 0 | AU98: =+SUM(AQ98:AT98)+AP98+AO98+AN98+AL98 -> 0 | AV98: =+AJ98-AU98 -> -50000 | AW98: =+M121 -> 0 | AX98: =+M123 -> 0 | AY98: =+M125 -> 0 | AZ98: =+M128 -> 0 | BA98: =+AW98-AX98+AY98-AZ98 -> 0 | BB98: =+M127 -> 0 | BC98: 0 | BD98: =+BB98+BC98 -> 0 | BE98: =+BA98-BD98 -> 0 | BF98: =+IF(AV98=M117,"","NOT OK") | BH98: =+G95 -> PAN | BI98: =+A94 | BJ98: {=IFERROR(OFFSET('MAR-21'!$B$1,MATCH(Sheet1!A94,'MAR-21'!$B:$B,0)+1,0,1,1),"")} | BK98: =+J98 -> 0 | BL98: =+R98 -> 0 | BM98: {=IFERROR(OFFSET('MAR-21'!$A$1,MATCH(Sheet1!A94,'MAR-21'!$A:$A,0)-2,0,1,1),"")}
A99: 2 | B99: 44287 | C99: =IFERROR(SUM(SUMIF(OFFSET('APR-21'!$A$1,MATCH(Sheet1!A94,'APR-21'!$A:$A,0),0,22,1),{"BA*C","BASIC??"},OFFSET('APR-21'!$A$1,MATCH(Sheet1!A94,'APR-21'!$A:$A,0),1,22,1))),0) -> 0 | D99: =IFERROR(SUM(SUMIF(OFFSET('APR-21'!$A$1,MATCH(Sheet1!A94,'APR-21'!$A:$A,0),0,22,1),{"DA*C","D. *"},OFFSET('APR-21'!$A$1,MATCH(Sheet1!A94,'APR-21'!$A:$A,0),1,22,1))),0) -> 0 | E99: =IFERROR(SUM(SUMIF(OFFSET('APR-21'!$A$1,MATCH(Sheet1!A94,'APR-21'!$A:$A,0),0,22,1),{"H. R. A."},OFFSET('APR-21'!$A$1,MATCH(Sheet1!A94,'APR-21'!$A:$A,0),1,22,1))),0) -> 0 | F99: =IFERROR(SUM(SUMIF(OFFSET('APR-21'!$A$1,MATCH(Sheet1!A94,'APR-21'!$A:$A,0),0,22,1),{"SP*AY*","S D A*","O.A.*","CLA (5th Pay)*","REF. Allow*","Trans.Allw.*","LF*","P. O.*","ARM*","Conv.A*","Otr.Allow*","Trans_Arrear*","BMIA*","Incentives*","Fit Allow*","KMA","NON-*","U.*","ME*A","PG*","Per.Tra"},OFFSET('APR-21'!$A$1,MATCH(Sheet1!A94,'APR-21'!$A:$A,0),1,22,1))),0) -> 0 | G99: =IFERROR(SUM(SUMIF(OFFSET('APR-21'!$A$1,MATCH(Sheet1!A94,'APR-21'!$A:$A,0),0,22,1),{"WA"},OFFSET('APR-21'!$A$1,MATCH(Sheet1!A94,'APR-21'!$A:$A,0),1,22,1))),0) -> 0 | H99: =IFERROR(SUM(SUMIF(OFFSET('APR-21'!$A$1,MATCH(Sheet1!A94,'APR-21'!$A:$A,0),0,22,1),{"DCPS","GROSS_ADJUST"},OFFSET('APR-21'!$A$1,MATCH(Sheet1!A94,'APR-21'!$A:$A,0),1,22,1))),0) -> 0 | I99: {=+IFERROR(SUM(SUMIF(OFFSET('APR-21'!$A$1,MATCH(Sheet1!A94,'APR-21'!$A:$A,0),0,22,1),{"Arr*","7th Pay* Arr*","Basic Arr."},OFFSET('APR-21'!$A$1,MATCH(Sheet1!A94,'APR-21'!$A:$A,0),1,22,1))),0)} -> 0 | J99: =SUM(C99:I99) -> 0 | K99: =IFERROR(SUM(SUMIF(OFFSET('APR-21'!$A$1,MATCH(Sheet1!A94,'APR-21'!$A:$A,0),2,22,1),{"*Pro*ax*"},OFFSET('APR-21'!$A$1,MATCH(Sheet1!A94,'APR-21'!$A:$A,0),3,22,1))),0) -> 0 | L99: =IFERROR(SUM(SUMIF(OFFSET('APR-21'!$A$1,MATCH(Sheet1!A94,'APR-21'!$A:$A,0),2,22,1),{"GPF_G*","DCPS"},OFFSET('APR-21'!$A$1,MATCH(Sheet1!A94,'APR-21'!$A:$A,0),3,22,1))),0) -> 0 | M99: =IFERROR(SUM(SUMIF(OFFSET('APR-21'!$A$1,MATCH(Sheet1!A94,'APR-21'!$A:$A,0),2,22,1),{"*GIS","GIS*R"},OFFSET('APR-21'!$A$1,MATCH(Sheet1!A94,'APR-21'!$A:$A,0),3,22,1))),0) -> 0 | N99: =IFERROR(SUM(SUMIF(OFFSET('APR-21'!$A$1,MATCH(Sheet1!A94,'APR-21'!$A:$A,0),5,22,1),{"LI*1"},OFFSET('APR-21'!$A$1,MATCH(Sheet1!A94,'APR-21'!$A:$A,0),6,22,1))),0) -> 0 | O99: {=IFERROR(SUM(SUMIF(OFFSET('APR-21'!$A$1,MATCH(Sheet1!A94,'APR-21'!$A:$A,0),2,22,1),{"HB*USE","HB*INT"},OFFSET('APR-21'!$A$1,MATCH(Sheet1!A94,'APR-21'!$A:$A,0),3,22,1))),0)} -> 0 | P99: {=IFERROR(SUM(SUMIF(OFFSET('APR-21'!$A$1,MATCH(Sheet1!A94,'APR-21'!$A:$A,0),5,22,1),{"OTHE*1","CO.*1","OTHE*2","WEL*ND","BAN*1","CLU*ND","RD*1","LI*2","MIS*US","*TAINAN*","MCA*INT*","MAIN*NANCE*","*C M Relief Fund*","Co. Op. Hsg Soc.*","GPF_ADV*","Co. Op. Cr. Soc. 2*","DCPS DA","DCPS Pay","MCA Int"},OFFSET('APR-21'!$A$1,MATCH(Sheet1!A94,'APR-21'!$A:$A,0),6,22,1)))+SUM(SUMIF(OFFSET('APR-21'!$A$1,MATCH(Sheet1!A94,'APR-21'!$A:$A,0),2,22,1),{"MCA","COM*DV*","HB*ND","CO*SOC","HRR","SRV*H","ACC*CY","F.A","STAMP_REVENUE","*C M Relief Fund*","GPF_ADV*","Co. Op. Cr. Soc. 2*","DCPS DA","DCPS Pay","MCA Int"},OFFSET('APR-21'!$A$1,MATCH(Sheet1!A94,'APR-21'!$A:$A,0),3,22,1))),0)} -> 0 | Q99: =+J99-H99-K99-L99-M99-N99-O99-P99-R99 -> 0 | R99: {=IFERROR(SUM(SUMIF(OFFSET('APR-21'!$A$1,MATCH(Sheet1!A94,'APR-21'!$A:$A,0),2,22,1),{"*I. *ax*"},OFFSET('APR-21'!$A$1,MATCH(Sheet1!A94,'APR-21'!$A:$A,0),3,22,1))),0)} -> 0 | S99: {=+IFERROR(IF(OFFSET('APR-21'!$B$1,MATCH(Sheet1!A94,'APR-21'!B:B,0)-2,0,1,1)=Sheet1!J99,IF(MID(IFERROR(OFFSET('APR-21'!$B$1,MATCH(Sheet1!A94,'APR-21'!$B:$B,0)-1,-1,1,1),"GROSS ERROR"),11,FIND(" ",OFFSET('APR-21'!$B$1,MATCH(Sheet1!A94,'APR-21'!$B:$B,0)-1,-1,1,1),12)-11)-Q99=0,"","NET MISMATCH"),"GROSS MISMATCH"),"")} | BH99: =+G95 -> PAN | BI99: =+A94 | BJ99: {=IFERROR(OFFSET('APR-21'!$B$1,MATCH(Sheet1!A94,'APR-21'!$B:$B,0)+1,0,1,1),"")} | BK99: =+J99 -> 0 | BL99: =+R99 -> 0 | BM99: {=IFERROR(OFFSET('APR-21'!$A$1,MATCH(Sheet1!A94,'APR-21'!$A:$A,0)-2,0,1,1),"")}
A100: 3 | B100: 44317 | C100: =IFERROR(SUM(SUMIF(OFFSET('MAY-21'!$A$1,MATCH(Sheet1!A94,'MAY-21'!$A:$A,0),0,22,1),{"BA*C","BASIC??"},OFFSET('MAY-21'!$A$1,MATCH(Sheet1!A94,'MAY-21'!$A:$A,0),1,22,1))),0) -> 0 | D100: =IFERROR(SUM(SUMIF(OFFSET('MAY-21'!$A$1,MATCH(Sheet1!A94,'MAY-21'!$A:$A,0),0,22,1),{"DA*C","D. *"},OFFSET('MAY-21'!$A$1,MATCH(Sheet1!A94,'MAY-21'!$A:$A,0),1,22,1))),0) -> 0 | E100: =IFERROR(SUM(SUMIF(OFFSET('MAY-21'!$A$1,MATCH(Sheet1!A94,'MAY-21'!$A:$A,0),0,22,1),{"H. R. A."},OFFSET('MAY-21'!$A$1,MATCH(Sheet1!A94,'MAY-21'!$A:$A,0),1,22,1))),0) -> 0 | F100: {=IFERROR(SUM(SUMIF(OFFSET('MAY-21'!$A$1,MATCH(Sheet1!A94,'MAY-21'!$A:$A,0),0,22,1),{"SP*AY*","S D A*","O.A.*","CLA (5th Pay)*","REF. Allow*","Trans.Allw.*","LF*","P. O.*","ARM*","Conv.A*","Otr.Allow*","Trans_Arrear*","BMIA*","Incentives*","Fit Allow*","KMA","NON-*","U.*","ME*A","PG*","Per.Tra"},OFFSET('MAY-21'!$A$1,MATCH(Sheet1!A94,'MAY-21'!$A:$A,0),1,22,1))),0)} -> 0 | G100: =IFERROR(SUM(SUMIF(OFFSET('MAY-21'!$A$1,MATCH(Sheet1!A94,'MAY-21'!$A:$A,0),0,22,1),{"WA"},OFFSET('MAY-21'!$A$1,MATCH(Sheet1!A94,'MAY-21'!$A:$A,0),1,22,1))),0) -> 0 | H100: =IFERROR(SUM(SUMIF(OFFSET('MAY-21'!$A$1,MATCH(Sheet1!A94,'MAY-21'!$A:$A,0),0,22,1),{"DCPS","GROSS_ADJUST"},OFFSET('MAY-21'!$A$1,MATCH(Sheet1!A94,'MAY-21'!$A:$A,0),1,22,1))),0) -> 0 | I100: {=+IFERROR(SUM(SUMIF(OFFSET('MAY-21'!$A$1,MATCH(Sheet1!A94,'MAY-21'!$A:$A,0),0,22,1),{"Arr*","7th Pay* Arr*","Basic Arr.","DA Arr"},OFFSET('MAY-21'!$A$1,MATCH(Sheet1!A94,'MAY-21'!$A:$A,0),1,22,1))),0)} -> 0 | J100: =SUM(C100:I100) -> 0 | K100: =IFERROR(SUM(SUMIF(OFFSET('MAY-21'!$A$1,MATCH(Sheet1!A94,'MAY-21'!$A:$A,0),2,22,1),{"*Pro*ax*"},OFFSET('MAY-21'!$A$1,MATCH(Sheet1!A94,'MAY-21'!$A:$A,0),3,22,1))),0) -> 0 | L100: =IFERROR(SUM(SUMIF(OFFSET('MAY-21'!$A$1,MATCH(Sheet1!A94,'MAY-21'!$A:$A,0),2,22,1),{"GPF_G*","DCPS"},OFFSET('MAY-21'!$A$1,MATCH(Sheet1!A94,'MAY-21'!$A:$A,0),3,22,1))),0) -> 0 | M100: =IFERROR(SUM(SUMIF(OFFSET('MAY-21'!$A$1,MATCH(Sheet1!A94,'MAY-21'!$A:$A,0),2,22,1),{"*GIS","GIS*R"},OFFSET('MAY-21'!$A$1,MATCH(Sheet1!A94,'MAY-21'!$A:$A,0),3,22,1))),0) -> 0 | N100: =IFERROR(SUM(SUMIF(OFFSET('MAY-21'!$A$1,MATCH(Sheet1!A94,'MAY-21'!$A:$A,0),5,22,1),{"LI*1"},OFFSET('MAY-21'!$A$1,MATCH(Sheet1!A94,'MAY-21'!$A:$A,0),6,22,1))),0) -> 0 | O100: {=IFERROR(SUM(SUMIF(OFFSET('MAY-21'!$A$1,MATCH(Sheet1!A94,'MAY-21'!$A:$A,0),2,22,1),{"HB*USE","HB*INT"},OFFSET('MAY-21'!$A$1,MATCH(Sheet1!A94,'MAY-21'!$A:$A,0),3,22,1))),0)} -> 0 | P100: {=IFERROR(SUM(SUMIF(OFFSET('MAY-21'!$A$1,MATCH(Sheet1!A94,'MAY-21'!$A:$A,0),5,22,1),{"OTHE*1","CO.*1","OTHE*2","WEL*ND","BAN*1","CLU*ND","RD*1","LI*2","MIS*US","*TAINAN*","MCA*INT*","MAIN*NANCE*","*C M Relief Fund*","Co. Op. Hsg Soc.*","GPF_ADV*","Co. Op. Cr. Soc. 2*","DCPS DA","DCPS Pay","MCA Int"},OFFSET('MAY-21'!$A$1,MATCH(Sheet1!A94,'MAY-21'!$A:$A,0),6,22,1)))+SUM(SUMIF(OFFSET('MAY-21'!$A$1,MATCH(Sheet1!A94,'MAY-21'!$A:$A,0),2,22,1),{"MCA","COM*DV*","HB*ND","CO*SOC","HRR","SRV*H","ACC*CY","F.A","STAMP_REVENUE","*C M Relief Fund*","GPF_ADV*","Co. Op. Cr. Soc. 2*","DCPS DA","DCPS Pay","MCA Int"},OFFSET('MAY-21'!$A$1,MATCH(Sheet1!A94,'MAY-21'!$A:$A,0),3,22,1))),0)} -> 0 | Q100: =+J100-H100-K100-L100-M100-N100-O100-P100-R100 -> 0 | R100: =IFERROR(SUM(SUMIF(OFFSET('MAY-21'!$A$1,MATCH(Sheet1!A94,'MAY-21'!$A:$A,0),2,22,1),{"*I. *ax*"},OFFSET('MAY-21'!$A$1,MATCH(Sheet1!A94,'MAY-21'!$A:$A,0),3,22,1))),0) -> 0 | S100: {=+IFERROR(IF(OFFSET('MAY-21'!$B$1,MATCH(Sheet1!A94,'MAY-21'!B:B,0)-2,0,1,1)=Sheet1!J100,IF(MID(IFERROR(OFFSET('MAY-21'!$B$1,MATCH(Sheet1!A94,'MAY-21'!$B:$B,0)-1,-1,1,1),"GROSS ERROR"),11,FIND(" ",OFFSET('MAY-21'!$B$1,MATCH(Sheet1!A94,'MAY-21'!$B:$B,0)-1,-1,1,1),12)-11)-Q100=0,"","NET MISMATCH"),"GROSS MISMATCH"),"")} | BH100: =+G95 -> PAN | BI100: =+A94 | BJ100: {=IFERROR(OFFSET('MAY-21'!$B$1,MATCH(Sheet1!A94,'MAY-21'!$B:$B,0)+1,0,1,1),"")} | BK100: =+J100 -> 0 | BL100: =+R100 -> 0 | BM100: {=+IFERROR(OFFSET('MAY-21'!$A$1,MATCH(Sheet1!A94,'MAY-21'!$A:$A,0)-2,0,1,1),"")}
A101: 4 | B101: 44348 | C101: =IFERROR(SUM(SUMIF(OFFSET('JUN-21'!$A$1,MATCH(Sheet1!A94,'JUN-21'!$A:$A,0),0,22,1),{"BA*C","BASIC??"},OFFSET('JUN-21'!$A$1,MATCH(Sheet1!A94,'JUN-21'!$A:$A,0),1,22,1))),0) -> 0 | D101: =IFERROR(SUM(SUMIF(OFFSET('JUN-21'!$A$1,MATCH(Sheet1!A94,'JUN-21'!$A:$A,0),0,22,1),{"DA*C","D. *"},OFFSET('JUN-21'!$A$1,MATCH(Sheet1!A94,'JUN-21'!$A:$A,0),1,22,1))),0) -> 0 | E101: =IFERROR(SUM(SUMIF(OFFSET('JUN-21'!$A$1,MATCH(Sheet1!A94,'JUN-21'!$A:$A,0),0,22,1),{"H. R. A."},OFFSET('JUN-21'!$A$1,MATCH(Sheet1!A94,'JUN-21'!$A:$A,0),1,22,1))),0) -> 0 | F101: {=IFERROR(SUM(SUMIF(OFFSET('JUN-21'!$A$1,MATCH(Sheet1!A94,'JUN-21'!$A:$A,0),0,22,1),{"SP*AY*","S D A*","O.A.*","CLA (5th Pay)*","REF. Allow*","Trans.Allw.*","LF*","P. O.*","ARM*","Conv.A*","Otr.Allow*","Trans_Arrear*","BMIA*","Incentives*","Fit Allow*","KMA","NON-*","U.*","ME*A","PG*","Per.Tra"},OFFSET('JUN-21'!$A$1,MATCH(Sheet1!A94,'JUN-21'!$A:$A,0),1,22,1))),0)} -> 0 | G101: =IFERROR(SUM(SUMIF(OFFSET('JUN-21'!$A$1,MATCH(Sheet1!A94,'JUN-21'!$A:$A,0),0,22,1),{"WA"},OFFSET('JUN-21'!$A$1,MATCH(Sheet1!A94,'JUN-21'!$A:$A,0),1,22,1))),0) -> 0 | H101: =IFERROR(SUM(SUMIF(OFFSET('JUN-21'!$A$1,MATCH(Sheet1!A94,'JUN-21'!$A:$A,0),0,22,1),{"DCPS","GROSS_ADJUST"},OFFSET('JUN-21'!$A$1,MATCH(Sheet1!A94,'JUN-21'!$A:$A,0),1,22,1))),0) -> 0 | I101: {=+IFERROR(SUM(SUMIF(OFFSET('JUN-21'!$A$1,MATCH(Sheet1!A94,'JUN-21'!$A:$A,0),0,22,1),{"Basic*Arr*","7th Pay* Arr*"},OFFSET('JUN-21'!$A$1,MATCH(Sheet1!A94,'JUN-21'!$A:$A,0),1,22,1))),0)} -> 0 | J101: =SUM(C101:I101) -> 0 | K101: =IFERROR(SUM(SUMIF(OFFSET('JUN-21'!$A$1,MATCH(Sheet1!A94,'JUN-21'!$A:$A,0),2,22,1),{"*Pro*ax*"},OFFSET('JUN-21'!$A$1,MATCH(Sheet1!A94,'JUN-21'!$A:$A,0),3,22,1))),0) -> 0 | L101: =IFERROR(SUM(SUMIF(OFFSET('JUN-21'!$A$1,MATCH(Sheet1!A94,'JUN-21'!$A:$A,0),2,22,1),{"GPF_G*","DCPS"},OFFSET('JUN-21'!$A$1,MATCH(Sheet1!A94,'JUN-21'!$A:$A,0),3,22,1))),0) -> 0 | M101: =IFERROR(SUM(SUMIF(OFFSET('JUN-21'!$A$1,MATCH(Sheet1!A94,'JUN-21'!$A:$A,0),2,22,1),{"*GIS","GIS*R"},OFFSET('JUN-21'!$A$1,MATCH(Sheet1!A94,'JUN-21'!$A:$A,0),3,22,1))),0) -> 0 | N101: =IFERROR(SUM(SUMIF(OFFSET('JUN-21'!$A$1,MATCH(Sheet1!A94,'JUN-21'!$A:$A,0),5,22,1),{"LI*1"},OFFSET('JUN-21'!$A$1,MATCH(Sheet1!A94,'JUN-21'!$A:$A,0),6,22,1))),0) -> 0 | O101: {=IFERROR(SUM(SUMIF(OFFSET('JUN-21'!$A$1,MATCH(Sheet1!A94,'JUN-21'!$A:$A,0),2,22,1),{"HB*USE","HB*INT"},OFFSET('JUN-21'!$A$1,MATCH(Sheet1!A94,'JUN-21'!$A:$A,0),3,22,1))),0)} -> 0 | P101: {=IFERROR(SUM(SUMIF(OFFSET('JUN-21'!$A$1,MATCH(Sheet1!A94,'JUN-21'!$A:$A,0),5,22,1),{"OTHE*1","CO.*1","OTHE*2","WEL*ND","BAN*1","CLU*ND","RD*1","LI*2","MIS*US","*TAINAN*","MCA*INT*","MAIN*NANCE*","*C M Relief Fund*","Co. Op. Hsg Soc.*","GPF_ADV*","Co. Op. Cr. Soc. 2*","DCPS DA","DCPS Pay","MCA Int"},OFFSET('JUN-21'!$A$1,MATCH(Sheet1!A94,'JUN-21'!$A:$A,0),6,22,1)))+SUM(SUMIF(OFFSET('JUN-21'!$A$1,MATCH(Sheet1!A94,'JUN-21'!$A:$A,0),2,22,1),{"MCA","COM*DV*","HB*ND","CO*SOC","HRR","SRV*H","ACC*CY","F.A","STAMP_REVENUE","*C M Relief Fund*","GPF_ADV*","Co. Op. Cr. Soc. 2*","DCPS DA","DCPS Pay","MCA Int"},OFFSET('JUN-21'!$A$1,MATCH(Sheet1!A94,'JUN-21'!$A:$A,0),3,22,1))),0)} -> 0 | Q101: =+J101-H101-K101-L101-M101-N101-O101-P101-R101 -> 0 | R101: {=IFERROR(SUM(SUMIF(OFFSET('JUN-21'!$A$1,MATCH(Sheet1!A94,'JUN-21'!$A:$A,0),2,22,1),{"*I. *ax*"},OFFSET('JUN-21'!$A$1,MATCH(Sheet1!A94,'JUN-21'!$A:$A,0),3,22,1))),0)} -> 0 | S101: {=+IFERROR(IF(OFFSET('JUN-21'!$B$1,MATCH(Sheet1!A94,'JUN-21'!B:B,0)-2,0,1,1)=Sheet1!J101,IF(MID(IFERROR(OFFSET('JUN-21'!$B$1,MATCH(Sheet1!A94,'JUN-21'!$B:$B,0)-1,-1,1,1),"GROSS ERROR"),11,FIND(" ",OFFSET('JUN-21'!$B$1,MATCH(Sheet1!A94,'JUN-21'!$B:$B,0)-1,-1,1,1),12)-11)-Q101=0,"","NET MISMATCH"),"GROSS MISMATCH"),"")} | BH101: =+G95 -> PAN | BI101: =+A94 | BJ101: {=IFERROR(OFFSET('JUN-21'!$B$1,MATCH(Sheet1!A94,'JUN-21'!$B:$B,0)+1,0,1,1),"")} | BK101: =+J101 -> 0 | BL101: =+R101 -> 0 | BM101: {=IFERROR(OFFSET('JUN-21'!$A$1,MATCH(Sheet1!A94,'JUN-21'!$A:$A,0)-2,0,1,1),"")}
A102: 5 | B102: 44378 | C102: =IFERROR(SUM(SUMIF(OFFSET('JUL-21'!$A$1,MATCH(Sheet1!A94,'JUL-21'!$A:$A,0),0,22,1),{"BA*C","BASIC??"},OFFSET('JUL-21'!$A$1,MATCH(Sheet1!A94,'JUL-21'!$A:$A,0),1,22,1))),0) -> 0 | D102: =IFERROR(SUM(SUMIF(OFFSET('JUL-21'!$A$1,MATCH(Sheet1!A94,'JUL-21'!$A:$A,0),0,22,1),{"DA*C","D. *"},OFFSET('JUL-21'!$A$1,MATCH(Sheet1!A94,'JUL-21'!$A:$A,0),1,22,1))),0) -> 0 | E102: =IFERROR(SUM(SUMIF(OFFSET('JUL-21'!$A$1,MATCH(Sheet1!A94,'JUL-21'!$A:$A,0),0,22,1),{"H. R. A."},OFFSET('JUL-21'!$A$1,MATCH(Sheet1!A94,'JUL-21'!$A:$A,0),1,22,1))),0) -> 0 | F102: {=IFERROR(SUM(SUMIF(OFFSET('JUL-21'!$A$1,MATCH(Sheet1!A94,'JUL-21'!$A:$A,0),0,22,1),{"SP*AY*","S D A*","O.A.*","CLA (5th Pay)*","REF. Allow*","Trans.Allw.*","LF*","P. O.*","ARM*","Conv.A*","Otr.Allow*","Trans_Arrear*","BMIA*","Incentives*","Fit Allow*","KMA","NON-*","U.*","ME*A","PG*","Per.Tra"},OFFSET('JUL-21'!$A$1,MATCH(Sheet1!A94,'JUL-21'!$A:$A,0),1,22,1))),0)} -> 0 | G102: =IFERROR(SUM(SUMIF(OFFSET('JUL-21'!$A$1,MATCH(Sheet1!A94,'JUL-21'!$A:$A,0),0,22,1),{"WA"},OFFSET('JUL-21'!$A$1,MATCH(Sheet1!A94,'JUL-21'!$A:$A,0),1,22,1))),0) -> 0 | H102: =IFERROR(SUM(SUMIF(OFFSET('JUL-21'!$A$1,MATCH(Sheet1!A94,'JUL-21'!$A:$A,0),0,22,1),{"DCPS","GROSS_ADJUST"},OFFSET('JUL-21'!$A$1,MATCH(Sheet1!A94,'JUL-21'!$A:$A,0),1,22,1))),0) -> 0 | I102: {=++IFERROR(SUM(SUMIF(OFFSET('JUL-21'!$A$1,MATCH(Sheet1!A94,'JUL-21'!$A:$A,0),0,22,1),{"Basic*Arr*","7th Pay* Arr*"},OFFSET('JUL-21'!$A$1,MATCH(Sheet1!A94,'JUL-21'!$A:$A,0),1,22,1))),0)} -> 0 | J102: =SUM(C102:I102) -> 0 | K102: =IFERROR(SUM(SUMIF(OFFSET('JUL-21'!$A$1,MATCH(Sheet1!A94,'JUL-21'!$A:$A,0),2,22,1),{"*Pro*ax*"},OFFSET('JUL-21'!$A$1,MATCH(Sheet1!A94,'JUL-21'!$A:$A,0),3,22,1))),0) -> 0 | L102: =IFERROR(SUM(SUMIF(OFFSET('JUL-21'!$A$1,MATCH(Sheet1!A94,'JUL-21'!$A:$A,0),2,22,1),{"GPF_G*","DCPS"},OFFSET('JUL-21'!$A$1,MATCH(Sheet1!A94,'JUL-21'!$A:$A,0),3,22,1))),0) -> 0 | M102: =IFERROR(SUM(SUMIF(OFFSET('JUL-21'!$A$1,MATCH(Sheet1!A94,'JUL-21'!$A:$A,0),2,22,1),{"*GIS","GIS*R"},OFFSET('JUL-21'!$A$1,MATCH(Sheet1!A94,'JUL-21'!$A:$A,0),3,22,1))),0) -> 0 | N102: =IFERROR(SUM(SUMIF(OFFSET('JUL-21'!$A$1,MATCH(Sheet1!A94,'JUL-21'!$A:$A,0),5,22,1),{"LI*1"},OFFSET('JUL-21'!$A$1,MATCH(Sheet1!A94,'JUL-21'!$A:$A,0),6,22,1))),0) -> 0 | O102: {=IFERROR(SUM(SUMIF(OFFSET('JUL-21'!$A$1,MATCH(Sheet1!A94,'JUL-21'!$A:$A,0),2,22,1),{"HB*USE","HB*INT"},OFFSET('JUL-21'!$A$1,MATCH(Sheet1!A94,'JUL-21'!$A:$A,0),3,22,1))),0)} -> 0 | P102: {=IFERROR(SUM(SUMIF(OFFSET('JUL-21'!$A$1,MATCH(Sheet1!A94,'JUL-21'!$A:$A,0),5,22,1),{"OTHE*1","CO.*1","OTHE*2","WEL*ND","BAN*1","CLU*ND","RD*1","LI*2","MIS*US","*TAINAN*","MCA*INT*","MAIN*NANCE*","*C M Relief Fund*","Co. Op. Hsg Soc.*","GPF_ADV*","Co. Op. Cr. Soc. 2*","DCPS DA","DCPS Pay","MCA Int"},OFFSET('JUL-21'!$A$1,MATCH(Sheet1!A94,'JUL-21'!$A:$A,0),6,22,1)))+SUM(SUMIF(OFFSET('JUL-21'!$A$1,MATCH(Sheet1!A94,'JUL-21'!$A:$A,0),2,22,1),{"MCA","COM*DV*","HB*ND","CO*SOC","HRR","SRV*H","ACC*CY","F.A","STAMP_REVENUE","*C M Relief Fund*","GPF_ADV*","Co. Op. Cr. Soc. 2*","DCPS DA","DCPS Pay","MCA Int"},OFFSET('JUL-21'!$A$1,MATCH(Sheet1!A94,'JUL-21'!$A:$A,0),3,22,1))),0)} -> 0 | Q102: =+J102-H102-K102-L102-M102-N102-O102-P102-R102 -> 0 | R102: =IFERROR(SUM(SUMIF(OFFSET('JUL-21'!$A$1,MATCH(Sheet1!A94,'JUL-21'!$A:$A,0),2,22,1),{"*I. *ax*"},OFFSET('JUL-21'!$A$1,MATCH(Sheet1!A94,'JUL-21'!$A:$A,0),3,22,1))),0) -> 0 | S102: {=+IFERROR(IF(OFFSET('JUL-21'!$B$1,MATCH(Sheet1!A94,'JUL-21'!B:B,0)-2,0,1,1)=Sheet1!J102,IF(MID(IFERROR(OFFSET('JUL-21'!$B$1,MATCH(Sheet1!A94,'JUL-21'!$B:$B,0)-1,-1,1,1),"GROSS ERROR"),11,FIND(" ",OFFSET('JUL-21'!$B$1,MATCH(Sheet1!A94,'JUL-21'!$B:$B,0)-1,-1,1,1),12)-11)-Q102=0,"","NET MISMATCH"),"GROSS MISMATCH"),"")} | BH102: =+G95 -> PAN | BI102: =+A94 | BJ102: {=+IFERROR(OFFSET('JUL-21'!$B$1,MATCH(Sheet1!A94,'JUL-21'!$B:$B,0)+1,0,1,1),"")} | BK102: =+J102 -> 0 | BL102: =+R102 -> 0 | BM102: {=IFERROR(OFFSET('JUL-21'!$A$1,MATCH(Sheet1!A94,'JUL-21'!$A:$A,0)-2,0,1,1),"")}
A103: 6 | B103: 44409 | C103: =IFERROR(SUM(SUMIF(OFFSET('AUG-21'!$A$1,MATCH(Sheet1!A94,'AUG-21'!$A:$A,0),0,22,1),{"BA*C","BASIC??"},OFFSET('AUG-21'!$A$1,MATCH(Sheet1!A94,'AUG-21'!$A:$A,0),1,22,1))),0) -> 0 | D103: =IFERROR(SUM(SUMIF(OFFSET('AUG-21'!$A$1,MATCH(Sheet1!A94,'AUG-21'!$A:$A,0),0,22,1),{"DA*C","D. *"},OFFSET('AUG-21'!$A$1,MATCH(Sheet1!A94,'AUG-21'!$A:$A,0),1,22,1))),0) -> 0 | E103: =IFERROR(SUM(SUMIF(OFFSET('AUG-21'!$A$1,MATCH(Sheet1!A94,'AUG-21'!$A:$A,0),0,22,1),{"H. R. A."},OFFSET('AUG-21'!$A$1,MATCH(Sheet1!A94,'AUG-21'!$A:$A,0),1,22,1))),0) -> 0 | F103: {=IFERROR(SUM(SUMIF(OFFSET('AUG-21'!$A$1,MATCH(Sheet1!A94,'AUG-21'!$A:$A,0),0,22,1),{"SP*AY*","S D A*","O.A.*","CLA (5th Pay)*","REF. Allow*","Trans.Allw.*","LF*","P. O.*","ARM*","Conv.A*","Otr.Allow*","Trans_Arrear*","BMIA*","Incentives*","Fit Allow*","KMA","NON-*","U.*","ME*A","PG*","Per.Tra"},OFFSET('AUG-21'!$A$1,MATCH(Sheet1!A94,'AUG-21'!$A:$A,0),1,22,1))),0)} -> 0 | G103: =IFERROR(SUM(SUMIF(OFFSET('AUG-21'!$A$1,MATCH(Sheet1!A94,'AUG-21'!$A:$A,0),0,22,1),{"WA"},OFFSET('AUG-21'!$A$1,MATCH(Sheet1!A94,'AUG-21'!$A:$A,0),1,22,1))),0) -> 0 | H103: =IFERROR(SUM(SUMIF(OFFSET('AUG-21'!$A$1,MATCH(Sheet1!A94,'AUG-21'!$A:$A,0),0,22,1),{"DCPS","GROSS_ADJUST"},OFFSET('AUG-21'!$A$1,MATCH(Sheet1!A94,'AUG-21'!$A:$A,0),1,22,1))),0) -> 0 | I103: {=+IFERROR(SUM(SUMIF(OFFSET('AUG-21'!$A$1,MATCH(Sheet1!A94,'AUG-21'!$A:$A,0),0,22,1),{"7th Pay* Arr*","Basic Arr*","DA Arr"},OFFSET('AUG-21'!$A$1,MATCH(Sheet1!A94,'AUG-21'!$A:$A,0),1,22,1))),0)} -> 0 | J103: =SUM(C103:I103) -> 0 | K103: =IFERROR(SUM(SUMIF(OFFSET('AUG-21'!$A$1,MATCH(Sheet1!A94,'AUG-21'!$A:$A,0),2,22,1),{"*Pro*ax*"},OFFSET('AUG-21'!$A$1,MATCH(Sheet1!A94,'AUG-21'!$A:$A,0),3,22,1))),0) -> 0 | L103: =IFERROR(SUM(SUMIF(OFFSET('AUG-21'!$A$1,MATCH(Sheet1!A94,'AUG-21'!$A:$A,0),2,22,1),{"GPF_G*","DCPS","*7thPay GP*"},OFFSET('AUG-21'!$A$1,MATCH(Sheet1!A94,'AUG-21'!$A:$A,0),3,22,1))),0) -> 0 | M103: =IFERROR(SUM(SUMIF(OFFSET('AUG-21'!$A$1,MATCH(Sheet1!A94,'AUG-21'!$A:$A,0),2,22,1),{"*GIS","GIS*R"},OFFSET('AUG-21'!$A$1,MATCH(Sheet1!A94,'AUG-21'!$A:$A,0),3,22,1))),0) -> 0 | N103: =IFERROR(SUM(SUMIF(OFFSET('AUG-21'!$A$1,MATCH(Sheet1!A94,'AUG-21'!$A:$A,0),5,22,1),{"LI*1"},OFFSET('AUG-21'!$A$1,MATCH(Sheet1!A94,'AUG-21'!$A:$A,0),6,22,1))),0) -> 0 | O103: {=IFERROR(SUM(SUMIF(OFFSET('AUG-21'!$A$1,MATCH(Sheet1!A94,'AUG-21'!$A:$A,0),2,22,1),{"HB*USE","HB*INT"},OFFSET('AUG-21'!$A$1,MATCH(Sheet1!A94,'AUG-21'!$A:$A,0),3,22,1))),0)} -> 0 | P103: {=IFERROR(SUM(SUMIF(OFFSET('AUG-21'!$A$1,MATCH(Sheet1!A94,'AUG-21'!$A:$A,0),5,22,1),{"OTHE*1","CO.*1","OTHE*2","WEL*ND","BAN*1","CLU*ND","RD*1","LI*2","MIS*US","*TAINAN*","MCA*INT*","MAIN*NANCE*","*C M Relief Fund*","Co. Op. Hsg Soc.*","GPF_ADV*","Co. Op. Cr. Soc. 2*","DCPS DA","DCPS Pay","MCA Int"},OFFSET('AUG-21'!$A$1,MATCH(Sheet1!A94,'AUG-21'!$A:$A,0),6,22,1)))+SUM(SUMIF(OFFSET('AUG-21'!$A$1,MATCH(Sheet1!A94,'AUG-21'!$A:$A,0),2,22,1),{"MCA","COM*DV*","HB*ND","CO*SOC","HRR","SRV*H","ACC*CY","F.A","STAMP_REVENUE","*C M Relief Fund*","GPF_ADV*","Co. Op. Cr. Soc. 2*","DCPS DA","DCPS Pay","MCA Int"},OFFSET('AUG-21'!$A$1,MATCH(Sheet1!A94,'AUG-21'!$A:$A,0),3,22,1))),0)} -> 0 | Q103: =+J103-H103-K103-L103-M103-N103-O103-P103-R103 -> 0 | R103: {=IFERROR(SUM(SUMIF(OFFSET('AUG-21'!$A$1,MATCH(Sheet1!A94,'AUG-21'!$A:$A,0),2,22,1),{"*I. *ax*"},OFFSET('AUG-21'!$A$1,MATCH(Sheet1!A94,'AUG-21'!$A:$A,0),3,22,1))),0)} -> 0 | S103: {=+IFERROR(IF(OFFSET('AUG-21'!$B$1,MATCH(Sheet1!A94,'AUG-21'!B:B,0)-2,0,1,1)=Sheet1!J103,IF(MID(IFERROR(OFFSET('AUG-21'!$B$1,MATCH(Sheet1!A94,'AUG-21'!$B:$B,0)-1,-1,1,1),"GROSS ERROR"),11,FIND(" ",OFFSET('AUG-21'!$B$1,MATCH(Sheet1!A94,'AUG-21'!$B:$B,0)-1,-1,1,1),12)-11)-Q103=0,"","NET MISMATCH"),"GROSS MISMATCH"),"")} | BH103: =+G95 -> PAN | BI103: =+A94 | BJ103: {=IFERROR(OFFSET('AUG-21'!$B$1,MATCH(Sheet1!A94,'AUG-21'!$B:$B,0)+1,0,1,1),"")} | BK103: =+J103 -> 0 | BL103: =+R103 -> 0 | BM103: {=IFERROR(OFFSET('AUG-21'!$A$1,MATCH(Sheet1!A94,'AUG-21'!$A:$A,0)-2,0,1,1),"")}
...

Sheet MAR-21
A1: PaySlip

Sheet APR-21
A1: PaySlip

Sheet MAY-21
A1: PaySlip

Sheet JUN-21
A1: PaySlip

Sheet JUL-21
A1: PaySlip

Sheet AUG-21
A1: PaySlip

Sheet SEP-21

Sheet OCT-21

Sheet NOV-21

Sheet DEC-21

Sheet JAN-22

Sheet FEB-22

Sheet SUPP

Sheet EMP NAMES
A1: MONTH | B1: ALL NAMES | C1: ALL PAN | D1: UNIQUE NAMES
A2: 44256 | D2: {=IFERROR(INDEX(B2:B24,MATCH(0,COUNTIF($D$1:D1,B2:B24),0)),"")} -> 0 | E2: =+INDEX($B$2:$C$1500,MATCH(D2,$B$2:$B$1500,0),2) -> #N/A
A3: 44256 | D3: {=IFERROR(INDEX(B3:B25,MATCH(0,COUNTIF($D$1:D2,B3:B25),0)),"")} | E3: =+INDEX($B$2:$C$1500,MATCH(D3,$B$2:$B$1500,0),2) -> #N/A
A4: 44256 | D4: {=IFERROR(INDEX(B4:B26,MATCH(0,COUNTIF($D$1:D3,B4:B26),0)),"")} | E4: =+INDEX($B$2:$C$1500,MATCH(D4,$B$2:$B$1500,0),2) -> #N/A
A5: 44256 | D5: {=IFERROR(INDEX(B5:B27,MATCH(0,COUNTIF($D$1:D4,B5:B27),0)),"")} | E5: =+INDEX($B$2:$C$1500,MATCH(D5,$B$2:$B$1500,0),2) -> #N/A
A6: 44256 | D6: {=IFERROR(INDEX(B6:B28,MATCH(0,COUNTIF($D$1:D5,B6:B28),0)),"")} | E6: =+INDEX($B$2:$C$1500,MATCH(D6,$B$2:$B$1500,0),2) -> #N/A
A7: 44256 | D7: {=IFERROR(INDEX(B7:B29,MATCH(0,COUNTIF($D$1:D6,B7:B29),0)),"")} | E7: =+INDEX($B$2:$C$1500,MATCH(D7,$B$2:$B$1500,0),2) -> #N/A
A8: 44256 | D8: {=IFERROR(INDEX(B8:B30,MATCH(0,COUNTIF($D$1:D7,B8:B30),0)),"")} | E8: =+INDEX($B$2:$C$1500,MATCH(D8,$B$2:$B$1500,0),2) -> #N/A
A9: 44256 | D9: {=IFERROR(INDEX(B9:B31,MATCH(0,COUNTIF($D$1:D8,B9:B31),0)),"")} | E9: =+INDEX($B$2:$C$1500,MATCH(D9,$B$2:$B$1500,0),2) -> #N/A
A10: 44256 | D10: {=IFERROR(INDEX(B10:B32,MATCH(0,COUNTIF($D$1:D9,B10:B32),0)),"")} | E10: =+INDEX($B$2:$C$1500,MATCH(D10,$B$2:$B$1500,0),2) -> #N/A
D11: {=IFERROR(INDEX(B11:B33,MATCH(0,COUNTIF($D$1:D10,B11:B33),0)),"")} | E11: =+INDEX($B$2:$C$1500,MATCH(D11,$B$2:$B$1500,0),2) -> #N/A
D12: {=IFERROR(INDEX(B12:B34,MATCH(0,COUNTIF($D$1:D11,B12:B34),0)),"")} | E12: =+INDEX($B$2:$C$1500,MATCH(D12,$B$2:$B$1500,0),2) -> #N/A
D13: {=IFERROR(INDEX(B13:B35,MATCH(0,COUNTIF($D$1:D12,B13:B35),0)),"")} | E13: =+INDEX($B$2:$C$1500,MATCH(D13,$B$2:$B$1500,0),2) -> #N/A
D14: {=IFERROR(INDEX(B14:B36,MATCH(0,COUNTIF($D$1:D13,B14:B36),0)),"")} | E14: =+INDEX($B$2:$C$1500,MATCH(D14,$B$2:$B$1500,0),2) -> #N/A
D15: {=IFERROR(INDEX(B15:B37,MATCH(0,COUNTIF($D$1:D14,B15:B37),0)),"")} | E15: =+INDEX($B$2:$C$1500,MATCH(D15,$B$2:$B$1500,0),2) -> #N/A
D16: {=IFERROR(INDEX(B16:B38,MATCH(0,COUNTIF($D$1:D15,B16:B38),0)),"")} | E16: =+INDEX($B$2:$C$1500,MATCH(D16,$B$2:$B$1500,0),2) -> #N/A
D17: {=IFERROR(INDEX(B17:B39,MATCH(0,COUNTIF($D$1:D16,B17:B39),0)),"")} | E17: =+INDEX($B$2:$C$1500,MATCH(D17,$B$2:$B$1500,0),2) -> #N/A
D18: {=IFERROR(INDEX(B18:B40,MATCH(0,COUNTIF($D$1:D17,B18:B40),0)),"")} | E18: =+INDEX($B$2:$C$1500,MATCH(D18,$B$2:$B$1500,0),2) -> #N/A
D19: {=IFERROR(INDEX(B19:B41,MATCH(0,COUNTIF($D$1:D18,B19:B41),0)),"")} | E19: =+INDEX($B$2:$C$1500,MATCH(D19,$B$2:$B$1500,0),2) -> #N/A
D20: {=IFERROR(INDEX(B20:B42,MATCH(0,COUNTIF($D$1:D19,B20:B42),0)),"")} | E20: =+INDEX($B$2:$C$1500,MATCH(D20,$B$2:$B$1500,0),2) -> #N/A
D21: {=IFERROR(INDEX(B21:B43,MATCH(0,COUNTIF($D$1:D20,B21:B43),0)),"")} | E21: =+INDEX($B$2:$C$1500,MATCH(D21,$B$2:$B$1500,0),2) -> #N/A
D22: {=IFERROR(INDEX(B22:B44,MATCH(0,COUNTIF($D$1:D21,B22:B44),0)),"")} | E22: =+INDEX($B$2:$C$1500,MATCH(D22,$B$2:$B$1500,0),2) -> #N/A
... D300: {=IFERROR(INDEX(B300:B322,MATCH(0,COUNTIF($D$1:D299,B300:B322),0)),"")} | E300: =+INDEX($B$2:$C$1500,MATCH(D300,$B$2:$B$1500,0),2) -> #N/A
